Workbook
Name HR: HR!$N$1
Name Monitoring: Monitoring!$A$1
Name SAP: 'SAP Report'!$A$1

Sheet Summary
B2: Board Approved vs Allotted
B3: (without Special Projects)
B4: SBU | C4: ORIGINAL BOARD APPROVED | D4: ADDITIONAL/ REDUCTION | E4: TOTAL BOARD APPROVED | F4: ACTUAL | G4: COMMITTED (open PR PO) | H4: ALLOTTED | J4: REMAINING1 (vs Allotted) | L4: REMAINING2 (vs Actual) | N4: Jan | O4: Feb | P4: Mar | Q4: Apr | R4: May | S4: Jun | T4: Jul | U4: Aug | V4: Sep | W4: Oct | X4: Nov | Y4: Dec | Z4: 2026 FORECAST | AA4: BALANCE
H5: PHP | I5: % | J5: PHP | K5: % | L5: PHP | M5: % | AA5: PHP | AB5: %
C6: A | D6: B | E6: C = A+B | F6: D | G6: E | H6: F = D+E | I6: G = F/C | J6: H = C-F | K6: I = H/C | L6: M = C-D | M6: N = M/C | Z6: J | AA6: K = C-J | AB6: L = K/C
B7: CORPORATE - HR | C7: 19700000 | E7: =C7+D7 -> 19700000 | F7: =SUMIFS(Monitoring!$AA:$AA,Monitoring!$D:$D,$B7,Monitoring!$F:$F,"N") -> 9832978.6 | G7: =SUMIFS(Monitoring!$AB:$AB,Monitoring!$D:$D,$B7,Monitoring!$F:$F,"N") -> 2203571.4 | H7: =SUM(F7:G7) -> 12036550 | I7: =H7/E7 -> 0.61099239 | J7: =E7-H7 -> 7663450 | K7: =J7/E7 -> 0.38900761 | L7: =E7-F7 -> 9867021.4 | M7: =L7/E7 -> 0.50086403 | N7: =SUMIFS(Monitoring!AG:AG,Monitoring!$D:$D,$B7,Monitoring!$F:$F,"N") -> 0 | O7: =SUMIFS(Monitoring!AH:AH,Monitoring!$D:$D,$B7,Monitoring!$F:$F,"N") -> 1828571.4 | P7: =SUMIFS(Monitoring!AI:AI,Monitoring!$D:$D,$B7,Monitoring!$F:$F,"N") -> 0 | Q7: =SUMIFS(Monitoring!AJ:AJ,Monitoring!$D:$D,$B7,Monitoring!$F:$F,"N") -> 0 | R7: =SUMIFS(Monitoring!AK:AK,Monitoring!$D:$D,$B7,Monitoring!$F:$F,"N") -> 1756428.6 | S7: =SUMIFS(Monitoring!AL:AL,Monitoring!$D:$D,$B7,Monitoring!$F:$F,"N") -> 2803335.7 | T7: =SUMIFS(Monitoring!AM:AM,Monitoring!$D:$D,$B7,Monitoring!$F:$F,"N") -> 775000 | U7: =SUMIFS(Monitoring!AN:AN,Monitoring!$D:$D,$B7,Monitoring!$F:$F,"N") -> 2669642.9 | V7: =SUMIFS(Monitoring!AO:AO,Monitoring!$D:$D,$B7,Monitoring!$F:$F,"N") -> 0 | W7: =SUMIFS(Monitoring!AP:AP,Monitoring!$D:$D,$B7,Monitoring!$F:$F,"N") -> 2203571.4 | X7: =SUMIFS(Monitoring!AQ:AQ,Monitoring!$D:$D,$B7,Monitoring!$F:$F,"N") -> 452232.58 | Y7: =SUMIFS(Monitoring!AR:AR,Monitoring!$D:$D,$B7,Monitoring!$F:$F,"N") -> 452232.58 | Z7: =SUM(N7:Y7) -> 12941015 | AA7: =E7-Z7 -> 6758984.8 | AB7: =AA7/E7 -> 0.34309568
B8: CORPORATE - IT | C8: 31000000 | E8: =C8+D8 -> 31000000 | F8: =SUMIFS(Monitoring!$AA:$AA,Monitoring!$D:$D,$B8,Monitoring!$F:$F,"N") -> 16165522 | G8: =SUMIFS(Monitoring!$AB:$AB,Monitoring!$D:$D,$B8,Monitoring!$F:$F,"N") -> 1562946.4 | H8: =SUM(F8:G8) -> 17728469 | I8: =H8/E8 -> 0.57188609 | J8: =E8-H8 -> 13271531 | K8: =J8/E8 -> 0.42811391 | L8: =E8-F8 -> 14834478 | M8: =L8/E8 -> 0.47853154 | N8: =SUMIFS(Monitoring!AG:AG,Monitoring!$D:$D,$B8,Monitoring!$F:$F,"N") -> 350000 | O8: =SUMIFS(Monitoring!AH:AH,Monitoring!$D:$D,$B8,Monitoring!$F:$F,"N") -> 0 | P8: =SUMIFS(Monitoring!AI:AI,Monitoring!$D:$D,$B8,Monitoring!$F:$F,"N") -> 0 | Q8: =SUMIFS(Monitoring!AJ:AJ,Monitoring!$D:$D,$B8,Monitoring!$F:$F,"N") -> 128571.43 | R8: =SUMIFS(Monitoring!AK:AK,Monitoring!$D:$D,$B8,Monitoring!$F:$F,"N") -> 13953571 | S8: =SUMIFS(Monitoring!AL:AL,Monitoring!$D:$D,$B8,Monitoring!$F:$F,"N") -> 0 | T8: =SUMIFS(Monitoring!AM:AM,Monitoring!$D:$D,$B8,Monitoring!$F:$F,"N") -> 0 | U8: =SUMIFS(Monitoring!AN:AN,Monitoring!$D:$D,$B8,Monitoring!$F:$F,"N") -> 424107.15 | V8: =SUMIFS(Monitoring!AO:AO,Monitoring!$D:$D,$B8,Monitoring!$F:$F,"N") -> 1309272.3 | W8: =SUMIFS(Monitoring!AP:AP,Monitoring!$D:$D,$B8,Monitoring!$F:$F,"N") -> 1562946.4 | X8: =SUMIFS(Monitoring!AQ:AQ,Monitoring!$D:$D,$B8,Monitoring!$F:$F,"N") -> 596617.46 | Y8: =SUMIFS(Monitoring!AR:AR,Monitoring!$D:$D,$B8,Monitoring!$F:$F,"N") -> 596617.46 | Z8: =SUM(N8:Y8) -> 18921704 | AA8: =E8-Z8 -> 12078296 | AB8: =AA8/E8 -> 0.38962246 | AC8: 1.6M upcoming laptops
B9: CORPORATE - ADMIN | C9: 2337486 | E9: =C9+D9 -> 2337486 | F9: =SUMIFS(Monitoring!$AA:$AA,Monitoring!$D:$D,$B9,Monitoring!$F:$F,"N") -> 138392.86 | G9: =SUMIFS(Monitoring!$AB:$AB,Monitoring!$D:$D,$B9,Monitoring!$F:$F,"N") -> 0 | H9: =SUM(F9:G9) -> 138392.86 | I9: =H9/E9 -> 0.059205856 | J9: =E9-H9 -> 2199093.1 | K9: =J9/E9 -> 0.94079414 | L9: =E9-F9 -> 2199093.1 | M9: =L9/E9 -> 0.94079414 | N9: =SUMIFS(Monitoring!AG:AG,Monitoring!$D:$D,$B9,Monitoring!$F:$F,"N") -> 0 | O9: =SUMIFS(Monitoring!AH:AH,Monitoring!$D:$D,$B9,Monitoring!$F:$F,"N") -> 138392.86 | P9: =SUMIFS(Monitoring!AI:AI,Monitoring!$D:$D,$B9,Monitoring!$F:$F,"N") -> 0 | Q9: =SUMIFS(Monitoring!AJ:AJ,Monitoring!$D:$D,$B9,Monitoring!$F:$F,"N") -> 0 | R9: =SUMIFS(Monitoring!AK:AK,Monitoring!$D:$D,$B9,Monitoring!$F:$F,"N") -> 0 | S9: =SUMIFS(Monitoring!AL:AL,Monitoring!$D:$D,$B9,Monitoring!$F:$F,"N") -> 0 | T9: =SUMIFS(Monitoring!AM:AM,Monitoring!$D:$D,$B9,Monitoring!$F:$F,"N") -> 0 | U9: =SUMIFS(Monitoring!AN:AN,Monitoring!$D:$D,$B9,Monitoring!$F:$F,"N") -> 0 | V9: =SUMIFS(Monitoring!AO:AO,Monitoring!$D:$D,$B9,Monitoring!$F:$F,"N") -> 0 | W9: =SUMIFS(Monitoring!AP:AP,Monitoring!$D:$D,$B9,Monitoring!$F:$F,"N") -> 0 | X9: =SUMIFS(Monitoring!AQ:AQ,Monitoring!$D:$D,$B9,Monitoring!$F:$F,"N") -> 0 | Y9: =SUMIFS(Monitoring!AR:AR,Monitoring!$D:$D,$B9,Monitoring!$F:$F,"N") -> 0 | Z9: =SUM(N9:Y9) -> 138392.86 | AA9: =E9-Z9 -> 2199093.1 | AB9: =AA9/E9 -> 0.94079414
B10: ESTATES | C10: 60000000 | E10: =C10+D10 -> 60000000 | F10: =SUMIFS(Monitoring!$AA:$AA,Monitoring!$D:$D,$B10,Monitoring!$F:$F,"N") -> 10913929 | G10: =SUMIFS(Monitoring!$AB:$AB,Monitoring!$D:$D,$B10,Monitoring!$F:$F,"N") -> 35518593 | H10: =SUM(F10:G10) -> 46432522 | I10: =H10/E10 -> 0.77387536 | J10: =E10-H10 -> 13567478 | K10: =J10/E10 -> 0.22612464 | L10: =E10-F10 -> 49086071 | M10: =L10/E10 -> 0.81810119 | N10: =SUMIFS(Monitoring!AG:AG,Monitoring!$D:$D,$B10,Monitoring!$F:$F,"N") -> 0 | O10: =SUMIFS(Monitoring!AH:AH,Monitoring!$D:$D,$B10,Monitoring!$F:$F,"N") -> 0 | P10: =SUMIFS(Monitoring!AI:AI,Monitoring!$D:$D,$B10,Monitoring!$F:$F,"N") -> 0 | Q10: =SUMIFS(Monitoring!AJ:AJ,Monitoring!$D:$D,$B10,Monitoring!$F:$F,"N") -> 982142.86 | R10: =SUMIFS(Monitoring!AK:AK,Monitoring!$D:$D,$B10,Monitoring!$F:$F,"N") -> 7096071.4 | S10: =SUMIFS(Monitoring!AL:AL,Monitoring!$D:$D,$B10,Monitoring!$F:$F,"N") -> 1517857.1 | T10: =SUMIFS(Monitoring!AM:AM,Monitoring!$D:$D,$B10,Monitoring!$F:$F,"N") -> -83928.57 | U10: =SUMIFS(Monitoring!AN:AN,Monitoring!$D:$D,$B10,Monitoring!$F:$F,"N") -> 0 | V10: =SUMIFS(Monitoring!AO:AO,Monitoring!$D:$D,$B10,Monitoring!$F:$F,"N") -> 1401785.7 | W10: =SUMIFS(Monitoring!AP:AP,Monitoring!$D:$D,$B10,Monitoring!$F:$F,"N") -> 35518593 | X10: =SUMIFS(Monitoring!AQ:AQ,Monitoring!$D:$D,$B10,Monitoring!$F:$F,"N") -> 3262664.8 | Y10: =SUMIFS(Monitoring!AR:AR,Monitoring!$D:$D,$B10,Monitoring!$F:$F,"N") -> 3262664.8 | Z10: =SUM(N10:Y10) -> 52957851 | AA10: =E10-Z10 -> 7042148.7 | AB10: =AA10/E10 -> 0.11736915
B11: MALLS | C11: =Malls!$G$1 -> 1.1320605e+08 | E11: =C11+D11 -> 1.1320605e+08 | F11: =SUMIFS(Monitoring!$AA:$AA,Monitoring!$D:$D,$B11,Monitoring!$F:$F,"N") -> 27138755 | G11: =SUMIFS(Monitoring!$AB:$AB,Monitoring!$D:$D,$B11,Monitoring!$F:$F,"N") -> 55946400 | H11: =SUM(F11:G11) -> 83085155 | I11: =H11/E11 -> 0.73392856 | J11: =E11-H11 -> 30120898 | K11: =J11/E11 -> 0.26607144 | L11: =E11-F11 -> 86067298 | M11: =L11/E11 -> 0.76027117 | N11: =SUMIFS(Monitoring!AG:AG,Monitoring!$D:$D,$B11,Monitoring!$F:$F,"N") -> 303160.72 | O11: =SUMIFS(Monitoring!AH:AH,Monitoring!$D:$D,$B11,Monitoring!$F:$F,"N") -> 192133.92 | P11: =SUMIFS(Monitoring!AI:AI,Monitoring!$D:$D,$B11,Monitoring!$F:$F,"N") -> 4099106 | Q11: =SUMIFS(Monitoring!AJ:AJ,Monitoring!$D:$D,$B11,Monitoring!$F:$F,"N") -> 5106499.9 | R11: =SUMIFS(Monitoring!AK:AK,Monitoring!$D:$D,$B11,Monitoring!$F:$F,"N") -> 1056861 | S11: =SUMIFS(Monitoring!AL:AL,Monitoring!$D:$D,$B11,Monitoring!$F:$F,"N") -> 1758947.2 | T11: =SUMIFS(Monitoring!AM:AM,Monitoring!$D:$D,$B11,Monitoring!$F:$F,"N") -> 4291527.3 | U11: =SUMIFS(Monitoring!AN:AN,Monitoring!$D:$D,$B11,Monitoring!$F:$F,"N") -> 8630965.4 | V11: =SUMIFS(Monitoring!AO:AO,Monitoring!$D:$D,$B11,Monitoring!$F:$F,"N") -> 1699553.6 | W11: =SUMIFS(Monitoring!AP:AP,Monitoring!$D:$D,$B11,Monitoring!$F:$F,"N") -> 55946400 | X11: =SUMIFS(Monitoring!AQ:AQ,Monitoring!$D:$D,$B11,Monitoring!$F:$F,"N") -> 26185449 | Y11: =SUMIFS(Monitoring!AR:AR,Monitoring!$D:$D,$B11,Monitoring!$F:$F,"N") -> 26185449 | Z11: =SUM(N11:Y11) -> 1.3545605e+08 | AA11: =E11-Z11 -> -22250000 | AB11: =AA11/E11 -> -0.19654426
B12: OFFICES | C12: 67300000 | E12: =C12+D12 -> 67300000 | F12: =SUMIFS(Monitoring!$AA:$AA,Monitoring!$D:$D,$B12,Monitoring!$F:$F,"N") -> 33367018 | G12: =SUMIFS(Monitoring!$AB:$AB,Monitoring!$D:$D,$B12,Monitoring!$F:$F,"N") -> 20169252 | H12: =SUM(F12:G12) -> 53536270 | I12: =H12/E12 -> 0.79548692 | J12: =E12-H12 -> 13763730 | K12: =J12/E12 -> 0.20451308 | L12: =E12-F12 -> 33932982 | M12: =L12/E12 -> 0.50420479 | N12: =SUMIFS(Monitoring!AG:AG,Monitoring!$D:$D,$B12,Monitoring!$F:$F,"N") -> 0 | O12: =SUMIFS(Monitoring!AH:AH,Monitoring!$D:$D,$B12,Monitoring!$F:$F,"N") -> 3563196.5 | P12: =SUMIFS(Monitoring!AI:AI,Monitoring!$D:$D,$B12,Monitoring!$F:$F,"N") -> 6383928.6 | Q12: =SUMIFS(Monitoring!AJ:AJ,Monitoring!$D:$D,$B12,Monitoring!$F:$F,"N") -> 9682285.7 | R12: =SUMIFS(Monitoring!AK:AK,Monitoring!$D:$D,$B12,Monitoring!$F:$F,"N") -> 410714.29 | S12: =SUMIFS(Monitoring!AL:AL,Monitoring!$D:$D,$B12,Monitoring!$F:$F,"N") -> 7600107.2 | T12: =SUMIFS(Monitoring!AM:AM,Monitoring!$D:$D,$B12,Monitoring!$F:$F,"N") -> 403571.43 | U12: =SUMIFS(Monitoring!AN:AN,Monitoring!$D:$D,$B12,Monitoring!$F:$F,"N") -> 1707142.9 | V12: =SUMIFS(Monitoring!AO:AO,Monitoring!$D:$D,$B12,Monitoring!$F:$F,"N") -> 3616071.4 | W12: =SUMIFS(Monitoring!AP:AP,Monitoring!$D:$D,$B12,Monitoring!$F:$F,"N") -> 20169252 | X12: =SUMIFS(Monitoring!AQ:AQ,Monitoring!$D:$D,$B12,Monitoring!$F:$F,"N") -> 6881865.1 | Y12: =SUMIFS(Monitoring!AR:AR,Monitoring!$D:$D,$B12,Monitoring!$F:$F,"N") -> 6881865.1 | Z12: =SUM(N12:Y12) -> 67300000 | AA12: =E12-Z12 -> 0.004285723 | AB12: =AA12/E12 -> 6.3680876e-11
B13: RESIDENTIAL | C13: 50000000 | E13: =C13+D13 -> 50000000 | F13: =SUMIFS(Monitoring!$AA:$AA,Monitoring!$D:$D,$B13,Monitoring!$F:$F,"N") -> 8244582.9 | G13: =SUMIFS(Monitoring!$AB:$AB,Monitoring!$D:$D,$B13,Monitoring!$F:$F,"N") -> 3777253.7 | H13: =SUM(F13:G13) -> 12021837 | I13: =H13/E13 -> 0.24043673 | J13: =E13-H13 -> 37978163 | K13: =J13/E13 -> 0.75956327 | L13: =E13-F13 -> 41755417 | M13: =L13/E13 -> 0.83510834 | N13: =SUMIFS(Monitoring!AG:AG,Monitoring!$D:$D,$B13,Monitoring!$F:$F,"N") -> 276196.43 | O13: =SUMIFS(Monitoring!AH:AH,Monitoring!$D:$D,$B13,Monitoring!$F:$F,"N") -> 6428571.4 | P13: =SUMIFS(Monitoring!AI:AI,Monitoring!$D:$D,$B13,Monitoring!$F:$F,"N") -> 12767.85 | Q13: =SUMIFS(Monitoring!AJ:AJ,Monitoring!$D:$D,$B13,Monitoring!$F:$F,"N") -> -9.3132257e-10 | R13: =SUMIFS(Monitoring!AK:AK,Monitoring!$D:$D,$B13,Monitoring!$F:$F,"N") -> 70526.79 | S13: =SUMIFS(Monitoring!AL:AL,Monitoring!$D:$D,$B13,Monitoring!$F:$F,"N") -> 1192187.5 | T13: =SUMIFS(Monitoring!AM:AM,Monitoring!$D:$D,$B13,Monitoring!$F:$F,"N") -> 62500 | U13: =SUMIFS(Monitoring!AN:AN,Monitoring!$D:$D,$B13,Monitoring!$F:$F,"N") -> 201832.86 | V13: =SUMIFS(Monitoring!AO:AO,Monitoring!$D:$D,$B13,Monitoring!$F:$F,"N") -> 0 | W13: =SUMIFS(Monitoring!AP:AP,Monitoring!$D:$D,$B13,Monitoring!$F:$F,"N") -> 3777253.7 | X13: =SUMIFS(Monitoring!AQ:AQ,Monitoring!$D:$D,$B13,Monitoring!$F:$F,"N") -> 1036030.5 | Y13: =SUMIFS(Monitoring!AR:AR,Monitoring!$D:$D,$B13,Monitoring!$F:$F,"N") -> 1036030.5 | Z13: =SUM(N13:Y13) -> 14093898 | AA13: =E13-Z13 -> 35906102 | AB13: =AA13/E13 -> 0.71812205
B14: TOTAL | C14: =SUM(C7:C13) -> 3.4354354e+08 | D14: =SUM(D7:D13) -> 0 | E14: =SUM(E7:E13) -> 3.4354354e+08 | F14: =SUM(F7:F13) -> 1.0580118e+08 | G14: =SUM(G7:G13) -> 1.1917802e+08 | H14: =SUM(H7:H13) -> 2.2497919e+08 | I14: =H14/E14 -> 0.65487826 | J14: =SUM(J7:J13) -> 1.1856434e+08 | K14: =J14/E14 -> 0.34512174 | L14: =SUM(L7:L13) -> 2.3774236e+08 | M14: =L14/E14 -> 0.69202978 | N14: =SUM(N7:N13) -> 929357.15 | O14: =SUM(O7:O13) -> 12150866 | P14: =SUM(P7:P13) -> 10495802 | Q14: =SUM(Q7:Q13) -> 15899500 | R14: =SUM(R7:R13) -> 24344173 | S14: =SUM(S7:S13) -> 14872435 | T14: =SUM(T7:T13) -> 5448670.1 | U14: =SUM(U7:U13) -> 13633691 | ... AA14: =SUM(AA7:AA13) -> 41734625 | AB14: =AA14/E14 -> 0.12148278
F15: =F14-SUMIF(Monitoring!$F:$F,"N",Monitoring!AA:AA) -> 0 | G15: =G14-SUMIF(Monitoring!$F:$F,"N",Monitoring!AB:AB) -> 0 | H15: =H14-SUMIF(Monitoring!$F:$F,"N",Monitoring!AC:AC) -> 0 | N15: =N14-SUMIF(Monitoring!$F:$F,"N",Monitoring!AG:AG) -> 0 | O15: =O14-SUMIF(Monitoring!$F:$F,"N",Monitoring!AH:AH) -> 0 | P15: =P14-SUMIF(Monitoring!$F:$F,"N",Monitoring!AI:AI) -> 0 | Q15: =Q14-SUMIF(Monitoring!$F:$F,"N",Monitoring!AJ:AJ) -> 0 | R15: =R14-SUMIF(Monitoring!$F:$F,"N",Monitoring!AK:AK) -> 0 | S15: =S14-SUMIF(Monitoring!$F:$F,"N",Monitoring!AL:AL) -> 0 | T15: =T14-SUMIF(Monitoring!$F:$F,"N",Monitoring!AM:AM) -> 0 | U15: =U14-SUMIF(Monitoring!$F:$F,"N",Monitoring!AN:AN) -> 0 | V15: =V14-SUMIF(Monitoring!$F:$F,"N",Monitoring!AO:AO) -> 0 | W15: =W14-SUMIF(Monitoring!$F:$F,"N",Monitoring!AP:AP) -> 0 | X15: =X14-SUMIF(Monitoring!$F:$F,"N",Monitoring!AQ:AQ) -> 0 | Y15: =Y14-SUMIF(Monitoring!$F:$F,"N",Monitoring!AR:AR) -> 0 | Z15: =Z14-SUMIF(Monitoring!$F:$F,"N",Monitoring!AS:AS) -> 0
B16: Board Approved vs SAP IO
B17: (without Special Projects)
B18: SBU | C18: ORIGINAL BOARD APPROVED | D18: ADDITIONAL/ REDUCTION | E18: TOTAL BOARD APPROVED | F18: SAP IO | H18: REMAINING
F19: PHP | G19: % | H19: PHP | I19: %
C20: A | D20: B | E20: C = A+B | F20: D | G20: E = D/C | H20: F = C-D | I20: G = F/C
B21: CORPORATE - HR | C21: 19700000 | E21: =C21+D21 -> 19700000 | F21: =SUMIFS(Monitoring!R:R,Monitoring!D:D,Summary!B21,Monitoring!F:F,"N") -> 13721451 | G21: =F21/E21 -> 0.69652035 | H21: =E21-F21 -> 5978549.1 | I21: =H21/E21 -> 0.30347965
B22: CORPORATE - IT | C22: 31000000 | E22: =C22+D22 -> 31000000 | F22: =SUMIFS(Monitoring!R:R,Monitoring!D:D,Summary!B22,Monitoring!F:F,"N") -> 18921704 | G22: =F22/E22 -> 0.61037754 | H22: =E22-F22 -> 12078296 | I22: =H22/E22 -> 0.38962246
B23: CORPORATE - ADMIN | C23: 2337486 | E23: =C23+D23 -> 2337486 | F23: =SUMIFS(Monitoring!R:R,Monitoring!D:D,Summary!B23,Monitoring!F:F,"N") -> 138392.86 | G23: =F23/E23 -> 0.059205856 | H23: =E23-F23 -> 2199093.1 | I23: =H23/E23 -> 0.94079414
B24: ESTATES | C24: 60000000 | E24: =C24+D24 -> 60000000 | F24: =SUMIFS(Monitoring!R:R,Monitoring!D:D,Summary!B24,Monitoring!F:F,"N") -> 52957851 | G24: =F24/E24 -> 0.88263085 | H24: =E24-F24 -> 7042148.7 | I24: =H24/E24 -> 0.11736915
B25: MALLS | C25: =Malls!$G$1 -> 1.1320605e+08 | E25: =C25+D25 -> 1.1320605e+08 | F25: =SUMIFS(Monitoring!R:R,Monitoring!D:D,Summary!B25,Monitoring!F:F,"N") -> 1.3795605e+08 | G25: =F25/E25 -> 1.2186279 | H25: =E25-F25 -> -24750000 | I25: =H25/E25 -> -0.21862789
B26: OFFICES | C26: 67300000 | E26: =C26+D26 -> 67300000 | F26: =SUMIFS(Monitoring!R:R,Monitoring!D:D,Summary!B26,Monitoring!F:F,"N") -> 66298214 | G26: =F26/E26 -> 0.98511463 | H26: =E26-F26 -> 1001785.7 | I26: =H26/E26 -> 0.014885375
B27: RESIDENTIAL | C27: 50000000 | E27: =C27+D27 -> 50000000 | F27: =SUMIFS(Monitoring!R:R,Monitoring!D:D,Summary!B27,Monitoring!F:F,"N") -> 14093898 | G27: =F27/E27 -> 0.28187795 | H27: =E27-F27 -> 35906102 | I27: =H27/E27 -> 0.71812205
B28: TOTAL | C28: =SUM(C21:C27) -> 3.4354354e+08 | D28: =SUM(D21:D27) -> 0 | E28: =SUM(E21:E27) -> 3.4354354e+08 | F28: =SUM(F21:F27) -> 3.0408756e+08 | G28: =F28/E28 -> 0.88515 | H28: =SUM(H21:H27) -> 39455976 | I28: =H28/E28 -> 0.11485
B30: Board Approved vs Allotted
B31: (with Special Projects)
B32: SBU | C32: ORIGINAL BOARD APPROVED | D32: ADDITIONAL/ REDUCTION | E32: TOTAL BOARD APPROVED | F32: ACTUAL | G32: COMMITTED (open PR PO) | H32: ALLOTTED | J32: AVAILABLE1 | L32: AVAILABLE2 | N32: Jan | O32: Feb | P32: Mar | Q32: Apr | R32: May | S32: Jun | T32: Jul | U32: Aug | V32: Sep | W32: Oct | X32: Nov | Y32: Dec | Z32: 2026 FORECAST | AA32: BALANCE
H33: PHP | I33: % | J33: PHP | K33: % | L33: PHP | M33: % | AA33: PHP | AB33: %
C34: A | D34: B | E34: C = A+B | F34: D | G34: E | H34: F = D+E | I34: G = F/C | J34: H = C-F | K34: I = H/C | Z34: J | AA34: K = C-J | AB34: L = K/C
B35: CORPORATE - HR | C35: 19700000 | E35: =C35+D35 -> 19700000 | F35: =SUMIF(Monitoring!$D:$D,Summary!$B35,Monitoring!$AA:$AA) -> 9832978.6 | G35: =SUMIF(Monitoring!$D:$D,Summary!$B35,Monitoring!$AB:$AB) -> 2203571.4 | H35: =SUM(F35:G35) -> 12036550 | I35: =H35/E35 -> 0.61099239 | J35: =E35-H35 -> 7663450 | K35: =J35/E35 -> 0.38900761 | Z35: =SUM(N35:Y35) -> 0 | AA35: =E35-Z35 -> 19700000 | AB35: =AA35/E35 -> 1
B36: CORPORATE - IT | C36: 31000000 | E36: =C36+D36 -> 31000000 | F36: =SUMIF(Monitoring!$D:$D,Summary!$B36,Monitoring!$AA:$AA) -> 16165522 | G36: =SUMIF(Monitoring!$D:$D,Summary!$B36,Monitoring!$AB:$AB) -> 1562946.4 | H36: =SUM(F36:G36) -> 17728469 | I36: =H36/E36 -> 0.57188609 | J36: =E36-H36 -> 13271531 | K36: =J36/E36 -> 0.42811391 | Z36: =SUM(N36:Y36) -> 0 | AA36: =E36-Z36 -> 31000000 | AB36: =AA36/E36 -> 1
B37: CORPORATE - ADMIN | C37: 2337486 | E37: =C37+D37 -> 2337486 | F37: =SUMIF(Monitoring!$D:$D,Summary!$B37,Monitoring!$AA:$AA) -> 138392.86 | G37: =SUMIF(Monitoring!$D:$D,Summary!$B37,Monitoring!$AB:$AB) -> 0 | H37: =SUM(F37:G37) -> 138392.86 | I37: =H37/E37 -> 0.059205856 | J37: =E37-H37 -> 2199093.1 | K37: =J37/E37 -> 0.94079414 | Z37: =SUM(N37:Y37) -> 0 | AA37: =E37-Z37 -> 2337486 | AB37: =AA37/E37 -> 1
B38: ESTATES | C38: 60000000 | E38: =C38+D38 -> 60000000 | F38: =SUMIF(Monitoring!$D:$D,Summary!$B38,Monitoring!$AA:$AA) -> 50481169 | G38: =SUMIF(Monitoring!$D:$D,Summary!$B38,Monitoring!$AB:$AB) -> 1.4525823e+08 | H38: =SUM(F38:G38) -> 1.9573939e+08 | I38: =H38/E38 -> 3.2623232 | J38: =E38-H38 -> -1.3573939e+08 | K38: =J38/E38 -> -2.2623232 | Z38: =SUM(N38:Y38) -> 0 | AA38: =E38-Z38 -> 60000000 | AB38: =AA38/E38 -> 1
B39: MALLS | C39: =Malls!$G$1 -> 1.1320605e+08 | E39: =C39+D39 -> 1.1320605e+08 | F39: =SUMIF(Monitoring!$D:$D,Summary!$B39,Monitoring!$AA:$AA) -> 27138755 | G39: =SUMIF(Monitoring!$D:$D,Summary!$B39,Monitoring!$AB:$AB) -> 55946400 | H39: =SUM(F39:G39) -> 83085155 | I39: =H39/E39 -> 0.73392856 | J39: =E39-H39 -> 30120898 | K39: =J39/E39 -> 0.26607144 | Z39: =SUM(N39:Y39) -> 0 | AA39: =E39-Z39 -> 1.1320605e+08 | AB39: =AA39/E39 -> 1
B40: OFFICES | C40: 67300000 | E40: =C40+D40 -> 67300000 | F40: =SUMIF(Monitoring!$D:$D,Summary!$B40,Monitoring!$AA:$AA) -> 42886794 | G40: =SUMIF(Monitoring!$D:$D,Summary!$B40,Monitoring!$AB:$AB) -> 25379823 | H40: =SUM(F40:G40) -> 68266617 | I40: =H40/E40 -> 1.0143628 | J40: =E40-H40 -> -966617.47 | K40: =J40/E40 -> -0.014362815 | Z40: =SUM(N40:Y40) -> 0 | AA40: =E40-Z40 -> 67300000 | AB40: =AA40/E40 -> 1
B41: RESIDENTIAL | C41: 50000000 | E41: =C41+D41 -> 50000000 | F41: =SUMIF(Monitoring!$D:$D,Summary!$B41,Monitoring!$AA:$AA) -> 8244582.9 | G41: =SUMIF(Monitoring!$D:$D,Summary!$B41,Monitoring!$AB:$AB) -> 3777253.7 | H41: =SUM(F41:G41) -> 12021837 | I41: =H41/E41 -> 0.24043673 | J41: =E41-H41 -> 37978163 | K41: =J41/E41 -> 0.75956327 | Z41: =SUM(N41:Y41) -> 0 | AA41: =E41-Z41 -> 50000000 | AB41: =AA41/E41 -> 1
B42: TOTAL | C42: =SUM(C35:C41) -> 3.4354354e+08 | D42: =SUM(D35:D41) -> 0 | E42: =SUM(E35:E41) -> 3.4354354e+08 | F42: =SUM(F35:F41) -> 1.5488819e+08 | G42: =SUM(G35:G41) -> 234128221 | H42: =SUM(H35:H41) -> 3.8901642e+08 | I42: =H42/E42 -> 1.1323642 | J42: =SUM(J35:J41) -> -45472876 | K42: =J42/E42 -> -0.13236423 | N42: =SUM(N35:N41) -> 0 | Y42: =SUM(Y35:Y41) -> 0 | Z42: =SUM(Z35:Z41) -> 0 | AA42: =SUM(AA35:AA41) -> 3.4354354e+08 | AB42: =AA42/E42 -> 1
F43: =F42-Monitoring!AA5 -> 0 | G43: =G42-Monitoring!AB5 -> 0 | H43: =H42-Monitoring!AC5 -> 0

Sheet SAP Report
A1: Updated as of | B1: 09/15/2026
C2: =SUBTOTAL(9,C4:C179) -> 7.0766826e+08 | D2: =SUBTOTAL(9,D4:D179) -> 1.5488819e+08 | E2: =SUBTOTAL(9,E4:E179) -> 234128221 | F2: =SUBTOTAL(9,F4:F179) -> 3.8901642e+08 | G2: =SUBTOTAL(9,G4:G179) -> 3.1865184e+08
A3: IO Number | B3: Description | C3: Budget | D3: Actual | E3: Commitment | F3: Allotted | G3: Available
A4: 10000820 | B4: GH IMPROVEMENT OF VMALL PARK | C4: 278125 | E4: 278125 | F4: 278125 | G4: =C4-F4 -> 0
A5: 10001021 | B5: GH PH1 STREETSCAPE PROJECT | C5: 4855625 | E5: 4855625 | F5: 4855625 | G5: =C5-F5 -> 0
A6: 10001072 | B6: GH RFDCK/CNOPIES/PRMTR WALL | C6: 142000 | E6: 142000 | F6: 142000 | G6: =C6-F6 -> 0
A7: 10001075 | B7: CC STP UPGRADE | G7: =C7-F7 -> 0
A8: 10001134 | B8: GH TIANGGE EIFS DROPWALL | C8: 789517.86 | E8: 789517.86 | F8: 789517.86 | G8: =C8-F8 -> 0
A9: 10001136 | B9: CCIC SALES OFFICE SPLIT-TYPE | C9: 982142.86 | D9: 982142.86 | F9: 982142.86 | G9: =C9-F9 -> 0
A10: 10001140 | B10: CCIC MEZZANINE 2 AIRCON UNIT | C10: 232142.86 | E10: 232142.86 | F10: 232142.86 | G10: =C10-F10 -> 0
A11: 10001143 | B11: CCIC EXTERIOR WALL & CEILING | C11: 308303.57 | G11: =C11-F11 -> 308303.57
A12: 10001190 | B12: SC4 VRF SYSTEM RECONDITIONIN | C12: 2400000 | D12: 2400000 | F12: 2400000 | G12: =C12-F12 -> 0
A13: 10001220 | B13: GH ESTATES LIFT STATION | C13: 99196.43 | E13: 99196.43 | F13: 99196.43 | G13: =C13-F13 -> 0
A14: 10001254 | B14: ES CONSTRUCTION OF OMD ADMIN | C14: 32193.08 | E14: 32193.08 | F14: 32193.08 | G14: =C14-F14 -> 0
A15: 10001262 | B15: GH NEW MALL REWATERPROOFING | C15: 767321.43 | D15: 417857.14 | E15: 349464.28 | F15: 767321.42 | G15: =C15-F15 -> 0.01
A16: 10001269 | B16: EONS ELEVATORS PARTS REPLACE | C16: 560714.29 | D16: 560714.29 | F16: 560714.29 | G16: =C16-F16 -> 0
A17: 10001270 | B17: ESW LIFT STATION REHABILITAT | C17: 437500 | D17: 437500 | F17: 437500 | G17: =C17-F17 -> 0
A18: 10001281 | B18: SC4 WATER PROOFING OF ROOF D | C18: 3004771.5 | D18: 1973033.9 | E18: 1031737.5 | F18: 3004771.5 | G18: =C18-F18 -> 0
A19: 10001288 | B19: ES EAST WING 2024 SPACE RE-C | C19: 7500 | E19: 7500 | F19: 7500 | G19: =C19-F19 -> 0
A20: 10001289 | B20: ES MAIN 2025 SPACE RE-CUT & | C20: 42857.14 | E20: 42857.14 | F20: 42857.14 | G20: =C20-F20 -> 0
A21: 10001294 | B21: GH TIANGGE STALLS ELECTRICAL | C21: 4560714.3 | D21: 4253567.6 | F21: 4253567.6 | G21: =C21-F21 -> 307146.69
A22: 10001296 | B22: GH MALL ADMIN RELOCATION AND | C22: 506471.03 | D22: 437499.99 | E22: 20810.32 | F22: 458310.31 | G22: =C22-F22 -> 48160.72
A23: 10001298 | B23: CC DRAINAGE IMPROVEMENT PH1A | C23: 7190.4 | D23: -0.01 | E23: 7190.4 | F23: 7190.39 | G23: =C23-F23 -> 0.01
A24: 10001302 | B24: GH TENANT RECUTS | C24: 278743.18 | E24: 278743.18 | F24: 278743.18 | G24: =C24-F24 -> 0
A25: 10001305 | B25: GH ANNEX ALFRESCO AREA COLUM | C25: 356250 | E25: 356250 | F25: 356250 | G25: =C25-F25 -> 0
A26: 10001308 | B26: CC PASIG CIVIC CENTER | C26: 25714286 | G26: =C26-F26 -> 25714286
A27: 10001311 | B27: SC2&3 WATER PROOFING OF ROOF | C27: 3660714.3 | D27: 3161591.1 | E27: 499123.19 | F27: 3660714.3 | G27: =C27-F27 -> 0
A28: 10001312 | B28: EM EAST WING CHAPEL AIRCON A | C28: 12232.14 | E28: 12232.14 | F28: 12232.14 | G28: =C28-F28 -> 0
A29: 10001314 | B29: GH TOWER BIR FIT-OUT | C29: 10217698 | D29: 8096919.1 | E29: 1429857.1 | F29: 9526776.2 | G29: =C29-F29 -> 690921.41
A30: 10001315 | B30: GH MALL VIP READER SYSTEM FO | C30: 26321.43 | D30: 133464.29 | F30: 133464.29 | G30: =C30-F30 -> -107142.86
A31: 10001320 | B31: THE STRIP SEISMIC ACCELEROGR | C31: 875000 | E31: 875000 | F31: 875000 | G31: =C31-F31 -> 0
A32: 10001322 | B32: CC DRAINAGE IMPROVEMENT PHAS | C32: 15000000 | D32: 6300000 | E32: 8700000 | F32: 15000000 | G32: =C32-F32 -> 0
A33: 10001340 | B33: IBP ACP REPLACEMENT & PUMP R | C33: 285714.29 | D33: 285714.29 | F33: 285714.29 | G33: =C33-F33 -> 0
A34: 10001341 | B34: CC PARK REDEVELOPMENT | C34: 50718878 | D34: 24715944 | E34: 20320127 | F34: 45036072 | G34: =C34-F34 -> 5682806.2
A35: 10001342 | B35: GH EXISTING MALL PRE-WATERPR | C35: 341960.05 | D35: 208214.29 | E35: 133745.76 | F35: 341960.05 | G35: =C35-F35 -> 0
A36: 10001348 | B36: GH VMALL CHAPEL RENOVATION | C36: 486257.14 | E36: 486257.14 | F36: 486257.14 | G36: =C36-F36 -> 0
A37: 10001350 | B37: CAPITOL COMMONS IMPROVEMENTS | C37: 20168929 | D37: 11986161 | E37: 3966040.4 | F37: 15952201 | G37: =C37-F37 -> 4216727.5
A38: 10001360 | B38: ESWW WATERPROOFING | C38: 2437500 | D38: 2437500 | F38: 2437500 | G38: =C38-F38 -> 0
A39: 10001361 | B39: SC2&3 REHAB OF VRF | C39: 2901785.7 | D39: 2901785.7 | F39: 2901785.7 | G39: =C39-F39 -> 0
A40: 10001362 | B40: CC STP REHAB AND REPAIR | C40: 366071.43 | D40: 366071.43 | F40: 366071.43 | G40: =C40-F40 -> 0
A41: 10001363 | B41: SC5 ISOLATION VALVES REPLACE | C41: 714285.71 | D41: 714285.71 | F41: 714285.71 | G41: =C41-F41 -> 0
A42: 10001364 | B42: SC1 STP REHABILITATION | C42: 3493750 | D42: 3082801.4 | E42: 342533.48 | F42: 3425334.8 | G42: =C42-F42 -> 68415.17
A43: 10001365 | B43: SC2&3 STP REHABILITATION | C43: 2673660.7 | D43: 2344721 | E43: 260524.55 | F43: 2605245.5 | G43: =C43-F43 -> 68415.18
A44: 10001366 | B44: SC4 STP REHABILITATION | C44: 2048660.7 | D44: 1781819.2 | E44: 197979.91 | F44: 1979799.1 | G44: =C44-F44 -> 68861.61
A45: 10001372 | B45: ORTIGAS PARKLANE PARKING SYS | C45: 321428.57 | E45: 321428.57 | F45: 321428.57 | G45: =C45-F45 -> 0
A46: 10001374 | B46: GH MRF IMPROVEMENTS AND FAÇA | C46: 1316964.3 | D46: 1316964.3 | F46: 1316964.3 | G46: =C46-F46 -> 0.01
A47: 10001378 | B47: THE STRIP VARIOUS TENANCY PR | C47: 1178571.4 | D47: 346071.43 | E47: 832500 | F47: 1178571.4 | G47: =C47-F47 -> 0
A48: 10001381 | B48: SC3 REHABILITATION OF TURNST | C48: 968800 | D48: 625000 | F48: 625000 | G48: =C48-F48 -> 343800
A49: 10001385 | B49: GH AUTOMATIC SLIDING DOOR | C49: 5500000 | D49: 2053571.4 | E49: 3237276.8 | F49: 5290848.2 | G49: =C49-F49 -> 209151.79
A50: 10001386 | B50: ES PARKING LIGHTINGS & BARRI | C50: 2000000 | D50: 300000 | E50: 104738 | F50: 404738 | G50: =C50-F50 -> 1595262
A51: 10001387 | B51: ES UPGRADE OF MALL ENTRANCES | C51: 3355000 | D51: 49316.69 | E51: 469548.71 | F51: 518865.4 | G51: =C51-F51 -> 2836134.6
A52: 10001388 | B52: ES UPGRADE OF MALL COMMON CR | C52: 5000000 | D52: 843125.13 | E52: 3688102.2 | F52: 4531227.3 | G52: =C52-F52 -> 468772.69
A53: 10001389 | B53: ES EW FACILITY ENHANCEMENTS | C53: 3000000 | D53: 700173.93 | E53: 1484187.5 | F53: 2184361.4 | G53: =C53-F53 -> 815638.57
A54: 10001390 | B54: ES REFRESH OF AL FRESCO | C54: 3000000 | D54: 1076321.4 | E54: 614678.57 | F54: 1691000 | G54: =C54-F54 -> 1309000
A55: 10001391 | B55: ES REPAINTING & IMPROVEMENT | C55: 1000000 | D55: 283779.72 | F55: 283779.72 | G55: =C55-F55 -> 716220.28
A56: 10001392 | B56: ES EW PARKING SIGNAGES REPAI | G56: =C56-F56 -> 0
A57: 10001393 | B57: ES 2026 SPACE RE-CUT & STUB- | C57: 1500000 | D57: 1373767.4 | E57: 71428.57 | F57: 1445196 | G57: =C57-F57 -> 54804.04
A58: 10001394 | B58: ES EW 2026 SPACE RE-CUT & ST | C58: 4000000 | D58: 1098009.3 | E58: 2270763.5 | F58: 3368772.8 | G58: =C58-F58 -> 631227.16
A59: 10001395 | B59: GH TENANT SPACE RE-CUT & UTI | C59: 6212500 | D59: 4193750 | E59: 858035.72 | F59: 5051785.7 | G59: =C59-F59 -> 1160714.3
A60: 10001396 | B60: IBP TOWER CONFERENCE ROOM | C60: 409178.55 | E60: 401785.71 | F60: 401785.71 | G60: =C60-F60 -> 7392.84
A61: 10001397 | B61: IBP TOWER PRV REPLACEMENT | C61: 350000 | D61: 133928.57 | F61: 133928.57 | G61: =C61-F61 -> 216071.43
A62: 10001398 | B62: IBP TOWER UPS REPLACEMENT | C62: 211000 | D62: 168000 | F62: 168000 | G62: =C62-F62 -> 43000
A63: 10001399 | B63: IBP TOWER WATERPROOFING ROOF | C63: 3000000 | E63: 2455357.1 | F63: 2455357.1 | G63: =C63-F63 -> 544642.86
A64: 10001400 | B64: IBP TOWER BLADDER TANK REPLA | C64: 350000 | D64: 294642.86 | F64: 294642.86 | G64: =C64-F64 -> 55357.14
A65: 10001401 | B65: IBP TOWER STP REHABILITATION | C65: 1500000 | D65: 406250 | E65: 593750 | F65: 1000000 | G65: =C65-F65 -> 500000
A66: 10001402 | B66: SC5 REHABILITATION OF COOLIN | C66: 750000 | G66: =C66-F66 -> 750000
A67: 10001403 | B67: SC5 REHABILITATION OF CONTRO | C67: 663234.54 | G67: =C67-F67 -> 663234.54
A68: 10001404 | B68: SC5 STP REHABILITATION WORKS | C68: 4191964.3 | D68: 3638872.8 | E68: 404319.2 | F68: 4043192 | G68: =C68-F68 -> 148772.32
A69: 10001405 | B69: SC2 REHABILITATION WOKRS | G69: =C69-F69 -> 0
A70: 10001406 | B70: SC1A ROOFDECK WATERPROOFING | C70: 2000000 | E70: 1294642.9 | F70: 1294642.9 | G70: =C70-F70 -> 705357.14
A71: 10001407 | B71: SC4 PARKING POS | C71: 250000 | D71: 225892.86 | F71: 225892.86 | G71: =C71-F71 -> 24107.14
A72: 10001409 | B72: SC1 DECAGON PERIMETER GLASS | C72: 1000000 | G72: =C72-F72 -> 1000000
A73: 10001410 | B73: SC1 INSTALLATION OF MOTORIZE | G73: =C73-F73 -> 0
A74: 10001411 | B74: SC1 REHABILITATION OF COMMON | C74: 1000000 | E74: 1000000 | F74: 1000000 | G74: =C74-F74 -> 0
A75: 10001412 | B75: SC1 REINSULATION OF AHU DUCT | G75: =C75-F75 -> 0
A76: 10001413 | B76: ENS ROOFDECK WATERPROOFING R | C76: 3179000 | E76: 2576530.6 | F76: 2576530.6 | G76: =C76-F76 -> 602469.39
A77: 10001414 | B77: ENS MAJOR ELEVATOR PARTS REP | C77: 2355000 | E77: 1929261.5 | F77: 1929261.5 | G77: =C77-F77 -> 425738.51
A78: 10001415 | B78: ENS REPLACEMENT OF AHU MOTOR | C78: 2000000 | G78: =C78-F78 -> 2000000
A79: 10001416 | B79: ENS REINSULATION OF MAIN CHI | C79: 800000 | D79: 43750 | F79: 43750 | G79: =C79-F79 -> 756250
A80: 10001417 | B80: ENS REPLACEMENT OF BARSCREEN | C80: 800000 | D80: 126000 | F80: 126000 | G80: =C80-F80 -> 674000
A81: 10001418 | B81: EWW MAJOR ELEVATOR PARTS REP | C81: 3000000 | E81: 2589285.7 | F81: 2589285.7 | G81: =C81-F81 -> 410714.29
A82: 10001419 | B82: EWW ROOFDECK WATERPROOFING R | C82: 5999500 | D82: 1318750 | E82: 2725892.9 | F82: 4044642.9 | G82: =C82-F82 -> 1954857.1
A83: 10001420 | B83: EWW WATERPROOFING OF ELEVATO | C83: 600000 | D83: 282142.86 | E83: 240741.96 | F83: 522884.82 | G83: =C83-F83 -> 77115.18
A84: 10001421 | B84: EWW BACK-UP SUBMERSIBLE PUMP | C84: 600000 | E84: 224000 | F84: 224000 | G84: =C84-F84 -> 376000
A85: 10001422 | B85: ENS INSTALLATION OF VENTILAT | C85: 700000 | D85: 459821.43 | F85: 459821.43 | G85: =C85-F85 -> 240178.57
A86: 10001423 | B86: SC1 FIRE AND JOCKEY PUMPS PA | C86: 295600 | D86: 96875 | F86: 96875 | G86: =C86-F86 -> 198725
A87: 10001424 | B87: SC1A FIRE AND JOCKEY PUMPS P | G87: =C87-F87 -> 0
A88: 10001425 | B88: SC2 FIRE AND JOCKEY PUMPS PA | C88: 147800 | D88: 37053.57 | F88: 37053.57 | G88: =C88-F88 -> 110746.43
A89: 10001426 | B89: SC3 FIRE AND JOCKEY PUMPS PA | C89: 435000 | D89: 348214.29 | F89: 348214.29 | G89: =C89-F89 -> 86785.71
A90: 10001427 | B90: SC4 FIRE AND JOCKEY PUMPS PA | G90: =C90-F90 -> 0
A91: 10001428 | B91: SC5 FIRE AND JOCKEY PUMPS PA | C91: 678200 | D91: 437500 | F91: 437500 | G91: =C91-F91 -> 240700
A92: 10001429 | B92: GH MALL CINEMA CINE-LUXE SEA | C92: 6000000 | G92: =C92-F92 -> 6000000
A93: 10001430 | B93: PROMENADE CINEMA 8 SEAT ENHA | C93: 2100000 | G93: =C93-F93 -> 2100000
A94: 10001431 | B94: PROMENADE CINEMA 8 FLOOR AND | C94: 1900000 | G94: =C94-F94 -> 1900000
A95: 10001432 | B95: GH STEEL BOLLARDS | C95: 787500 | E95: 625000 | F95: 625000 | G95: =C95-F95 -> 162500
A96: 10001433 | B96: GH REPLACEMENT OF ELECTRICAL | C96: 3500000 | E96: 3500000 | F96: 3500000 | G96: =C96-F96 -> 0
A97: 10001434 | B97: GH ESCALATORS/ELEVATORS MAJO | C97: 6000000 | E97: 2077976.1 | F97: 2077976.1 | G97: =C97-F97 -> 3922023.9
A98: 10001435 | B98: GH UPGRADE OF LIFT STATION | C98: 3000000 | D98: 1281250 | E98: 802901.79 | F98: 2084151.8 | G98: =C98-F98 -> 915848.2
A99: 10001440 | B99: CC MRF EXPANSION & REHABILIT | C99: 1800000 | D99: 1517857.1 | F99: 1517857.1 | G99: =C99-F99 -> 282142.86
A100: 10001441 | B100: CC LIFT STATION MANHOLE REHA | C100: 1500000 | D100: 1401785.7 | F100: 1401785.7 | G100: =C100-F100 -> 98214.29
...

Sheet Actual
F1: =SUBTOTAL(9,F3:F1048576) -> 1.5488819e+08
A2: Order | B2: CO object name | C2: Cost element name | D2: Purchasing Document | E2: Ref Document Number | F2: Val.in rep.cur. | G2: Purchase order text | H2: Document Header Text | I2: Total quantity | J2: Offsetting account type | K2: Offsetting acct no. | L2: Name of offsetting account | M2: Period | N2: Month
A3: 10001136 | B3: CCIC SALES OFFICE SPLIT-TYPE AIRCON | C3: IO CAPEX | D3: 4500023106 | E3: 5000056499 | F3: 982142.86 | G3: Supply and installation of 4Units AC | I3: 1 | J3: S | K3: 21301102 | L3: Trade A/P Clearing | M3: 6 | N3: =_xlfn.XLOOKUP(M3,$Q$3:$Q$14,$R$3:$R$14) -> Jun | Q3: 1 | R3: Jan
A4: 10001190 | B4: SC4 VRF SYSTEM RECONDITIONING | C4: IO CAPEX | D4: 4500030671 | E4: 5000055823 | F4: 2400000 | G4: Rehabilitation of VRF at SC4 | I4: 1 | J4: S | K4: 21301102 | L4: Trade A/P Clearing | M4: 4 | N4: =_xlfn.XLOOKUP(M4,$Q$3:$Q$14,$R$3:$R$14) -> Apr | Q4: 2 | R4: Feb
A5: 10001262 | B5: GH NEW MALL REWATERPROOFING PROJECT | C5: IO CAPEX | D5: 4500028476 | E5: 5000055813 | F5: 417857.14 | G5: Waterproofing and Facade Works at GH Ph1 | I5: 0.312 | J5: S | K5: 21301102 | L5: Trade A/P Clearing | M5: 4 | N5: =_xlfn.XLOOKUP(M5,$Q$3:$Q$14,$R$3:$R$14) -> Apr | Q5: 3 | R5: Mar
A6: 10001269 | B6: EONS ELEVATORS PARTS REPLACEMENT | C6: IO CAPEX | D6: 4500030559 | E6: 5000055592 | F6: 44642.86 | G6: PARTS REPLACEMENT OF FREIGHT ELEVATOR 1 | I6: 1 | J6: S | K6: 21301102 | L6: Trade A/P Clearing | M6: 4 | N6: =_xlfn.XLOOKUP(M6,$Q$3:$Q$14,$R$3:$R$14) -> Apr | Q6: 4 | R6: Apr
A7: 10001269 | B7: EONS ELEVATORS PARTS REPLACEMENT | C7: IO CAPEX | D7: 4500030559 | E7: 5000055592 | F7: 145535.71 | G7: PARTS REPLACEMENT PASSENGER ELEVATOR 3 | I7: 1 | J7: S | K7: 21301102 | L7: Trade A/P Clearing | M7: 4 | N7: =_xlfn.XLOOKUP(M7,$Q$3:$Q$14,$R$3:$R$14) -> Apr | Q7: 5 | R7: May
A8: 10001269 | B8: EONS ELEVATORS PARTS REPLACEMENT | C8: IO CAPEX | D8: 4500030559 | E8: 5000055592 | F8: 178571.43 | G8: PARTS REPLACEMENT PASSENGER ELEVATOR 2 | I8: 1 | J8: S | K8: 21301102 | L8: Trade A/P Clearing | M8: 4 | N8: =_xlfn.XLOOKUP(M8,$Q$3:$Q$14,$R$3:$R$14) -> Apr | Q8: 6 | R8: Jun
A9: 10001269 | B9: EONS ELEVATORS PARTS REPLACEMENT | C9: IO CAPEX | D9: 4500030559 | E9: 5000055592 | F9: 191964.29 | G9: PARTS REPLACEMENT PASSENGER ELEVATOR 1 | I9: 1 | J9: S | K9: 21301102 | L9: Trade A/P Clearing | M9: 4 | N9: =_xlfn.XLOOKUP(M9,$Q$3:$Q$14,$R$3:$R$14) -> Apr | Q9: 7 | R9: Jul
A10: 10001270 | B10: ESW LIFT STATION REHABILITATION | C10: IO CAPEX | D10: 4500030613 | E10: 5000055824 | F10: 80357.14 | G10: S&I OF DUPLEX PUMP CONTROLLER | I10: 1 | J10: S | K10: 21301102 | L10: Trade A/P Clearing | M10: 4 | N10: =_xlfn.XLOOKUP(M10,$Q$3:$Q$14,$R$3:$R$14) -> Apr | Q10: 8 | R10: Aug
A11: 10001270 | B11: ESW LIFT STATION REHABILITATION | C11: IO CAPEX | D11: 4500030613 | E11: 5000055824 | F11: 357142.86 | G11: S&I OF 2 UNITS BLADDER MEMBRANE | I11: 1 | J11: S | K11: 21301102 | L11: Trade A/P Clearing | M11: 4 | N11: =_xlfn.XLOOKUP(M11,$Q$3:$Q$14,$R$3:$R$14) -> Apr | Q11: 9 | R11: Sep
A12: 10001281 | B12: SC4 WATER PROOFING OF ROOF DECK FLOORING | C12: IO CAPEX | D12: 4500028439 | E12: 5000054530 | F12: 1473910.7 | G12: WATERPROOFING OF SC4 - 3,250 sq.m | I12: 0.4 | J12: S | K12: 21301102 | L12: Trade A/P Clearing | M12: 2 | N12: =_xlfn.XLOOKUP(M12,$Q$3:$Q$14,$R$3:$R$14) -> Feb | Q12: 10 | R12: Oct
A13: 10001281 | B13: SC4 WATER PROOFING OF ROOF DECK FLOORING | C13: IO CAPEX | D13: 4500030775 | E13: 5000055037 | F13: 499123.19 | G13: WATERPROOFING OF SC 2 (352.42sqm) | I13: 1 | J13: S | K13: 21301102 | L13: Trade A/P Clearing | M13: 3 | N13: =_xlfn.XLOOKUP(M13,$Q$3:$Q$14,$R$3:$R$14) -> Mar | Q13: 11 | R13: Nov
A14: 10001294 | B14: GH TIANGGE STALLS ELECTRICAL | C14: IO CAPEX | E14: 100731408 | F14: 133836.89 | I14: 0 | J14: S | K14: 21307111 | L14: Accrued Pay- Interco | M14: 7 | N14: =_xlfn.XLOOKUP(M14,$Q$3:$Q$14,$R$3:$R$14) -> Jul | Q14: 12 | R14: Dec
A15: 10001294 | B15: GH TIANGGE STALLS ELECTRICAL | C15: IO CAPEX | E15: 100731408 | F15: 54098.31 | I15: 0 | J15: S | K15: 21307111 | L15: Accrued Pay- Interco | M15: 7 | N15: =_xlfn.XLOOKUP(M15,$Q$3:$Q$14,$R$3:$R$14) -> Jul
A16: 10001294 | B16: GH TIANGGE STALLS ELECTRICAL | C16: IO CAPEX | E16: 100731408 | F16: 62859.59 | I16: 0 | J16: S | K16: 21307111 | L16: Accrued Pay- Interco | M16: 7 | N16: =_xlfn.XLOOKUP(M16,$Q$3:$Q$14,$R$3:$R$14) -> Jul
A17: 10001294 | B17: GH TIANGGE STALLS ELECTRICAL | C17: IO CAPEX | E17: 100731408 | F17: 111291.66 | I17: 0 | J17: S | K17: 21307111 | L17: Accrued Pay- Interco | M17: 7 | N17: =_xlfn.XLOOKUP(M17,$Q$3:$Q$14,$R$3:$R$14) -> Jul
A18: 10001294 | B18: GH TIANGGE STALLS ELECTRICAL | C18: IO CAPEX | E18: 100731408 | F18: 73621.39 | I18: 0 | J18: S | K18: 21307111 | L18: Accrued Pay- Interco | M18: 7 | N18: =_xlfn.XLOOKUP(M18,$Q$3:$Q$14,$R$3:$R$14) -> Jul
A19: 10001294 | B19: GH TIANGGE STALLS ELECTRICAL | C19: IO CAPEX | E19: 100731408 | F19: 98179.7 | I19: 0 | J19: S | K19: 21307111 | L19: Accrued Pay- Interco | M19: 7 | N19: =_xlfn.XLOOKUP(M19,$Q$3:$Q$14,$R$3:$R$14) -> Jul
A20: 10001294 | B20: GH TIANGGE STALLS ELECTRICAL | C20: IO CAPEX | E20: 100731408 | F20: 51090.77 | I20: 0 | J20: S | K20: 21307111 | L20: Accrued Pay- Interco | M20: 7 | N20: =_xlfn.XLOOKUP(M20,$Q$3:$Q$14,$R$3:$R$14) -> Jul
A21: 10001294 | B21: GH TIANGGE STALLS ELECTRICAL | C21: IO CAPEX | D21: 4500029617 | E21: 5000055775 | F21: 1134821.4 | G21: Electrical Provision for 427 Stalls | I21: 0.31 | J21: S | K21: 21301102 | L21: Trade A/P Clearing | M21: 4 | N21: =_xlfn.XLOOKUP(M21,$Q$3:$Q$14,$R$3:$R$14) -> Apr
A22: 10001294 | B22: GH TIANGGE STALLS ELECTRICAL | C22: IO CAPEX | D22: 4500029617 | E22: 5000055074 | F22: 2233035.7 | G22: Electrical Provision for 427 Stalls | I22: 0.61 | J22: S | K22: 21301102 | L22: Trade A/P Clearing | M22: 3 | N22: =_xlfn.XLOOKUP(M22,$Q$3:$Q$14,$R$3:$R$14) -> Mar
A23: 10001294 | B23: GH TIANGGE STALLS ELECTRICAL | C23: IO CAPEX | D23: 4500032689 | E23: 5000057548 | F23: 7875 | G23: UPS BATTERY 12V 7AH FOR UPS 650VA | I23: 9 | J23: S | K23: 21301102 | L23: Trade A/P Clearing | M23: 8 | N23: =_xlfn.XLOOKUP(M23,$Q$3:$Q$14,$R$3:$R$14) -> Aug
A24: 10001294 | B24: GH TIANGGE STALLS ELECTRICAL | C24: IO CAPEX | D24: 4500029617 | E24: 5000055492 | F24: -2233035.7 | G24: Electrical Provision for 427 Stalls | I24: -0.61 | J24: S | K24: 21301102 | L24: Trade A/P Clearing | M24: 4 | N24: =_xlfn.XLOOKUP(M24,$Q$3:$Q$14,$R$3:$R$14) -> Apr
A25: 10001294 | B25: GH TIANGGE STALLS ELECTRICAL | C25: IO CAPEX | D25: 4500029617 | E25: 5000055493 | F25: 2525892.9 | G25: Electrical Provision for 427 Stalls | I25: 0.69 | J25: S | K25: 21301102 | L25: Trade A/P Clearing | M25: 4 | N25: =_xlfn.XLOOKUP(M25,$Q$3:$Q$14,$R$3:$R$14) -> Apr
A26: 10001296 | B26: GH MALL ADMIN RELOCATION AND CONVERSION | C26: IO CAPEX | D26: 4500031193 | E26: 5000055010 | F26: 464285.71 | G26: ADDITIONAL WORKS AT GH ADMIN NEW OFFICE | I26: 1 | J26: S | K26: 21301102 | L26: Trade A/P Clearing | M26: 3 | N26: =_xlfn.XLOOKUP(M26,$Q$3:$Q$14,$R$3:$R$14) -> Mar
A27: 10001296 | B27: GH MALL ADMIN RELOCATION AND CONVERSION | C27: IO CAPEX | E27: 101668770 | F27: -197321.43 | I27: 0 | J27: S | K27: 52061103 | L27: DOE Rprs & Main-Bldg | M27: 2 | N27: =_xlfn.XLOOKUP(M27,$Q$3:$Q$14,$R$3:$R$14) -> Feb
A28: 10001296 | B28: GH MALL ADMIN RELOCATION AND CONVERSION | C28: IO CAPEX | D28: 4500027836 | E28: 5000054373 | F28: 169696.43 | G28: SUPPLY OF GRANDSTREAM IP PHONES DEVICES | I28: 0.86 | J28: S | K28: 21301102 | L28: Trade A/P Clearing | M28: 1 | N28: =_xlfn.XLOOKUP(M28,$Q$3:$Q$14,$R$3:$R$14) -> Jan
A29: 10001296 | B29: GH MALL ADMIN RELOCATION AND CONVERSION | C29: IO CAPEX | D29: 4500027836 | E29: 5000054747 | F29: -169696.43 | G29: SUPPLY OF GRANDSTREAM IP PHONES DEVICES | I29: -0.86 | J29: S | K29: 21301102 | L29: Trade A/P Clearing | M29: 2 | N29: =_xlfn.XLOOKUP(M29,$Q$3:$Q$14,$R$3:$R$14) -> Feb
A30: 10001296 | B30: GH MALL ADMIN RELOCATION AND CONVERSION | C30: IO CAPEX | D30: 4500027836 | E30: 5100047378 | F30: -26785.72 | G30: SUPPLY OF GRANDSTREAM IP PHONES DEVICES | H30: 4500027836 | I30: 0 | J30: S | K30: 21301102 | L30: Trade A/P Clearing | M30: 2 | N30: =_xlfn.XLOOKUP(M30,$Q$3:$Q$14,$R$3:$R$14) -> Feb
A31: 10001296 | B31: GH MALL ADMIN RELOCATION AND CONVERSION | C31: IO CAPEX | D31: 4500027836 | E31: 5000054748 | F31: 197321.43 | G31: SUPPLY OF GRANDSTREAM IP PHONES DEVICES | I31: 1 | J31: S | K31: 21301102 | L31: Trade A/P Clearing | M31: 2 | N31: =_xlfn.XLOOKUP(M31,$Q$3:$Q$14,$R$3:$R$14) -> Feb
A32: 10001298 | B32: CC DRAINAGE IMPROVEMENT PH1A | C32: IO CAPEX | E32: 1900352470 | F32: -0.01 | H32: PO#4500027421 | I32: 0 | J32: K | K32: 60000112 | L32: ADBASCO ENGINEERING WORKS AND | M32: 6 | N32: =_xlfn.XLOOKUP(M32,$Q$3:$Q$14,$R$3:$R$14) -> Jun
A33: 10001311 | B33: SC2&3 WATER PROOFING OF ROOF DECK FLOORI | C33: IO CAPEX | D33: 4500030775 | E33: 5000055255 | F33: 3161591.1 | G33: WATERPROOFING OF SC 2 (2,232.33sqm) | I33: 1 | J33: S | K33: 21301102 | L33: Trade A/P Clearing | M33: 3 | N33: =_xlfn.XLOOKUP(M33,$Q$3:$Q$14,$R$3:$R$14) -> Mar
A34: 10001314 | B34: GH TOWER BIR FIT-OUT | C34: IO CAPEX | D34: 4500030726 | E34: 5000055868 | F34: 42410.71 | G34: Solid Wood Top Mahogany | H34: BIR SAN JUAN-FB-AADD | I34: 1 | J34: S | K34: 21301102 | L34: Trade A/P Clearing | M34: 4 | N34: =_xlfn.XLOOKUP(M34,$Q$3:$Q$14,$R$3:$R$14) -> Apr
A35: 10001314 | B35: GH TOWER BIR FIT-OUT | C35: IO CAPEX | D35: 4500030726 | E35: 5000055867 | F35: 55803.57 | G35: Solid Wood Top Mahogany | H35: BIR SAN JUAN-FB-AADD | I35: 1 | J35: S | K35: 21301102 | L35: Trade A/P Clearing | M35: 4 | N35: =_xlfn.XLOOKUP(M35,$Q$3:$Q$14,$R$3:$R$14) -> Apr
A36: 10001314 | B36: GH TOWER BIR FIT-OUT | C36: IO CAPEX | D36: 4500030253 | E36: 5100047916 | F36: 0.01 | G36: 6-DOOR LOCKER | H36: 4500030253 | I36: 0 | J36: K | K36: 60003928 | L36: EXTENSIVE SALES ENTERPRISES COMPANY | M36: 3 | N36: =_xlfn.XLOOKUP(M36,$Q$3:$Q$14,$R$3:$R$14) -> Mar
A37: 10001314 | B37: GH TOWER BIR FIT-OUT | C37: IO CAPEX | D37: 4500030253 | E37: 5100047915 | F37: -0.01 | G37: 6-DOOR LOCKER | H37: 4500030253 | I37: 0 | J37: K | K37: 60003928 | L37: EXTENSIVE SALES ENTERPRISES COMPANY | M37: 3 | N37: =_xlfn.XLOOKUP(M37,$Q$3:$Q$14,$R$3:$R$14) -> Mar
A38: 10001314 | B38: GH TOWER BIR FIT-OUT | C38: IO CAPEX | D38: 4500032520 | E38: 5000057367 | F38: 53571.43 | G38: Supply of Imported Manual Curtain | H38: BIR SAN JUAN-FB-MCIP | I38: 1 | J38: S | K38: 21301102 | L38: Trade A/P Clearing | M38: 7 | N38: =_xlfn.XLOOKUP(M38,$Q$3:$Q$14,$R$3:$R$14) -> Jul
A39: 10001314 | B39: GH TOWER BIR FIT-OUT | C39: IO CAPEX | D39: 4500030726 | E39: 5100048423 | F39: 0.01 | G39: Solid Wood Top Mahogany | H39: 4500030726 | I39: 0 | J39: K | K39: 60002241 | L39: AADD OFFICE FURNITURE TRADING | M39: 4 | N39: =_xlfn.XLOOKUP(M39,$Q$3:$Q$14,$R$3:$R$14) -> Apr
A40: 10001314 | B40: GH TOWER BIR FIT-OUT | C40: IO CAPEX | D40: 4500030253 | E40: 5100047914 | F40: 0.01 | G40: 6-DOOR LOCKER | H40: 4500030253 | I40: 0 | J40: K | K40: 60003928 | L40: EXTENSIVE SALES ENTERPRISES COMPANY | M40: 3 | N40: =_xlfn.XLOOKUP(M40,$Q$3:$Q$14,$R$3:$R$14) -> Mar
A41: 10001314 | B41: GH TOWER BIR FIT-OUT | C41: IO CAPEX | D41: 4500030253 | E41: 5100047912 | F41: -0.01 | G41: 6-DOOR LOCKER | H41: 4500030253 | I41: 0 | J41: K | K41: 60003928 | L41: EXTENSIVE SALES ENTERPRISES COMPANY | M41: 3 | N41: =_xlfn.XLOOKUP(M41,$Q$3:$Q$14,$R$3:$R$14) -> Mar
A42: 10001314 | B42: GH TOWER BIR FIT-OUT | C42: IO CAPEX | D42: 4500030839 | E42: 5000054834 | F42: 297953.57 | G42: S&D of Sheer Curtains | H42: BIR SAN JUAN-FB-MCIP | I42: 1 | J42: S | K42: 21301102 | L42: Trade A/P Clearing | M42: 2 | N42: =_xlfn.XLOOKUP(M42,$Q$3:$Q$14,$R$3:$R$14) -> Feb
A43: 10001314 | B43: GH TOWER BIR FIT-OUT | C43: IO CAPEX | D43: 4500030253 | E43: 5000057741 | F43: 12964.72 | G43: 4-LAYER VERTICAL FILING CABINET | H43: BIR SAN JUAN-FB-EXTENSIVE | I43: 2 | J43: S | K43: 21301102 | L43: Trade A/P Clearing | M43: 8 | N43: =_xlfn.XLOOKUP(M43,$Q$3:$Q$14,$R$3:$R$14) -> Aug
A44: 10001314 | B44: GH TOWER BIR FIT-OUT | C44: IO CAPEX | D44: 4500030253 | E44: 5000057740 | F44: 21774.08 | G44: 4-LAYER LATERAL CABINET | H44: BIR SAN JUAN-FB-EXTENSIVE | I44: 2 | J44: S | K44: 21301102 | L44: Trade A/P Clearing | M44: 8 | N44: =_xlfn.XLOOKUP(M44,$Q$3:$Q$14,$R$3:$R$14) -> Aug
A45: 10001314 | B45: GH TOWER BIR FIT-OUT | C45: IO CAPEX | D45: 4500031531 | E45: 5000057736 | F45: 5491.07 | G45: E-Lounge 2 seater | H45: BIR SAN JUAN-FB-EXTENSIVE | I45: 2 | J45: S | K45: 21301102 | L45: Trade A/P Clearing | M45: 8 | N45: =_xlfn.XLOOKUP(M45,$Q$3:$Q$14,$R$3:$R$14) -> Aug
... A47: 10001314 | B47: GH TOWER BIR FIT-OUT | C47: IO CAPEX | D47: 4500031531 | E47: 5000057734 | F47: 10125 | G47: Grommet | H47: BIR SAN JUAN-FB-EXTENSIVE | I47: 126 | J47: S | K47: 21301102 | L47: Trade A/P Clearing | M47: 8 | N47: =_xlfn.XLOOKUP(M47,$Q$3:$Q$14,$R$3:$R$14) -> Aug
A48: 10001314 | B48: GH TOWER BIR FIT-OUT | C48: IO CAPEX | E48: 1700003462 | F48: 1507573.5 | H48: 4500028599 | I48: 0 | J48: K | K48: 60002970 | L48: FORMS & LINES EXCELLENCE CONSTRUCTI | M48: 4 | N48: =_xlfn.XLOOKUP(M48,$Q$3:$Q$14,$R$3:$R$14) -> Apr
A49: 10001314 | B49: GH TOWER BIR FIT-OUT | C49: IO CAPEX | D49: 4500030729 | E49: 5000055568 | F49: 508928.57 | G49: Supply & Installation of Signages | H49: BIR SAN JUAN-FB-SUPER8 A1 | I49: 1 | J49: S | K49: 21301102 | L49: Trade A/P Clearing | M49: 4 | N49: =_xlfn.XLOOKUP(M49,$Q$3:$Q$14,$R$3:$R$14) -> Apr
A50: 10001314 | B50: GH TOWER BIR FIT-OUT | C50: IO CAPEX | D50: 4500030966 | E50: 5000055525 | F50: 1446428.6 | G50: Various revisions requested by BIR | H50: BIR SAN JUAN-FBCO3-FLECS | I50: 1 | J50: S | K50: 21301102 | L50: Trade A/P Clearing | M50: 4 | N50: =_xlfn.XLOOKUP(M50,$Q$3:$Q$14,$R$3:$R$14) -> Apr
A51: 10001314 | B51: GH TOWER BIR FIT-OUT | C51: IO CAPEX | D51: 4500030682 | E51: 5000055524 | F51: 347311.3 | G51: Add'l Works @ BIR Office | H51: BIR SAN JUAN-FBCO2-FLECS | I51: 1 | J51: S | K51: 21301102 | L51: Trade A/P Clearing | M51: 4 | N51: =_xlfn.XLOOKUP(M51,$Q$3:$Q$14,$R$3:$R$14) -> Apr
A52: 10001314 | B52: GH TOWER BIR FIT-OUT | C52: IO CAPEX | D52: 4500028599 | E52: 5000055523 | F52: 2501811.3 | G52: Fit-Out Works | H52: BIR SAN JUAN-FB-FLECS | I52: 0.115 | J52: S | K52: 21301102 | L52: Trade A/P Clearing | M52: 4 | N52: =_xlfn.XLOOKUP(M52,$Q$3:$Q$14,$R$3:$R$14) -> Apr
A53: 10001314 | B53: GH TOWER BIR FIT-OUT | C53: IO CAPEX | E53: 1900040646 | F53: -1397102.6 | H53: 4500028599 | I53: 0 | J53: K | K53: 60002970 | L53: FORMS & LINES EXCELLENCE CONSTRUCTI | M53: 4 | N53: =_xlfn.XLOOKUP(M53,$Q$3:$Q$14,$R$3:$R$14) -> Apr
A54: 10001314 | B54: GH TOWER BIR FIT-OUT | C54: IO CAPEX | E54: 1900040644 | F54: -1507573.5 | H54: 4500028599 | I54: 0 | J54: K | K54: 60002970 | L54: FORMS & LINES EXCELLENCE CONSTRUCTI | M54: 4 | N54: =_xlfn.XLOOKUP(M54,$Q$3:$Q$14,$R$3:$R$14) -> Apr
A55: 10001314 | B55: GH TOWER BIR FIT-OUT | C55: IO CAPEX | D55: 4500030253 | E55: 5100047910 | F55: 0.01 | G55: 6-DOOR LOCKER | H55: 4500030253 | I55: 0 | J55: K | K55: 60003928 | L55: EXTENSIVE SALES ENTERPRISES COMPANY | M55: 3 | N55: =_xlfn.XLOOKUP(M55,$Q$3:$Q$14,$R$3:$R$14) -> Mar
A56: 10001314 | B56: GH TOWER BIR FIT-OUT | C56: IO CAPEX | D56: 4500030253 | E56: 5100047844 | F56: 0.01 | G56: 6-DOOR LOCKER | H56: 4500030253 | I56: 0 | J56: K | K56: 60003928 | L56: EXTENSIVE SALES ENTERPRISES COMPANY | M56: 3 | N56: =_xlfn.XLOOKUP(M56,$Q$3:$Q$14,$R$3:$R$14) -> Mar
A57: 10001314 | B57: GH TOWER BIR FIT-OUT | C57: IO CAPEX | D57: 4500030253 | E57: 5000055179 | F57: 7215 | G57: 6-DOOR LOCKER | H57: BIR SAN JUAN-PB#2-EXTENSI | I57: 1 | J57: S | K57: 21301102 | L57: Trade A/P Clearing | M57: 3 | N57: =_xlfn.XLOOKUP(M57,$Q$3:$Q$14,$R$3:$R$14) -> Mar
A58: 10001314 | B58: GH TOWER BIR FIT-OUT | C58: IO CAPEX | D58: 4500030253 | E58: 5000055178 | F58: 449984.08 | G58: 3-LAYER MOBILE PEDESTAL | H58: BIR SAN JUAN-PB#2-EXTENSI | I58: 91 | J58: S | K58: 21301102 | L58: Trade A/P Clearing | M58: 3 | N58: =_xlfn.XLOOKUP(M58,$Q$3:$Q$14,$R$3:$R$14) -> Mar
A59: 10001314 | B59: GH TOWER BIR FIT-OUT | C59: IO CAPEX | D59: 4500030253 | E59: 5000055177 | F59: 369494.52 | G59: 4-LAYER VERTICAL FILING CABINET | H59: BIR SAN JUAN-PB#2-EXTENSI | I59: 57 | J59: S | K59: 21301102 | L59: Trade A/P Clearing | M59: 3 | N59: =_xlfn.XLOOKUP(M59,$Q$3:$Q$14,$R$3:$R$14) -> Mar
A60: 10001314 | B60: GH TOWER BIR FIT-OUT | C60: IO CAPEX | D60: 4500030253 | E60: 5000055176 | F60: 424594.56 | G60: 4-LAYER LATERAL CABINET | H60: BIR SAN JUAN-PB#2-EXTENSI | I60: 39 | J60: S | K60: 21301102 | L60: Trade A/P Clearing | M60: 3 | N60: =_xlfn.XLOOKUP(M60,$Q$3:$Q$14,$R$3:$R$14) -> Mar
A61: 10001314 | B61: GH TOWER BIR FIT-OUT | C61: IO CAPEX | D61: 4500030253 | E61: 5000055174 | F61: 446368.64 | G61: 4-LAYER LATERAL CABINET | H61: BIR SAN JUAN-PB#2-EXTENSI | I61: 41 | J61: S | K61: 21301102 | L61: Trade A/P Clearing | M61: 3 | N61: =_xlfn.XLOOKUP(M61,$Q$3:$Q$14,$R$3:$R$14) -> Mar
A62: 10001314 | B62: GH TOWER BIR FIT-OUT | C62: IO CAPEX | D62: 4500030253 | E62: 5100047908 | F62: -0.01 | G62: 6-DOOR LOCKER | H62: 4500030253 | I62: 0 | J62: K | K62: 60003928 | L62: EXTENSIVE SALES ENTERPRISES COMPANY | M62: 3 | N62: =_xlfn.XLOOKUP(M62,$Q$3:$Q$14,$R$3:$R$14) -> Mar
A63: 10001314 | B63: GH TOWER BIR FIT-OUT | C63: IO CAPEX | D63: 4500030253 | E63: 5000055175 | F63: -446368.64 | G63: 4-LAYER LATERAL CABINET | H63: BIR SAN JUAN-PB#2-EXTENSI | I63: -41 | J63: S | K63: 21301102 | L63: Trade A/P Clearing | M63: 3 | N63: =_xlfn.XLOOKUP(M63,$Q$3:$Q$14,$R$3:$R$14) -> Mar
A64: 10001314 | B64: GH TOWER BIR FIT-OUT | C64: IO CAPEX | E64: 1900039074 | F64: 111598.21 | I64: 0 | J64: K | K64: 60002447 | L64: CASAMIA FURNITURE CENTER, INC. | M64: 1 | N64: =_xlfn.XLOOKUP(M64,$Q$3:$Q$14,$R$3:$R$14) -> Jan
A65: 10001314 | B65: GH TOWER BIR FIT-OUT | C65: IO CAPEX | E65: 1900038912 | F65: 24506.25 | I65: 0 | J65: K | K65: 60001147 | L65: BARANGAY GREENHILLS | M65: 1 | N65: =_xlfn.XLOOKUP(M65,$Q$3:$Q$14,$R$3:$R$14) -> Jan
A66: 10001314 | B66: GH TOWER BIR FIT-OUT | C66: IO CAPEX | D66: 4500030253 | E66: 5000054694 | F66: 153365.67 | G66: 5-SEATER GANG CHAIR | H66: BIR SAN JUAN-PB#1-EXTENSI | I66: 9 | J66: S | K66: 21301102 | L66: Trade A/P Clearing | M66: 2 | N66: =_xlfn.XLOOKUP(M66,$Q$3:$Q$14,$R$3:$R$14) -> Feb
A67: 10001314 | B67: GH TOWER BIR FIT-OUT | C67: IO CAPEX | D67: 4500030253 | E67: 5000054696 | F67: 30464.49 | G67: 3-SEATER GANG CHAIR | H67: BIR SAN JUAN-PB#1-EXTENSI | I67: 3 | J67: S | K67: 21301102 | L67: Trade A/P Clearing | M67: 2 | N67: =_xlfn.XLOOKUP(M67,$Q$3:$Q$14,$R$3:$R$14) -> Feb
A68: 10001314 | B68: GH TOWER BIR FIT-OUT | C68: IO CAPEX | D68: 4500030253 | E68: 5000054698 | F68: 390437.73 | G68: 6-LAYER METAL OPEN SHELVES | H68: BIR SAN JUAN-PB#1-EXTENSI | I68: 87 | J68: S | K68: 21301102 | L68: Trade A/P Clearing | M68: 2 | N68: =_xlfn.XLOOKUP(M68,$Q$3:$Q$14,$R$3:$R$14) -> Feb
A69: 10001314 | B69: GH TOWER BIR FIT-OUT | C69: IO CAPEX | D69: 4500030253 | E69: 5000054699 | F69: 114213.76 | G69: GENERAL STAFF WORKSTATION 8 | H69: BIR SAN JUAN-PB#1-EXTENSI | I69: 2 | J69: S | K69: 21301102 | L69: Trade A/P Clearing | M69: 2 | N69: =_xlfn.XLOOKUP(M69,$Q$3:$Q$14,$R$3:$R$14) -> Feb
A70: 10001314 | B70: GH TOWER BIR FIT-OUT | C70: IO CAPEX | D70: 4500030253 | E70: 5000054705 | F70: 70822.5 | G70: GENERAL STAFF WORKSTATION 4 | H70: BIR SAN JUAN-PB#1-EXTENSI | I70: 2 | J70: S | K70: 21301102 | L70: Trade A/P Clearing | M70: 2 | N70: =_xlfn.XLOOKUP(M70,$Q$3:$Q$14,$R$3:$R$14) -> Feb
A71: 10001314 | B71: GH TOWER BIR FIT-OUT | C71: IO CAPEX | D71: 4500030253 | E71: 5000054706 | F71: 38403.76 | G71: GENERAL STAFF WORKSTATION 2 | H71: BIR SAN JUAN-PB#1-EXTENSI | I71: 2 | J71: S | K71: 21301102 | L71: Trade A/P Clearing | M71: 2 | N71: =_xlfn.XLOOKUP(M71,$Q$3:$Q$14,$R$3:$R$14) -> Feb
A72: 10001314 | B72: GH TOWER BIR FIT-OUT | C72: IO CAPEX | D72: 4500030253 | E72: 5000054707 | F72: 17700.63 | G72: GENERAL STAFF WORKSTATION 3 | H72: BIR SAN JUAN-PB#1-EXTENSI | I72: 1 | J72: S | K72: 21301102 | L72: Trade A/P Clearing | M72: 2 | N72: =_xlfn.XLOOKUP(M72,$Q$3:$Q$14,$R$3:$R$14) -> Feb
A73: 10001314 | B73: GH TOWER BIR FIT-OUT | C73: IO CAPEX | D73: 4500030253 | E73: 5000054717 | F73: 12219.38 | G73: GENERAL STAFF WORKSTATION 2 | H73: BIR SAN JUAN-PB#1-EXTENSI | I73: 1 | J73: S | K73: 21301102 | L73: Trade A/P Clearing | M73: 2 | N73: =_xlfn.XLOOKUP(M73,$Q$3:$Q$14,$R$3:$R$14) -> Feb
A74: 10001314 | B74: GH TOWER BIR FIT-OUT | C74: IO CAPEX | D74: 4500030253 | E74: 5000054718 | F74: 18370.63 | G74: GENERAL STAFF WORKSTATION 2 | H74: BIR SAN JUAN-PB#1-EXTENSI | I74: 1 | J74: S | K74: 21301102 | L74: Trade A/P Clearing | M74: 2 | N74: =_xlfn.XLOOKUP(M74,$Q$3:$Q$14,$R$3:$R$14) -> Feb
A75: 10001314 | B75: GH TOWER BIR FIT-OUT | C75: IO CAPEX | D75: 4500030253 | E75: 5000054719 | F75: 47547.5 | G75: GENERAL STAFF WORKSTATION + SW | H75: BIR SAN JUAN-PB#1-EXTENSI | I75: 2 | J75: S | K75: 21301102 | L75: Trade A/P Clearing | M75: 2 | N75: =_xlfn.XLOOKUP(M75,$Q$3:$Q$14,$R$3:$R$14) -> Feb
A76: 10001314 | B76: GH TOWER BIR FIT-OUT | C76: IO CAPEX | D76: 4500030253 | E76: 5000054720 | F76: 25768.75 | G76: GENERAL STAFF WORKSTATION 3 | H76: BIR SAN JUAN-PB#1-EXTENSI | I76: 1 | J76: S | K76: 21301102 | L76: Trade A/P Clearing | M76: 2 | N76: =_xlfn.XLOOKUP(M76,$Q$3:$Q$14,$R$3:$R$14) -> Feb
A77: 10001314 | B77: GH TOWER BIR FIT-OUT | C77: IO CAPEX | D77: 4500030253 | E77: 5000054721 | F77: 31504.38 | G77: GENERAL STAFF WORKSTATION + SW | H77: BIR SAN JUAN-PB#1-EXTENSI | I77: 1 | J77: S | K77: 21301102 | L77: Trade A/P Clearing | M77: 2 | N77: =_xlfn.XLOOKUP(M77,$Q$3:$Q$14,$R$3:$R$14) -> Feb
... A93: 10001314 | B93: GH TOWER BIR FIT-OUT | C93: IO CAPEX | D93: 4500030253 | E93: 5000054683 | F93: -106537.2 | G93: HIGH BACK CHAIR | H93: BIR SAN JUAN-PB#1-EXTENSI | I93: -20 | J93: S | K93: 21301102 | L93: Trade A/P Clearing | M93: 2 | N93: =_xlfn.XLOOKUP(M93,$Q$3:$Q$14,$R$3:$R$14) -> Feb
A94: 10001314 | B94: GH TOWER BIR FIT-OUT | C94: IO CAPEX | D94: 4500030253 | E94: 5000054684 | F94: -224727 | G94: LOW BACK CHAIR | I94: -75 | J94: S | K94: 21301102 | L94: Trade A/P Clearing | M94: 2 | N94: =_xlfn.XLOOKUP(M94,$Q$3:$Q$14,$R$3:$R$14) -> Feb
A95: 10001314 | B95: GH TOWER BIR FIT-OUT | C95: IO CAPEX | D95: 4500030839 | E95: 5000054619 | F95: 210975 | G95: S&D of Roll-up Shades | H95: BIR SAN JUAN-FB-MCIP | I95: 1 | J95: S | K95: 21301102 | L95: Trade A/P Clearing | M95: 2 | N95: =_xlfn.XLOOKUP(M95,$Q$3:$Q$14,$R$3:$R$14) -> Feb
A96: 10001314 | B96: GH TOWER BIR FIT-OUT | C96: IO CAPEX | D96: 4500029413 | E96: 5000054623 | F96: 172187.5 | G96: S&I of FDAS | H96: BIR SAN JUAN-FB-JPRIME | I96: 0.203 | J96: S | K96: 21301102 | L96: Trade A/P Clearing | M96: 2 | N96: =_xlfn.XLOOKUP(M96,$Q$3:$Q$14,$R$3:$R$14) -> Feb
A97: 10001314 | B97: GH TOWER BIR FIT-OUT | C97: IO CAPEX | D97: 4500030253 | E97: 5000054674 | F97: 15730.88 | G97: EXECUTIVE CHAIR (brown) | H97: BIR SAN JUAN-PB#1-EXTENSI | I97: 1 | J97: S | K97: 21301102 | L97: Trade A/P Clearing | M97: 2 | N97: =_xlfn.XLOOKUP(M97,$Q$3:$Q$14,$R$3:$R$14) -> Feb
A98: 10001314 | B98: GH TOWER BIR FIT-OUT | C98: IO CAPEX | D98: 4500030253 | E98: 5000054675 | F98: 106537.2 | G98: HIGH BACK CHAIR | H98: BIR SAN JUAN-PB#1-EXTENSI | I98: 20 | J98: S | K98: 21301102 | L98: Trade A/P Clearing | M98: 2 | N98: =_xlfn.XLOOKUP(M98,$Q$3:$Q$14,$R$3:$R$14) -> Feb
A99: 10001314 | B99: GH TOWER BIR FIT-OUT | C99: IO CAPEX | D99: 4500030253 | E99: 5000054676 | F99: 224727 | G99: LOW BACK CHAIR | I99: 75 | J99: S | K99: 21301102 | L99: Trade A/P Clearing | M99: 2 | N99: =_xlfn.XLOOKUP(M99,$Q$3:$Q$14,$R$3:$R$14) -> Feb
A100: 10001314 | B100: GH TOWER BIR FIT-OUT | C100: IO CAPEX | D100: 4500030253 | E100: 5000054685 | F100: 106537.2 | G100: HIGH BACK CHAIR | H100: BIR SAN JUAN-PB#1-EXTENSI | I100: 20 | J100: S | K100: 21301102 | L100: Trade A/P Clearing | M100: 2 | N100: =_xlfn.XLOOKUP(M100,$Q$3:$Q$14,$R$3:$R$14) -> Feb
A101: 10001314 | B101: GH TOWER BIR FIT-OUT | C101: IO CAPEX | D101: 4500030253 | E101: 5000054686 | F101: 224727 | G101: LOW BACK CHAIR | H101: BIR SAN JUAN-PB#1-EXTENSI | I101: 75 | J101: S | K101: 21301102 | L101: Trade A/P Clearing | M101: 2 | N101: =_xlfn.XLOOKUP(M101,$Q$3:$Q$14,$R$3:$R$14) -> Feb
A102: 10001314 | B102: GH TOWER BIR FIT-OUT | C102: IO CAPEX | D102: 4500030253 | E102: 5000054688 | F102: 15730.88 | G102: EXECUTIVE CHAIR (black) | H102: BIR SAN JUAN-PB#1-EXTENSI | I102: 1 | J102: S | K102: 21301102 | L102: Trade A/P Clearing | M102: 2 | N102: =_xlfn.XLOOKUP(M102,$Q$3:$Q$14,$R$3:$R$14) -> Feb
A103: 10001314 | B103: GH TOWER BIR FIT-OUT | C103: IO CAPEX | D103: 4500030253 | E103: 5000054689 | F103: 245535 | G103: MID BACK CHAIR | H103: BIR SAN JUAN-PB#1-EXTENSI | I103: 50 | J103: S | K103: 21301102 | L103: Trade A/P Clearing | M103: 2 | N103: =_xlfn.XLOOKUP(M103,$Q$3:$Q$14,$R$3:$R$14) -> Feb
A104: 10001314 | B104: GH TOWER BIR FIT-OUT | C104: IO CAPEX | D104: 4500030253 | E104: 5000054690 | F104: 101626.47 | G104: GUEST CHAIR | H104: BIR SAN JUAN-PB#1-EXTENSI | I104: 33 | J104: S | K104: 21301102 | L104: Trade A/P Clearing | M104: 2 | N104: =_xlfn.XLOOKUP(M104,$Q$3:$Q$14,$R$3:$R$14) -> Feb
A105: 10001314 | B105: GH TOWER BIR FIT-OUT | C105: IO CAPEX | D105: 4500030253 | E105: 5000054691 | F105: 101377.08 | G105: MULTIPURPOSE CHAIR | H105: BIR SAN JUAN-PB#1-EXTENSI | I105: 84 | J105: S | K105: 21301102 | L105: Trade A/P Clearing | M105: 2 | N105: =_xlfn.XLOOKUP(M105,$Q$3:$Q$14,$R$3:$R$14) -> Feb
A106: 10001314 | B106: GH TOWER BIR FIT-OUT | C106: IO CAPEX | D106: 4500030253 | E106: 5000054692 | F106: 4268.9 | G106: GUARD CHAIR | H106: BIR SAN JUAN-PB#1-EXTENSI | I106: 2 | J106: S | K106: 21301102 | L106: Trade A/P Clearing | M106: 2 | N106: =_xlfn.XLOOKUP(M106,$Q$3:$Q$14,$R$3:$R$14) -> Feb
A107: 10001314 | B107: GH TOWER BIR FIT-OUT | C107: IO CAPEX | D107: 4500030253 | E107: 5000054693 | F107: 7490.9 | G107: HIGH CHAIR | H107: BIR SAN JUAN-PB#1-EXTENSI | I107: 5 | J107: S | K107: 21301102 | L107: Trade A/P Clearing | M107: 2 | N107: =_xlfn.XLOOKUP(M107,$Q$3:$Q$14,$R$3:$R$14) -> Feb
A108: 10001315 | B108: GH MALL VIP READER SYSTEM FOR B2 PARKING | C108: IO CAPEX | D108: 4500029627 | E108: 5000054466 | F108: 26321.43 | G108: HANABISHI AIR COOLER 10L MODEL: HAC-500 | I108: 4 | J108: S | K108: 21301102 | L108: Trade A/P Clearing | M108: 1 | N108: =_xlfn.XLOOKUP(M108,$Q$3:$Q$14,$R$3:$R$14) -> Jan
A109: 10001315 | B109: GH MALL VIP READER SYSTEM FOR B2 PARKING | C109: IO CAPEX | D109: 4500028985 | E109: 5000054447 | F109: 107142.86 | G109: S&I PROVISION OF POWER SUPPLY | I109: 1 | J109: S | K109: 21301102 | L109: Trade A/P Clearing | M109: 1 | N109: =_xlfn.XLOOKUP(M109,$Q$3:$Q$14,$R$3:$R$14) -> Jan
A110: 10001322 | B110: CC DRAINAGE IMPROVEMENT PHASE 2 | C110: IO CAPEX | D110: 4500028576 | E110: 5000057014 | F110: -6750000 | G110: CC Drainage System Improvement Ph2 | I110: -0.45 | J110: S | K110: 21301102 | L110: Trade A/P Clearing | M110: 7 | N110: =_xlfn.XLOOKUP(M110,$Q$3:$Q$14,$R$3:$R$14) -> Jul
A111: 10001322 | B111: CC DRAINAGE IMPROVEMENT PHASE 2 | C111: IO CAPEX | D111: 4500028576 | E111: 5000057015 | F111: 6300000 | G111: CC Drainage System Improvement Ph2 | I111: 0.42 | J111: S | K111: 21301102 | L111: Trade A/P Clearing | M111: 7 | N111: =_xlfn.XLOOKUP(M111,$Q$3:$Q$14,$R$3:$R$14) -> Jul
A112: 10001322 | B112: CC DRAINAGE IMPROVEMENT PHASE 2 | C112: IO CAPEX | D112: 4500028576 | E112: 5000056371 | F112: 6750000 | G112: CC Drainage System Improvement Ph2 | I112: 0.45 | J112: S | K112: 21301102 | L112: Trade A/P Clearing | M112: 5 | N112: =_xlfn.XLOOKUP(M112,$Q$3:$Q$14,$R$3:$R$14) -> May
A113: 10001340 | B113: IBP ACP REPLACEMENT & PUMP ROOM COVER | C113: IO CAPEX | D113: 4500029701 | E113: 5000055400 | F113: 285714.29 | G113: ACP REPLACEMENT IN 10/F VERANDA | I113: 1 | J113: S | K113: 21301102 | L113: Trade A/P Clearing | M113: 3 | N113: =_xlfn.XLOOKUP(M113,$Q$3:$Q$14,$R$3:$R$14) -> Mar
A114: 10001341 | B114: CC PARK REDEVELOPMENT | C114: IO CAPEX | D114: 4500029576 | E114: 5000055215 | F114: 411428.57 | G114: S&D of Tiles for CC Redevelopment | H114: FB -CEBUOVERSEA-45-29576 | I114: 1440 | J114: S | K114: 21301102 | L114: Trade A/P Clearing | M114: 3 | N114: =_xlfn.XLOOKUP(M114,$Q$3:$Q$14,$R$3:$R$14) -> Mar
A115: 10001341 | B115: CC PARK REDEVELOPMENT | C115: IO CAPEX | D115: 4500029576 | E115: 5000055210 | F115: 274285.71 | G115: S&D of Tiles for CC Redevelopment | H115: PB#7CEBUOVERSEA-45-29576 | I115: 960 | J115: S | K115: 21301102 | L115: Trade A/P Clearing | M115: 3 | N115: =_xlfn.XLOOKUP(M115,$Q$3:$Q$14,$R$3:$R$14) -> Mar
A116: 10001341 | B116: CC PARK REDEVELOPMENT | C116: IO CAPEX | D116: 4500029576 | E116: 5000055209 | F116: 458285.71 | G116: S&D of Tiles for CC Redevelopment | H116: PB#6CEBUOVERSEA-45-29576 | I116: 1604 | J116: S | K116: 21301102 | L116: Trade A/P Clearing | M116: 3 | N116: =_xlfn.XLOOKUP(M116,$Q$3:$Q$14,$R$3:$R$14) -> Mar
...

Sheet Open PR PO
K1: =SUBTOTAL(9,K3:K1048576) -> 2.3412822e+08
A2: Order | B2: Cost element | C2: Company Code | D2: Document Date | E2: Debit date | F2: Reference document category | G2: Ref Document Number | H2: Name | I2: Total Quantity | J2: Unit of Measure | K2: Val.in rep.cur. | L2: Vendor | M2: User Name | N2: SBU
A3: 10000820 | B3: 78011101 | C3: 8000 | D3: 44483 | E3: 44497 | F3: POrd | G3: 4500016839 | H3: GH VMALL PARK DESIGN | I3: 0.35 | J3: LOT | K3: 278125 | L3: 60000389 | M3: LOPEZMV | N3: =_xlfn.XLOOKUP(A3,Monitoring!A:A,Monitoring!D:D) -> ESTATES
A4: 10001021 | B4: 78011101 | C4: 8000 | D4: 44776 | E4: 44790 | F4: POrd | G4: 4500019107 | H4: Utilities Relocation-Citiaire | I4: 0.157 | J4: LOT | K4: 3224107.1 | L4: 60000181 | M4: VIGALDF | N4: =_xlfn.XLOOKUP(A4,Monitoring!A:A,Monitoring!D:D) -> ESTATES
A5: 10001021 | B5: 78011101 | C5: 8000 | D5: 45847 | E5: 45861 | F5: POrd | G5: 4500028834 | H5: GH STREETSCAPING SIGNAGES | I5: 1 | J5: LOT | K5: 1160714.3 | L5: 60003122 | M5: CAMPONGSI | N5: =_xlfn.XLOOKUP(A5,Monitoring!A:A,Monitoring!D:D) -> ESTATES
A6: 10001021 | B6: 78011101 | C6: 8000 | D6: 45357 | E6: 45341 | F6: POrd | G6: 4500024077 | H6: S&I ELECTRICAL WORKS AT GH STREETSCAPE | I6: 0.1 | J6: LOT | K6: 441964.29 | L6: 60003331 | M6: VIGALDF | N6: =_xlfn.XLOOKUP(A6,Monitoring!A:A,Monitoring!D:D) -> ESTATES
A7: 10001021 | B7: 78011101 | C7: 8000 | D7: 44810 | E7: 44809 | F7: POrd | G7: 4500019418 | H7: Upon Project Completion | I7: 1 | J7: LOT | K7: 28839.29 | L7: 60002908 | M7: ABEJARND | N7: =_xlfn.XLOOKUP(A7,Monitoring!A:A,Monitoring!D:D) -> ESTATES
A8: 10001072 | B8: 78011101 | C8: 8100 | D8: 45159 | E8: 45163 | F8: POrd | G8: 4500022241 | H8: RECTIFICATION OF LEAK AT SHOPPESVILLE | I8: 1 | J8: LOT | K8: 142000 | L8: 60002847 | M8: AGUILARIB | N8: =_xlfn.XLOOKUP(A8,Monitoring!A:A,Monitoring!D:D) -> MALLS
A9: 10001134 | B9: 78011101 | C9: 8100 | D9: 45223 | E9: 45219 | F9: POrd | G9: 4500022912 | H9: EIFS DROPWALL | I9: 0.247 | J9: LOT | K9: 789517.86 | L9: 60003426 | M9: AP_OFC | N9: =_xlfn.XLOOKUP(A9,Monitoring!A:A,Monitoring!D:D) -> MALLS
A10: 10001136 | B10: 78011101 | C10: 8000 | D10: 45245 | E10: 46022 | F10: POrd | G10: 4500023106 | H10: Supply and installation of 4Units AC | I10: 0 | J10: LOT | K10: 0 | L10: 60000283 | M10: AP_RED | N10: =_xlfn.XLOOKUP(A10,Monitoring!A:A,Monitoring!D:D) -> RESIDENTIAL
A11: 10001140 | B11: 78011101 | C11: 8000 | D11: 45273 | E11: 45289 | F11: POrd | G11: 4500023470 | H11: AC DISMANTLING AND INSTALLATION WORKS | I11: 1 | J11: LOT | K11: 232142.86 | L11: 60002981 | M11: MAGABILINPR | N11: =_xlfn.XLOOKUP(A11,Monitoring!A:A,Monitoring!D:D) -> RESIDENTIAL
A12: 10001190 | B12: 78011101 | C12: 8100 | D12: 46006 | E12: 46022 | F12: POrd | G12: 4500030671 | H12: Rehabilitation of VRF at SC4 | I12: 0 | J12: LOT | K12: 0 | L12: 60003230 | M12: DEJORASTJO | N12: =_xlfn.XLOOKUP(A12,Monitoring!A:A,Monitoring!D:D) -> OFFICES
A13: 10001220 | B13: 78011101 | C13: 8000 | D13: 45790 | E13: 45790 | F13: POrd | G13: 4500028247 | H13: GH Estate Lift Station | I13: 0.02 | J13: LOT | K13: 99196.43 | L13: 60000181 | M13: DEJORASTJO | N13: =_xlfn.XLOOKUP(A13,Monitoring!A:A,Monitoring!D:D) -> ESTATES
A14: 10001254 | B14: 78011101 | C14: 8100 | D14: 45708 | E14: 45688 | F14: POrd | G14: 4500027401 | H14: S/S UTILITY & MOP SINK W/ FAUCET (PRIMY) | I14: 1 | J14: SET | K14: 23959.82 | L14: 60002230 | M14: CABATAYAD | N14: =_xlfn.XLOOKUP(A14,Monitoring!A:A,Monitoring!D:D) -> MALLS
... A25: 10001281 | B25: 78011101 | C25: 8100 | D25: 46049 | E25: 46112 | F25: POrd | G25: 4500030775 | H25: WATERPROOFING OF SC 2 (352.42sqm) | I25: 0 | J25: LOT | K25: 0 | L25: 60002847 | M25: DEJORASTJO | N25: =_xlfn.XLOOKUP(A25,Monitoring!A:A,Monitoring!D:D) -> OFFICES
A26: 10001281 | B26: 78011101 | C26: 8100 | D26: 46038 | E26: 46052 | F26: PReq | G26: 10032488 | H26: WATERPROOFING OF SC 2 | I26: 0 | J26: LOT | K26: 0 | M26: PANGANIBANCJ | N26: =_xlfn.XLOOKUP(A26,Monitoring!A:A,Monitoring!D:D) -> OFFICES
A27: 10001281 | B27: 78011101 | C27: 8100 | D27: 45806 | E27: 45900 | F27: POrd | G27: 4500028439 | H27: WATERPROOFING OF SC4 - 3,250 sq.m | I27: 0.28 | J27: LOT | K27: 1031737.5 | L27: 60003988 | M27: DEJORASTJO | N27: =_xlfn.XLOOKUP(A27,Monitoring!A:A,Monitoring!D:D) -> OFFICES
A28: 10001288 | B28: 78011101 | C28: 8100 | D28: 45973 | E28: 45961 | F28: POrd | G28: 4500030299 | H28: SUPPLY & INSTALLATION OF ISOLATOR SPRING | I28: 1 | J28: LOT | K28: 7500 | L28: 60003096 | M28: CABATAYAD | N28: =_xlfn.XLOOKUP(A28,Monitoring!A:A,Monitoring!D:D) -> MALLS
A29: 10001289 | B29: 78011101 | C29: 8100 | D29: 45796 | E29: 45808 | F29: POrd | G29: 4500028295 | H29: PROV.OF KITCHEN EXHAUST & FRESH AIR DUCT | I29: 1 | J29: LOT | K29: 42857.14 | L29: 60003096 | M29: CABATAYAD | N29: =_xlfn.XLOOKUP(A29,Monitoring!A:A,Monitoring!D:D) -> MALLS
A30: 10001294 | B30: 78011101 | C30: 8000 | D30: 46202 | E30: 46233 | F30: PReq | G30: 10034422 | H30: UPS BATTERY 12V 7AH FOR UPS 650VA | I30: 0 | J30: PC | K30: 0 | M30: CABATAYAD | N30: =_xlfn.XLOOKUP(A30,Monitoring!A:A,Monitoring!D:D) -> MALLS
A31: 10001294 | B31: 78011101 | C31: 8000 | D31: 46217 | E31: 46233 | F31: POrd | G31: 4500032689 | H31: UPS BATTERY 12V 7AH FOR UPS 650VA | I31: 0 | J31: PC | K31: 0 | L31: 60000772 | M31: ORLINAKC | N31: =_xlfn.XLOOKUP(A31,Monitoring!A:A,Monitoring!D:D) -> MALLS
A32: 10001294 | B32: 78011101 | C32: 8000 | D32: 45911 | E32: 45961 | F32: POrd | G32: 4500029617 | H32: Electrical Provision for 427 Stalls | I32: 0 | J32: LOT | K32: 0 | L32: 60003042 | M32: CAMPONGSI | N32: =_xlfn.XLOOKUP(A32,Monitoring!A:A,Monitoring!D:D) -> MALLS
A33: 10001296 | B33: 78011101 | C33: 8100 | D33: 45742 | E33: 45742 | F33: POrd | G33: 4500027836 | H33: SUPPLY OF GRANDSTREAM IP PHONES DEVICES | I33: 0 | J33: LOT | K33: 0 | L33: 60001016 | M33: CAMPONGSI | N33: =_xlfn.XLOOKUP(A33,Monitoring!A:A,Monitoring!D:D) -> MALLS
A34: 10001296 | B34: 78011101 | C34: 8100 | D34: 45742 | E34: 45742 | F34: POrd | G34: 4500027836 | H34: RELOCATION OF EXISTING PANASONIC | I34: 1 | J34: UNI | K34: 19754.46 | L34: 60001016 | M34: CABATAYAD | N34: =_xlfn.XLOOKUP(A34,Monitoring!A:A,Monitoring!D:D) -> MALLS
A35: 10001296 | B35: 78011101 | C35: 8100 | D35: 46079 | E35: 46093 | F35: PReq | G35: 10033015 | H35: ADDITIONAL WORKS AT GH ADMIN NEW OFFICE | I35: 0 | J35: LOT | K35: 0 | M35: PANGANIBANCJ | N35: =_xlfn.XLOOKUP(A35,Monitoring!A:A,Monitoring!D:D) -> MALLS
A36: 10001296 | B36: 78011101 | C36: 8100 | D36: 46080 | E36: 46093 | F36: POrd | G36: 4500031193 | H36: ADDITIONAL WORKS AT GH ADMIN NEW OFFICE | I36: 0 | J36: LOT | K36: 0 | L36: 60002747 | M36: CAMPONGSI | N36: =_xlfn.XLOOKUP(A36,Monitoring!A:A,Monitoring!D:D) -> MALLS
A37: 10001296 | B37: 78011101 | C37: 8100 | D37: 45875 | E37: 45883 | F37: POrd | G37: 4500029152 | H37: WILCON POZZI 959600000583 | I37: 1 | J37: SET | K37: 1055.86 | L37: 60001325 | M37: CABATAYAD | N37: =_xlfn.XLOOKUP(A37,Monitoring!A:A,Monitoring!D:D) -> MALLS
A38: 10001296 | B38: 78011101 | C38: 8100 | D38: 46076 | E38: 46090 | F38: PReq | G38: 10032960 | H38: ADDITIONAL WORKS AT NEW ADMIN OFFICE | I38: 0 | J38: LOT | K38: 0 | M38: CERTIFICOMDL | N38: =_xlfn.XLOOKUP(A38,Monitoring!A:A,Monitoring!D:D) -> MALLS
A39: 10001298 | B39: 78011101 | C39: 8000 | D39: 45792 | E39: 45797 | F39: POrd | G39: 4500028271 | H39: VERIFICATION AND AS-BUILT SURVEY | I39: 0.107 | J39: LOT | K39: 3595.2 | L39: 60003027 | M39: VIGALDF | N39: =_xlfn.XLOOKUP(A39,Monitoring!A:A,Monitoring!D:D) -> ESTATES
A40: 10001298 | B40: 78011101 | C40: 8000 | D40: 45792 | E40: 45797 | F40: POrd | G40: 4500028271 | H40: VERIFICATION AND AS-BUILT SURVEY | I40: 0.107 | J40: LOT | K40: 3595.2 | L40: 60003027 | M40: VIGALDF | N40: =_xlfn.XLOOKUP(A40,Monitoring!A:A,Monitoring!D:D) -> ESTATES
A41: 10001302 | B41: 78011101 | C41: 8100 | D41: 45757 | E41: 45763 | F41: POrd | G41: 4500028004 | H41: ADDITIONAL PROVISION OF COLD WATERLINE | I41: 1 | J41: LOT | K41: 42857.14 | L41: 60000181 | M41: CABATAYAD | N41: =_xlfn.XLOOKUP(A41,Monitoring!A:A,Monitoring!D:D) -> MALLS
A42: 10001302 | B42: 78011101 | C42: 8100 | D42: 45755 | E42: 45762 | F42: POrd | G42: 4500027972 | H42: ADDITIONAL ELECTRICAL WORKS AT TEPPANYA | I42: 1 | J42: LOT | K42: 62500 | L42: 60000349 | M42: MAGABILINPR | N42: =_xlfn.XLOOKUP(A42,Monitoring!A:A,Monitoring!D:D) -> MALLS
A43: 10001302 | B43: 78011101 | C43: 8100 | D43: 45968 | E43: 45991 | F43: PReq | G43: 10032052 | H43: SUPPLY & INSTALLATION OF POWER SUPPLY FO | I43: 1 | J43: LOT | K43: 173386.04 | M43: DAYMIELJMA | N43: =_xlfn.XLOOKUP(A43,Monitoring!A:A,Monitoring!D:D) -> MALLS
A44: 10001305 | B44: 78011101 | C44: 8100 | D44: 45744 | E44: 45751 | F44: POrd | G44: 4500027861 | H44: ACP Cladding on Column at GH Annex | I44: 0.57 | J44: LOT | K44: 356250 | L44: 60003343 | M44: CAMPONGSI | N44: =_xlfn.XLOOKUP(A44,Monitoring!A:A,Monitoring!D:D) -> MALLS
A45: 10001311 | B45: 78011101 | C45: 8100 | D45: 46049 | E45: 46112 | F45: POrd | G45: 4500030775 | H45: WATERPROOFING OF SC 2 (2,232.33sqm) | I45: 0 | J45: LOT | K45: 0 | L45: 60002847 | M45: DEJORASTJO | N45: =_xlfn.XLOOKUP(A45,Monitoring!A:A,Monitoring!D:D) -> OFFICES
A46: 10001311 | B46: 78011101 | C46: 8100 | D46: 46038 | E46: 46052 | F46: PReq | G46: 10032488 | H46: WATERPROOFING OF SC 2 | I46: 0 | J46: LOT | K46: 0 | M46: PANGANIBANCJ | N46: =_xlfn.XLOOKUP(A46,Monitoring!A:A,Monitoring!D:D) -> OFFICES
A47: 10001311 | B47: 78011101 | C47: 8100 | D47: 45806 | E47: 45900 | F47: POrd | G47: 4500028439 | H47: WATERPROOFING OF SC2 - 2,584.75 sq.m | I47: 1 | J47: LOT | K47: 499123.19 | L47: 60003988 | M47: PANGANIBANCJ | N47: =_xlfn.XLOOKUP(A47,Monitoring!A:A,Monitoring!D:D) -> OFFICES
A48: 10001312 | B48: 78011101 | C48: 8100 | D48: 45783 | E48: 45777 | F48: POrd | G48: 4500028207 | H48: S&I OF CONFESSION ROOM DIVIDER | I48: 1 | J48: LOT | K48: 12232.14 | L48: 60002670 | M48: CABATAYAD | N48: =_xlfn.XLOOKUP(A48,Monitoring!A:A,Monitoring!D:D) -> MALLS
A49: 10001314 | B49: 78011101 | C49: 8100 | D49: 46041 | E49: 46041 | F49: POrd | G49: 4500030726 | H49: Solid Wood Top Mahogany | I49: 0 | J49: SET | K49: 0 | L49: 60002241 | M49: VIGALDF | N49: =_xlfn.XLOOKUP(A49,Monitoring!A:A,Monitoring!D:D) -> OFFICES
A50: 10001314 | B50: 78011101 | C50: 8100 | D50: 46041 | E50: 46031 | F50: POrd | G50: 4500030726 | H50: Solid Wood Top Mahogany | I50: 0 | J50: SET | K50: 0 | L50: 60002241 | M50: VIGALDF | N50: =_xlfn.XLOOKUP(A50,Monitoring!A:A,Monitoring!D:D) -> OFFICES
A51: 10001314 | B51: 78011101 | C51: 8100 | D51: 46041 | E51: 46048 | F51: POrd | G51: 4500030729 | H51: Supply & Installation of Signages | I51: 0 | J51: LOT | K51: 0 | L51: 60001999 | M51: DEJORASTJO | N51: =_xlfn.XLOOKUP(A51,Monitoring!A:A,Monitoring!D:D) -> OFFICES
A52: 10001314 | B52: 78011101 | C52: 8100 | D52: 46200 | E52: 46202 | F52: POrd | G52: 4500032520 | H52: Supply of Imported Manual Curtain | I52: 0 | J52: LOT | K52: 0 | L52: 60000357 | M52: VIGALDF | N52: =_xlfn.XLOOKUP(A52,Monitoring!A:A,Monitoring!D:D) -> OFFICES
A53: 10001314 | B53: 78011101 | C53: 8100 | D53: 46279 | E53: 46280 | F53: POrd | G53: 4500033338 | H53: Fire Extinguisher | I53: 24 | J53: PC | K53: 35714.29 | L53: 60003591 | M53: LANSANGANRV | N53: =_xlfn.XLOOKUP(A53,Monitoring!A:A,Monitoring!D:D) -> OFFICES
A54: 10001314 | B54: 78011101 | C54: 8100 | D54: 46162 | E54: 46160 | F54: POrd | G54: 4500032119 | H54: 0.7x1.2 Partition Panel | I54: 2 | J54: PC | K54: 5535.71 | L54: 60003928 | M54: LANSANGANRV | N54: =_xlfn.XLOOKUP(A54,Monitoring!A:A,Monitoring!D:D) -> OFFICES
A55: 10001314 | B55: 78011101 | C55: 8100 | D55: 46162 | E55: 46160 | F55: POrd | G55: 4500032119 | H55: 1.2x1.2 Partition Panel | I55: 1 | J55: PC | K55: 4017.86 | L55: 60003928 | M55: LANSANGANRV | N55: =_xlfn.XLOOKUP(A55,Monitoring!A:A,Monitoring!D:D) -> OFFICES
A56: 10001314 | B56: 78011101 | C56: 8100 | D56: 46162 | E56: 46160 | F56: POrd | G56: 4500032119 | H56: 1.6x1.2 Partition Panel (Inc. Top Alum. | I56: 10 | J56: PC | K56: 54910.71 | L56: 60003928 | M56: LANSANGANRV | N56: =_xlfn.XLOOKUP(A56,Monitoring!A:A,Monitoring!D:D) -> OFFICES
A57: 10001314 | B57: 78011101 | C57: 8100 | D57: 46162 | E57: 46160 | F57: POrd | G57: 4500032119 | H57: 1.5x1.2 Partition w/ Middle Connector | I57: 4 | J57: PC | K57: 21428.57 | L57: 60003928 | M57: LANSANGANRV | N57: =_xlfn.XLOOKUP(A57,Monitoring!A:A,Monitoring!D:D) -> OFFICES
A58: 10001314 | B58: 78011101 | C58: 8100 | D58: 46162 | E58: 46160 | F58: POrd | G58: 4500032119 | H58: Corner Connector Alum Aloy | I58: 10 | J58: PC | K58: 4910.71 | L58: 60003928 | M58: LANSANGANRV | N58: =_xlfn.XLOOKUP(A58,Monitoring!A:A,Monitoring!D:D) -> OFFICES
... A108: 10001314 | B108: 78011101 | C108: 8100 | D108: 45825 | E108: 45825 | F108: POrd | G108: 4500028599 | H108: Fit-Out Works | I108: 0 | J108: LOT | K108: 0 | L108: 60002970 | M108: VIGALDF | N108: =_xlfn.XLOOKUP(A108,Monitoring!A:A,Monitoring!D:D) -> OFFICES
A109: 10001314 | B109: 78011101 | C109: 8100 | D109: 46189 | E109: 46203 | F109: PReq | G109: 10034291 | H109: Fire Extinguisher | I109: 0 | J109: PC | K109: 0 | M109: LANSANGANRV | N109: =_xlfn.XLOOKUP(A109,Monitoring!A:A,Monitoring!D:D) -> OFFICES
A110: 10001314 | B110: 78011101 | C110: 8100 | D110: 46182 | E110: 46196 | F110: PReq | G110: 10034215 | H110: Supply of Imported Manual Curtain | I110: 0 | J110: LOT | K110: 0 | M110: LANSANGANRV | N110: =_xlfn.XLOOKUP(A110,Monitoring!A:A,Monitoring!D:D) -> OFFICES
A111: 10001314 | B111: 78011101 | C111: 8100 | D111: 46146 | E111: 46160 | F111: PReq | G111: 10033833 | H111: Assembly Fee | I111: 0 | J111: LOT | K111: 0 | M111: LANSANGANRV | N111: =_xlfn.XLOOKUP(A111,Monitoring!A:A,Monitoring!D:D) -> OFFICES
A112: 10001314 | B112: 78011101 | C112: 8100 | D112: 46146 | E112: 46160 | F112: PReq | G112: 10033833 | H112: Furniture Sticker White | I112: 0 | J112: PC | K112: 0 | M112: LANSANGANRV | N112: =_xlfn.XLOOKUP(A112,Monitoring!A:A,Monitoring!D:D) -> OFFICES
A113: 10001314 | B113: 78011101 | C113: 8100 | D113: 46146 | E113: 46160 | F113: PReq | G113: 10033833 | H113: Single Workstation (1.2x0.7) | I113: 0 | J113: PC | K113: 0 | M113: LANSANGANRV | N113: =_xlfn.XLOOKUP(A113,Monitoring!A:A,Monitoring!D:D) -> OFFICES
A114: 10001314 | B114: 78011101 | C114: 8100 | D114: 46146 | E114: 46160 | F114: PReq | G114: 10033833 | H114: Metal Legs for 1.2x0.7 Table | I114: 0 | J114: PC | K114: 0 | M114: LANSANGANRV | N114: =_xlfn.XLOOKUP(A114,Monitoring!A:A,Monitoring!D:D) -> OFFICES
A115: 10001314 | B115: 78011101 | C115: 8100 | D115: 46146 | E115: 46160 | F115: PReq | G115: 10033833 | H115: L-Shape Table Metal support | I115: 0 | J115: PC | K115: 0 | M115: LANSANGANRV | N115: =_xlfn.XLOOKUP(A115,Monitoring!A:A,Monitoring!D:D) -> OFFICES
A116: 10001314 | B116: 78011101 | C116: 8100 | D116: 46146 | E116: 46160 | F116: PReq | G116: 10033833 | H116: Table Top Metal Support | I116: 0 | J116: PC | K116: 0 | M116: LANSANGANRV | N116: =_xlfn.XLOOKUP(A116,Monitoring!A:A,Monitoring!D:D) -> OFFICES
A117: 10001314 | B117: 78011101 | C117: 8100 | D117: 46146 | E117: 46160 | F117: PReq | G117: 10033833 | H117: 0.7x1.2 Partition Panel | I117: 0 | J117: PC | K117: 0 | M117: LANSANGANRV | N117: =_xlfn.XLOOKUP(A117,Monitoring!A:A,Monitoring!D:D) -> OFFICES
A118: 10001314 | B118: 78011101 | C118: 8100 | D118: 46146 | E118: 46160 | F118: PReq | G118: 10033833 | H118: 1.2x1.2 Partition Panel | I118: 0 | J118: PC | K118: 0 | M118: LANSANGANRV | N118: =_xlfn.XLOOKUP(A118,Monitoring!A:A,Monitoring!D:D) -> OFFICES
A119: 10001314 | B119: 78011101 | C119: 8100 | D119: 46146 | E119: 46160 | F119: PReq | G119: 10033833 | H119: 1.6x1.2 Partition Panel (Inc. Top Alum. | I119: 0 | J119: PC | K119: 0 | M119: LANSANGANRV | N119: =_xlfn.XLOOKUP(A119,Monitoring!A:A,Monitoring!D:D) -> OFFICES
A120: 10001314 | B120: 78011101 | C120: 8100 | D120: 46146 | E120: 46160 | F120: PReq | G120: 10033833 | H120: 1.5x1.2 Partition w/ Middle Connector | I120: 0 | J120: PC | K120: 0 | M120: LANSANGANRV | N120: =_xlfn.XLOOKUP(A120,Monitoring!A:A,Monitoring!D:D) -> OFFICES
... A124: 10001314 | B124: 78011101 | C124: 8100 | D124: 46008 | E124: 46017 | F124: PReq | G124: 10032326 | H124: S&I of Signages @ BIR Office | I124: 0 | J124: LOT | K124: 0 | M124: TUBANIAEO | N124: =_xlfn.XLOOKUP(A124,Monitoring!A:A,Monitoring!D:D) -> OFFICES
A125: 10001314 | B125: 78011101 | C125: 8100 | D125: 46162 | E125: 46160 | F125: POrd | G125: 4500032119 | H125: Assembly Fee | I125: 1 | J125: LOT | K125: 16964.29 | L125: 60003928 | M125: LANSANGANRV | N125: =_xlfn.XLOOKUP(A125,Monitoring!A:A,Monitoring!D:D) -> OFFICES
A126: 10001314 | B126: 78011101 | C126: 8100 | D126: 46162 | E126: 46160 | F126: POrd | G126: 4500032119 | H126: Furniture Sticker White | I126: 1 | J126: PC | K126: 133.93 | L126: 60003928 | M126: LANSANGANRV | N126: =_xlfn.XLOOKUP(A126,Monitoring!A:A,Monitoring!D:D) -> OFFICES
A127: 10001314 | B127: 78011101 | C127: 8100 | D127: 46162 | E127: 46160 | F127: POrd | G127: 4500032119 | H127: Single Workstation (1.2x0.7) | I127: 1 | J127: PC | K127: 10357.14 | L127: 60003928 | M127: LANSANGANRV | N127: =_xlfn.XLOOKUP(A127,Monitoring!A:A,Monitoring!D:D) -> OFFICES
A128: 10001314 | B128: 78011101 | C128: 8100 | D128: 46162 | E128: 46160 | F128: POrd | G128: 4500032119 | H128: Metal Legs for 1.2x0.7 Table | I128: 1 | J128: PC | K128: 1562.5 | L128: 60003928 | M128: LANSANGANRV | N128: =_xlfn.XLOOKUP(A128,Monitoring!A:A,Monitoring!D:D) -> OFFICES
A129: 10001314 | B129: 78011101 | C129: 8100 | D129: 46162 | E129: 46160 | F129: POrd | G129: 4500032119 | H129: L-Shape Table Metal support | I129: 2 | J129: PC | K129: 1250 | L129: 60003928 | M129: LANSANGANRV | N129: =_xlfn.XLOOKUP(A129,Monitoring!A:A,Monitoring!D:D) -> OFFICES
A130: 10001314 | B130: 78011101 | C130: 8100 | D130: 46162 | E130: 46160 | F130: POrd | G130: 4500032119 | H130: Table Top Metal Support | I130: 30 | J130: PC | K130: 1339.29 | L130: 60003928 | M130: LANSANGANRV | N130: =_xlfn.XLOOKUP(A130,Monitoring!A:A,Monitoring!D:D) -> OFFICES
A131: 10001314 | B131: 78011101 | C131: 8100 | D131: 46111 | E131: 46111 | F131: POrd | G131: 4500031531 | H131: E-Lounge 2 seater | I131: 0 | J131: SET | K131: 0 | L131: 60003928 | M131: VIGALDF | N131: =_xlfn.XLOOKUP(A131,Monitoring!A:A,Monitoring!D:D) -> OFFICES
A132: 10001314 | B132: 78011101 | C132: 8100 | D132: 46111 | E132: 46111 | F132: POrd | G132: 4500031531 | H132: E-Lounge 3 seater | I132: 0 | J132: SET | K132: 0 | L132: 60003928 | M132: VIGALDF | N132: =_xlfn.XLOOKUP(A132,Monitoring!A:A,Monitoring!D:D) -> OFFICES
A133: 10001314 | B133: 78011101 | C133: 8100 | D133: 46111 | E133: 46111 | F133: POrd | G133: 4500031531 | H133: Grommet | I133: 0 | J133: PC | K133: 0 | L133: 60003928 | M133: VIGALDF | N133: =_xlfn.XLOOKUP(A133,Monitoring!A:A,Monitoring!D:D) -> OFFICES
A134: 10001314 | B134: 78011101 | C134: 8100 | D134: 45972 | E134: 46022 | F134: POrd | G134: 4500030253 | H134: EXECUTIVE CHAIR (black) | I134: 0 | J134: UNI | K134: 0 | L134: 60003928 | M134: VIGALDF | N134: =_xlfn.XLOOKUP(A134,Monitoring!A:A,Monitoring!D:D) -> OFFICES
A135: 10001314 | B135: 78011101 | C135: 8100 | D135: 45972 | E135: 46022 | F135: POrd | G135: 4500030253 | H135: EXECUTIVE CHAIR (brown) | I135: 0 | J135: UNI | K135: 0 | L135: 60003928 | M135: VIGALDF | N135: =_xlfn.XLOOKUP(A135,Monitoring!A:A,Monitoring!D:D) -> OFFICES
A136: 10001314 | B136: 78011101 | C136: 8100 | D136: 45905 | E136: 45905 | F136: POrd | G136: 4500029529 | H136: Relocation of FCUs | I136: 1 | J136: LOT | K136: 491071.43 | L136: 60000283 | M136: LANSANGANRV | N136: =_xlfn.XLOOKUP(A136,Monitoring!A:A,Monitoring!D:D) -> OFFICES
... A138: 10001314 | B138: 78011101 | C138: 8100 | D138: 45897 | E138: 45897 | F138: POrd | G138: 4500029412 | H138: Fire Protection Works | I138: 0.02 | J138: LOT | K138: 10714.29 | L138: 60000181 | M138: DEJORASTJO | N138: =_xlfn.XLOOKUP(A138,Monitoring!A:A,Monitoring!D:D) -> OFFICES
A139: 10001314 | B139: 78011101 | C139: 8100 | D139: 46146 | E139: 46160 | F139: PReq | G139: 10033833 | H139: Corner Connector & Accessories | I139: 0 | J139: PC | K139: 0 | M139: LANSANGANRV | N139: =_xlfn.XLOOKUP(A139,Monitoring!A:A,Monitoring!D:D) -> OFFICES
A140: 10001314 | B140: 78011101 | C140: 8100 | D140: 46146 | E140: 46160 | F140: PReq | G140: 10033833 | H140: End Alum. Alloy Cover | I140: 0 | J140: PC | K140: 0 | M140: LANSANGANRV | N140: =_xlfn.XLOOKUP(A140,Monitoring!A:A,Monitoring!D:D) -> OFFICES
A141: 10001314 | B141: 78011101 | C141: 8100 | D141: 46146 | E141: 46160 | F141: PReq | G141: 10033833 | H141: End Cover | I141: 0 | J141: PC | K141: 0 | M141: LANSANGANRV | N141: =_xlfn.XLOOKUP(A141,Monitoring!A:A,Monitoring!D:D) -> OFFICES
A142: 10001314 | B142: 78011101 | C142: 8100 | D142: 46146 | E142: 46160 | F142: PReq | G142: 10033833 | H142: T-Connector & Accessories | I142: 0 | J142: PC | K142: 0 | M142: LANSANGANRV | N142: =_xlfn.XLOOKUP(A142,Monitoring!A:A,Monitoring!D:D) -> OFFICES
A143: 10001314 | B143: 78011101 | C143: 8100 | D143: 46146 | E143: 46160 | F143: PReq | G143: 10033833 | H143: T-Connector Alum. Alloy Cover | I143: 0 | J143: PC | K143: 0 | M143: LANSANGANRV | N143: =_xlfn.XLOOKUP(A143,Monitoring!A:A,Monitoring!D:D) -> OFFICES
A144: 10001314 | B144: 78011101 | C144: 8100 | D144: 46146 | E144: 46160 | F144: PReq | G144: 10033833 | H144: T-Connector & Accessories | I144: 0 | J144: PC | K144: 0 | M144: LANSANGANRV | N144: =_xlfn.XLOOKUP(A144,Monitoring!A:A,Monitoring!D:D) -> OFFICES
A145: 10001314 | B145: 78011101 | C145: 8100 | D145: 46098 | E145: 46105 | F145: PReq | G145: 10033267 | H145: E-Lounge 2 seater | I145: 0 | J145: SET | K145: 0 | M145: LANSANGANRV | N145: =_xlfn.XLOOKUP(A145,Monitoring!A:A,Monitoring!D:D) -> OFFICES
A146: 10001314 | B146: 78011101 | C146: 8100 | D146: 46098 | E146: 46105 | F146: PReq | G146: 10033267 | H146: E-Lounge 3 seater | I146: 0 | J146: SET | K146: 0 | M146: LANSANGANRV | N146: =_xlfn.XLOOKUP(A146,Monitoring!A:A,Monitoring!D:D) -> OFFICES
A147: 10001314 | B147: 78011101 | C147: 8100 | D147: 46098 | E147: 46105 | F147: PReq | G147: 10033267 | H147: Grommet | I147: 0 | J147: PC | K147: 0 | M147: LANSANGANRV | N147: =_xlfn.XLOOKUP(A147,Monitoring!A:A,Monitoring!D:D) -> OFFICES
A148: 10001314 | B148: 78011101 | C148: 8100 | D148: 46043 | E148: 46048 | F148: PReq | G148: 10032567 | H148: S&D of Sheer Curtains | I148: 0 | J148: LOT | K148: 0 | M148: LANSANGANRV | N148: =_xlfn.XLOOKUP(A148,Monitoring!A:A,Monitoring!D:D) -> OFFICES
A149: 10001314 | B149: 78011101 | C149: 8100 | D149: 46043 | E149: 46048 | F149: PReq | G149: 10032567 | H149: S&D of Roll-up Shades | I149: 0 | J149: LOT | K149: 0 | M149: LANSANGANRV | N149: =_xlfn.XLOOKUP(A149,Monitoring!A:A,Monitoring!D:D) -> OFFICES
A150: 10001314 | B150: 78011101 | C150: 8100 | D150: 46043 | E150: 46043 | F150: PReq | G150: 10032566 | H150: Delivery Charfe | I150: 0 | J150: LOT | K150: 0 | M150: TUBANIAEO | N150: =_xlfn.XLOOKUP(A150,Monitoring!A:A,Monitoring!D:D) -> OFFICES
... A158: 10001314 | B158: 78011101 | C158: 8100 | D158: 46028 | E158: 46031 | F158: PReq | G158: 10032342 | H158: Solid Wood Top Mahogany | I158: 0 | J158: SET | K158: 0 | M158: LANSANGANRV | N158: =_xlfn.XLOOKUP(A158,Monitoring!A:A,Monitoring!D:D) -> OFFICES
A159: 10001315 | B159: 78011101 | C159: 8100 | D159: 45916 | E159: 45930 | F159: POrd | G159: 4500029627 | H159: HANABISHI AIR COOLER 10L MODEL: HAC-500 | I159: 0 | J159: PC | K159: 0 | L159: 60002643 | M159: CAMPONGSI | N159: =_xlfn.XLOOKUP(A159,Monitoring!A:A,Monitoring!D:D) -> MALLS
A160: 10001320 | B160: 78011101 | C160: 8100 | D160: 45854 | E160: 45838 | F160: POrd | G160: 4500028914 | H160: S&I OF SEISMIC ACCELEROGRAPH SYSTEM | I160: 1 | J160: LOT | K160: 875000 | L160: 60001645 | M160: CABATAYAD | N160: =_xlfn.XLOOKUP(A160,Monitoring!A:A,Monitoring!D:D) -> ESTATES
A161: 10001322 | B161: 78011101 | C161: 8000 | D161: 45821 | E161: 45884 | F161: POrd | G161: 4500028576 | H161: CC Drainage System Improvement Ph2 | I161: 0.58 | J161: LOT | K161: 8700000 | L161: 60004008 | M161: VIGALDF | N161: =_xlfn.XLOOKUP(A161,Monitoring!A:A,Monitoring!D:D) -> ESTATES
A162: 10001340 | B162: 78011101 | C162: 8100 | D162: 45923 | E162: 45899 | F162: POrd | G162: 4500029701 | H162: ACP REPLACEMENT IN 10/F VERANDA | I162: 0 | J162: LOT | K162: 0 | L162: 60004125 | M162: VIGALDF | N162: =_xlfn.XLOOKUP(A162,Monitoring!A:A,Monitoring!D:D) -> OFFICES
A163: 10001341 | B163: 78011101 | C163: 8000 | D163: 46231 | E163: 46246 | F163: PReq | G163: 10034726 | H163: Additional Plants & Soil at CC Park | I163: 0 | J163: LOT | K163: 0 | M163: LANSANGANRV | N163: =_xlfn.XLOOKUP(A163,Monitoring!A:A,Monitoring!D:D) -> ESTATES
A164: 10001341 | B164: 78011101 | C164: 8000 | D164: 46202 | E164: 46203 | F164: POrd | G164: 4500032521 | H164: BOLLARD LIGHT FIXTURE | I164: 65 | J164: PC | K164: 174107.14 | L164: 60000357 | M164: LANSANGANRV | N164: =_xlfn.XLOOKUP(A164,Monitoring!A:A,Monitoring!D:D) -> ESTATES
A165: 10001341 | B165: 78011101 | C165: 8000 | D165: 46260 | E165: 46252 | F165: POrd | G165: 4500033180 | H165: ST KLENZALL CLEANER CONC 20L PAIL | I165: 2 | J165: PC | K165: 11322.57 | L165: 60004526 | M165: CABATAYAD | N165: =_xlfn.XLOOKUP(A165,Monitoring!A:A,Monitoring!D:D) -> ESTATES
A166: 10001341 | B166: 78011101 | C166: 8000 | D166: 46260 | E166: 46252 | F166: POrd | G166: 4500033180 | H166: ST RESTORE CLEANER CONC 20L PAIL | I166: 2 | J166: PC | K166: 13368.93 | L166: 60004526 | M166: CABATAYAD | N166: =_xlfn.XLOOKUP(A166,Monitoring!A:A,Monitoring!D:D) -> ESTATES
A167: 10001341 | B167: 78011101 | C167: 8000 | D167: 45880 | E167: 45930 | F167: POrd | G167: 4500029212 | H167: Demolition and Retiling works | I167: 0 | J167: LOT | K167: 0 | L167: 60000112 | M167: VIGALDF | N167: =_xlfn.XLOOKUP(A167,Monitoring!A:A,Monitoring!D:D) -> ESTATES
A168: 10001341 | B168: 78011101 | C168: 8000 | D168: 46276 | E168: 46293 | F168: PReq | G168: 10035224 | H168: 10W LED UPLIGHT 3000K | I168: 48 | J168: PC | K168: 154285.92 | M168: DEJORASTJO | N168: =_xlfn.XLOOKUP(A168,Monitoring!A:A,Monitoring!D:D) -> ESTATES
A169: 10001341 | B169: 78011101 | C169: 8000 | D169: 46238 | E169: 46252 | F169: PReq | G169: 10034798 | H169: ST KLENZALL CLEANER CONC 20L PAIL | I169: 0 | J169: PC | K169: 0 | M169: CABATAYAD | N169: =_xlfn.XLOOKUP(A169,Monitoring!A:A,Monitoring!D:D) -> ESTATES
A170: 10001341 | B170: 78011101 | C170: 8000 | D170: 46238 | E170: 46252 | F170: PReq | G170: 10034798 | H170: ST RESTORE CLEANER CONC 20L PAIL | I170: 0 | J170: PC | K170: 0 | M170: CABATAYAD | N170: =_xlfn.XLOOKUP(A170,Monitoring!A:A,Monitoring!D:D) -> ESTATES
...

Sheet Monitoring
A1: Ortigas Land Corporation
A2: NPC List
A3: December 31, 2026
A4: Sep | Z4: =Z5-'SAP Report'!C2 -> 2041964.3 | AA4: =AA5-'SAP Report'!D2 -> 0 | AB4: =AB5-'SAP Report'!E2 -> 0 | AC4: =AC5-'SAP Report'!F2 -> 0 | AD4: =AD5-'SAP Report'!G2 -> 2041964.3 | AG4: Monthly Forecast | AV4: YTD Forecast
R5: =SUBTOTAL(9,R7:R1048576) -> 7.1059177e+08 | Z5: =SUBTOTAL(9,Z7:Z1048576) -> 7.0971022e+08 | AA5: =SUBTOTAL(9,AA7:AA1048576) -> 1.5488819e+08 | AB5: =SUBTOTAL(9,AB7:AB1048576) -> 234128221 | AC5: =SUBTOTAL(9,AC7:AC1048576) -> 3.8901642e+08 | AD5: =SUBTOTAL(9,AD7:AD1048576) -> 3.2069381e+08 | AE5: =SUBTOTAL(9,AE7:AE1048576) -> 5.5482203e+08 | AG5: =SUBTOTAL(9,AG7:AG1048576) -> 5254631.9 | AH5: =SUBTOTAL(9,AH7:AH1048576) -> 15242658 | AI5: =SUBTOTAL(9,AI7:AI1048576) -> 20216894 | AJ5: =SUBTOTAL(9,AJ7:AJ1048576) -> 23144199 | AK5: =SUBTOTAL(9,AK7:AK1048576) -> 24344173 | AL5: =SUBTOTAL(9,AL7:AL1048576) -> 19564399 | AM5: =SUBTOTAL(9,AM7:AM1048576) -> 18820099 | AN5: =SUBTOTAL(9,AN7:AN1048576) -> 18255306 | ... AT5: =SUBTOTAL(9,AT7:AT1048576) -> 0 | AV5: =SUBTOTAL(9,AV7:AV1048576) -> 5254631.9 | AW5: =SUBTOTAL(9,AW7:AW1048576) -> 20497290 | AX5: =SUBTOTAL(9,AX7:AX1048576) -> 40714184 | AY5: =SUBTOTAL(9,AY7:AY1048576) -> 63858382 | AZ5: =SUBTOTAL(9,AZ7:AZ1048576) -> 88202556 | BA5: =SUBTOTAL(9,BA7:BA1048576) -> 1.0776695e+08 | BB5: =SUBTOTAL(9,BB7:BB1048576) -> 1.2658705e+08 | BC5: =SUBTOTAL(9,BC7:BC1048576) -> 1.4484236e+08 | ... BG5: =SUBTOTAL(9,BG7:BG1048576) -> 7.0971022e+08
A6: Orders | B6: IO Description | C6: SBU | D6: SBU2 | E6: Group | F6: Special Project? | G6: Type | H6: Budget Source Code | I6: Order Type | J6: PROJECT NAME | K6: Count | L6: Co. Code | M6: CC NUMBERS | N6: CC NAME | O6: APPLICANT | P6: PERSON RESPONSIBLE | Q6: BPM Ticket No. | R6: Amount | S6: APPLICATION DATE | T6: DIVISION | U6: START OF PROJECT | V6: END OF PROJECT | W6: Date processed | X6: SAP Doc. No. | Z6: Budget | AA6: Actual | AB6: Committed (open PRPO) | AC6: Allotted | AD6: Available1 | AE6: Available2 | AG6: Jan | AH6: Feb | AI6: Mar | AJ6: Apr | AK6: May | AL6: Jun | AM6: Jul | AN6: Aug | AO6: Sep | AP6: Oct | AQ6: Nov | AR6: Dec | AS6: Total | AT6: Balance | AV6: Jan | AW6: Feb | AX6: Mar | AY6: Apr | AZ6: May | BA6: Jun | BB6: Jul | BC6: Aug | BD6: Sep | BE6: Oct | BF6: Nov | BG6: Dec
A7: 10001072 | B7: GH RFDCK/CNOPIES/PRMTR WALL | C7: MALLS | D7: MALLS | F7: N | G7: Carry-over | R7: =_xlfn.XLOOKUP(A7,Malls!B:B,Malls!G:G) -> 142000 | T7: =_xlfn.XLOOKUP(M7,[1]Sheet1!$A:$A,[1]Sheet1!$E:$E) -> 0 | Z7: =_xlfn.XLOOKUP(A7,'SAP Report'!A:A,'SAP Report'!C:C) -> 142000 | AA7: =HLOOKUP($A$4,$AV$6:$BG7,2,FALSE) -> 0 | AB7: =SUMIF('Open PR PO'!A:A,Monitoring!A7,'Open PR PO'!K:K) -> 142000 | AC7: =AA7+AB7 -> 142000 | AD7: =Z7-AC7 -> 0 | AE7: =Z7-AA7 -> 142000 | AG7: =SUMIFS(Actual!$F:$F,Actual!$N:$N,Monitoring!AG$6,Actual!$A:$A,Monitoring!$A7) -> 0 | AH7: =SUMIFS(Actual!$F:$F,Actual!$N:$N,Monitoring!AH$6,Actual!$A:$A,Monitoring!$A7) -> 0 | AI7: =SUMIFS(Actual!$F:$F,Actual!$N:$N,Monitoring!AI$6,Actual!$A:$A,Monitoring!$A7) -> 0 | AJ7: =SUMIFS(Actual!$F:$F,Actual!$N:$N,Monitoring!AJ$6,Actual!$A:$A,Monitoring!$A7) -> 0 | AK7: =SUMIFS(Actual!$F:$F,Actual!$N:$N,Monitoring!AK$6,Actual!$A:$A,Monitoring!$A7) -> 0 | AL7: =SUMIFS(Actual!$F:$F,Actual!$N:$N,Monitoring!AL$6,Actual!$A:$A,Monitoring!$A7) -> 0 | AM7: =SUMIFS(Actual!$F:$F,Actual!$N:$N,Monitoring!AM$6,Actual!$A:$A,Monitoring!$A7) -> 0 | AN7: =SUMIFS(Actual!$F:$F,Actual!$N:$N,Monitoring!AN$6,Actual!$A:$A,Monitoring!$A7) -> 0 | AO7: =SUMIFS(Actual!$F:$F,Actual!$N:$N,Monitoring!AO$6,Actual!$A:$A,Monitoring!$A7) -> 0 | AP7: =AB7 -> 142000 | AQ7: =AD7/2 -> 0 | AR7: =AQ7 -> 0 | AS7: =SUM(AG7:AR7) -> 142000 | AT7: =Z7-AS7 -> 0 | AV7: =AG7 -> 0 | AW7: =AV7+AH7 -> 0 | AX7: =AW7+AI7 -> 0 | AY7: =AX7+AJ7 -> 0 | AZ7: =AY7+AK7 -> 0 | BA7: =AZ7+AL7 -> 0 | BB7: =BA7+AM7 -> 0 | BC7: =BB7+AN7 -> 0 | BD7: =BC7+AO7 -> 0 | ... BG7: =BF7+AR7 -> 142000 | BH7: 1
A8: 10001134 | B8: GH TIANGGE EIFS DROPWALL | C8: MALLS | D8: MALLS | F8: N | G8: Carry-over | R8: =_xlfn.XLOOKUP(A8,Malls!B:B,Malls!G:G) -> 789517.86 | T8: =_xlfn.XLOOKUP(M8,[1]Sheet1!$A:$A,[1]Sheet1!$E:$E) -> 0 | Z8: =_xlfn.XLOOKUP(A8,'SAP Report'!A:A,'SAP Report'!C:C) -> 789517.86 | AA8: =HLOOKUP($A$4,$AV$6:$BG8,(2+BH7),FALSE) -> 0 | AB8: =SUMIF('Open PR PO'!A:A,Monitoring!A8,'Open PR PO'!K:K) -> 789517.86 | AC8: =AA8+AB8 -> 789517.86 | AD8: =Z8-AC8 -> 0 | AE8: =Z8-AA8 -> 789517.86 | AG8: =SUMIFS(Actual!$F:$F,Actual!$N:$N,Monitoring!AG$6,Actual!$A:$A,Monitoring!$A8) -> 0 | AH8: =SUMIFS(Actual!$F:$F,Actual!$N:$N,Monitoring!AH$6,Actual!$A:$A,Monitoring!$A8) -> 0 | AI8: =SUMIFS(Actual!$F:$F,Actual!$N:$N,Monitoring!AI$6,Actual!$A:$A,Monitoring!$A8) -> 0 | AJ8: =SUMIFS(Actual!$F:$F,Actual!$N:$N,Monitoring!AJ$6,Actual!$A:$A,Monitoring!$A8) -> 0 | AK8: =SUMIFS(Actual!$F:$F,Actual!$N:$N,Monitoring!AK$6,Actual!$A:$A,Monitoring!$A8) -> 0 | AL8: =SUMIFS(Actual!$F:$F,Actual!$N:$N,Monitoring!AL$6,Actual!$A:$A,Monitoring!$A8) -> 0 | AM8: =SUMIFS(Actual!$F:$F,Actual!$N:$N,Monitoring!AM$6,Actual!$A:$A,Monitoring!$A8) -> 0 | AN8: =SUMIFS(Actual!$F:$F,Actual!$N:$N,Monitoring!AN$6,Actual!$A:$A,Monitoring!$A8) -> 0 | AO8: =SUMIFS(Actual!$F:$F,Actual!$N:$N,Monitoring!AO$6,Actual!$A:$A,Monitoring!$A8) -> 0 | AP8: =AB8 -> 789517.86 | AQ8: =AD8/2 -> 0 | AR8: =AQ8 -> 0 | AS8: =SUM(AG8:AR8) -> 789517.86 | AT8: =Z8-AS8 -> 0 | AV8: =AG8 -> 0 | AW8: =AV8+AH8 -> 0 | AX8: =AW8+AI8 -> 0 | AY8: =AX8+AJ8 -> 0 | AZ8: =AY8+AK8 -> 0 | BA8: =AZ8+AL8 -> 0 | BB8: =BA8+AM8 -> 0 | BC8: =BB8+AN8 -> 0 | BD8: =BC8+AO8 -> 0 | ... BG8: =BF8+AR8 -> 789517.86 | BH8: =BH7+1 -> 2
A9: 10001262 | B9: GH NEW MALL REWATERPROOFING | C9: MALLS | D9: MALLS | F9: N | G9: Carry-over | R9: =_xlfn.XLOOKUP(A9,Malls!B:B,Malls!G:G) -> 767321.42 | T9: =_xlfn.XLOOKUP(M9,[1]Sheet1!$A:$A,[1]Sheet1!$E:$E) -> 0 | Z9: =_xlfn.XLOOKUP(A9,'SAP Report'!A:A,'SAP Report'!C:C) -> 767321.43 | AA9: =HLOOKUP($A$4,$AV$6:$BG9,(2+BH8),FALSE) -> 417857.14 | AB9: =SUMIF('Open PR PO'!A:A,Monitoring!A9,'Open PR PO'!K:K) -> 349464.28 | AC9: =AA9+AB9 -> 767321.42 | AD9: =Z9-AC9 -> 0.01 | AE9: =Z9-AA9 -> 349464.29 | AG9: =SUMIFS(Actual!$F:$F,Actual!$N:$N,Monitoring!AG$6,Actual!$A:$A,Monitoring!$A9) -> 0 | AH9: =SUMIFS(Actual!$F:$F,Actual!$N:$N,Monitoring!AH$6,Actual!$A:$A,Monitoring!$A9) -> 0 | AI9: =SUMIFS(Actual!$F:$F,Actual!$N:$N,Monitoring!AI$6,Actual!$A:$A,Monitoring!$A9) -> 0 | AJ9: =SUMIFS(Actual!$F:$F,Actual!$N:$N,Monitoring!AJ$6,Actual!$A:$A,Monitoring!$A9) -> 417857.14 | AK9: =SUMIFS(Actual!$F:$F,Actual!$N:$N,Monitoring!AK$6,Actual!$A:$A,Monitoring!$A9) -> 0 | AL9: =SUMIFS(Actual!$F:$F,Actual!$N:$N,Monitoring!AL$6,Actual!$A:$A,Monitoring!$A9) -> 0 | AM9: =SUMIFS(Actual!$F:$F,Actual!$N:$N,Monitoring!AM$6,Actual!$A:$A,Monitoring!$A9) -> 0 | AN9: =SUMIFS(Actual!$F:$F,Actual!$N:$N,Monitoring!AN$6,Actual!$A:$A,Monitoring!$A9) -> 0 | AO9: =SUMIFS(Actual!$F:$F,Actual!$N:$N,Monitoring!AO$6,Actual!$A:$A,Monitoring!$A9) -> 0 | AP9: =AB9 -> 349464.28 | AQ9: =AD9/2 -> 0.005 | AR9: =AQ9 -> 0.005 | AS9: =SUM(AG9:AR9) -> 767321.43 | AT9: =Z9-AS9 -> 0 | AV9: =AG9 -> 0 | AW9: =AV9+AH9 -> 0 | AX9: =AW9+AI9 -> 0 | AY9: =AX9+AJ9 -> 417857.14 | AZ9: =AY9+AK9 -> 417857.14 | BA9: =AZ9+AL9 -> 417857.14 | BB9: =BA9+AM9 -> 417857.14 | BC9: =BB9+AN9 -> 417857.14 | BD9: =BC9+AO9 -> 417857.14 | ... BG9: =BF9+AR9 -> 767321.43 | BH9: =BH8+1 -> 3
A10: 10001254 | B10: ES CONSTRUCTION OF OMD ADMIN | C10: MALLS | D10: MALLS | F10: N | G10: Carry-over | R10: =_xlfn.XLOOKUP(A10,Malls!B:B,Malls!G:G) -> 32193.08 | T10: =_xlfn.XLOOKUP(M10,[1]Sheet1!$A:$A,[1]Sheet1!$E:$E) -> 0 | Z10: =_xlfn.XLOOKUP(A10,'SAP Report'!A:A,'SAP Report'!C:C) -> 32193.08 | AA10: =HLOOKUP($A$4,$AV$6:$BG10,(2+BH9),FALSE) -> 0 | AB10: =SUMIF('Open PR PO'!A:A,Monitoring!A10,'Open PR PO'!K:K) -> 32193.08 | AC10: =AA10+AB10 -> 32193.08 | AD10: =Z10-AC10 -> 0 | AE10: =Z10-AA10 -> 32193.08 | AG10: =SUMIFS(Actual!$F:$F,Actual!$N:$N,Monitoring!AG$6,Actual!$A:$A,Monitoring!$A10) -> 0 | AH10: =SUMIFS(Actual!$F:$F,Actual!$N:$N,Monitoring!AH$6,Actual!$A:$A,Monitoring!$A10) -> 0 | AI10: =SUMIFS(Actual!$F:$F,Actual!$N:$N,Monitoring!AI$6,Actual!$A:$A,Monitoring!$A10) -> 0 | AJ10: =SUMIFS(Actual!$F:$F,Actual!$N:$N,Monitoring!AJ$6,Actual!$A:$A,Monitoring!$A10) -> 0 | AK10: =SUMIFS(Actual!$F:$F,Actual!$N:$N,Monitoring!AK$6,Actual!$A:$A,Monitoring!$A10) -> 0 | AL10: =SUMIFS(Actual!$F:$F,Actual!$N:$N,Monitoring!AL$6,Actual!$A:$A,Monitoring!$A10) -> 0 | AM10: =SUMIFS(Actual!$F:$F,Actual!$N:$N,Monitoring!AM$6,Actual!$A:$A,Monitoring!$A10) -> 0 | AN10: =SUMIFS(Actual!$F:$F,Actual!$N:$N,Monitoring!AN$6,Actual!$A:$A,Monitoring!$A10) -> 0 | AO10: =SUMIFS(Actual!$F:$F,Actual!$N:$N,Monitoring!AO$6,Actual!$A:$A,Monitoring!$A10) -> 0 | AP10: =AB10 -> 32193.08 | AQ10: =AD10/2 -> 0 | AR10: =AQ10 -> 0 | AS10: =SUM(AG10:AR10) -> 32193.08 | AT10: =Z10-AS10 -> 0 | AV10: =AG10 -> 0 | AW10: =AV10+AH10 -> 0 | AX10: =AW10+AI10 -> 0 | AY10: =AX10+AJ10 -> 0 | AZ10: =AY10+AK10 -> 0 | BA10: =AZ10+AL10 -> 0 | BB10: =BA10+AM10 -> 0 | BC10: =BB10+AN10 -> 0 | BD10: =BC10+AO10 -> 0 | ... BG10: =BF10+AR10 -> 32193.08 | BH10: =BH9+1 -> 4
A11: 10001288 | B11: ES EAST WING 2024 SPACE RE-C | C11: MALLS | D11: MALLS | F11: N | G11: Carry-over | R11: =_xlfn.XLOOKUP(A11,Malls!B:B,Malls!G:G) -> 7500 | T11: =_xlfn.XLOOKUP(M11,[1]Sheet1!$A:$A,[1]Sheet1!$E:$E) -> 0 | Z11: =_xlfn.XLOOKUP(A11,'SAP Report'!A:A,'SAP Report'!C:C) -> 7500 | AA11: =HLOOKUP($A$4,$AV$6:$BG11,(2+BH10),FALSE) -> 0 | AB11: =SUMIF('Open PR PO'!A:A,Monitoring!A11,'Open PR PO'!K:K) -> 7500 | AC11: =AA11+AB11 -> 7500 | AD11: =Z11-AC11 -> 0 | AE11: =Z11-AA11 -> 7500 | AG11: =SUMIFS(Actual!$F:$F,Actual!$N:$N,Monitoring!AG$6,Actual!$A:$A,Monitoring!$A11) -> 0 | AH11: =SUMIFS(Actual!$F:$F,Actual!$N:$N,Monitoring!AH$6,Actual!$A:$A,Monitoring!$A11) -> 0 | AI11: =SUMIFS(Actual!$F:$F,Actual!$N:$N,Monitoring!AI$6,Actual!$A:$A,Monitoring!$A11) -> 0 | AJ11: =SUMIFS(Actual!$F:$F,Actual!$N:$N,Monitoring!AJ$6,Actual!$A:$A,Monitoring!$A11) -> 0 | AK11: =SUMIFS(Actual!$F:$F,Actual!$N:$N,Monitoring!AK$6,Actual!$A:$A,Monitoring!$A11) -> 0 | AL11: =SUMIFS(Actual!$F:$F,Actual!$N:$N,Monitoring!AL$6,Actual!$A:$A,Monitoring!$A11) -> 0 | AM11: =SUMIFS(Actual!$F:$F,Actual!$N:$N,Monitoring!AM$6,Actual!$A:$A,Monitoring!$A11) -> 0 | AN11: =SUMIFS(Actual!$F:$F,Actual!$N:$N,Monitoring!AN$6,Actual!$A:$A,Monitoring!$A11) -> 0 | AO11: =SUMIFS(Actual!$F:$F,Actual!$N:$N,Monitoring!AO$6,Actual!$A:$A,Monitoring!$A11) -> 0 | AP11: =AB11 -> 7500 | AQ11: =AD11/2 -> 0 | AR11: =AQ11 -> 0 | AS11: =SUM(AG11:AR11) -> 7500 | AT11: =Z11-AS11 -> 0 | AV11: =AG11 -> 0 | AW11: =AV11+AH11 -> 0 | AX11: =AW11+AI11 -> 0 | AY11: =AX11+AJ11 -> 0 | AZ11: =AY11+AK11 -> 0 | BA11: =AZ11+AL11 -> 0 | BB11: =BA11+AM11 -> 0 | BC11: =BB11+AN11 -> 0 | BD11: =BC11+AO11 -> 0 | ... BG11: =BF11+AR11 -> 7500 | BH11: =BH10+1 -> 5
A12: 10001289 | B12: ES MAIN 2025 SPACE RE-CUT & | C12: MALLS | D12: MALLS | F12: N | G12: Carry-over | R12: =_xlfn.XLOOKUP(A12,Malls!B:B,Malls!G:G) -> 42857.14 | T12: =_xlfn.XLOOKUP(M12,[1]Sheet1!$A:$A,[1]Sheet1!$E:$E) -> 0 | Z12: =_xlfn.XLOOKUP(A12,'SAP Report'!A:A,'SAP Report'!C:C) -> 42857.14 | AA12: =HLOOKUP($A$4,$AV$6:$BG12,(2+BH11),FALSE) -> 0 | AB12: =SUMIF('Open PR PO'!A:A,Monitoring!A12,'Open PR PO'!K:K) -> 42857.14 | AC12: =AA12+AB12 -> 42857.14 | AD12: =Z12-AC12 -> 0 | AE12: =Z12-AA12 -> 42857.14 | AG12: =SUMIFS(Actual!$F:$F,Actual!$N:$N,Monitoring!AG$6,Actual!$A:$A,Monitoring!$A12) -> 0 | AH12: =SUMIFS(Actual!$F:$F,Actual!$N:$N,Monitoring!AH$6,Actual!$A:$A,Monitoring!$A12) -> 0 | AI12: =SUMIFS(Actual!$F:$F,Actual!$N:$N,Monitoring!AI$6,Actual!$A:$A,Monitoring!$A12) -> 0 | AJ12: =SUMIFS(Actual!$F:$F,Actual!$N:$N,Monitoring!AJ$6,Actual!$A:$A,Monitoring!$A12) -> 0 | AK12: =SUMIFS(Actual!$F:$F,Actual!$N:$N,Monitoring!AK$6,Actual!$A:$A,Monitoring!$A12) -> 0 | AL12: =SUMIFS(Actual!$F:$F,Actual!$N:$N,Monitoring!AL$6,Actual!$A:$A,Monitoring!$A12) -> 0 | AM12: =SUMIFS(Actual!$F:$F,Actual!$N:$N,Monitoring!AM$6,Actual!$A:$A,Monitoring!$A12) -> 0 | AN12: =SUMIFS(Actual!$F:$F,Actual!$N:$N,Monitoring!AN$6,Actual!$A:$A,Monitoring!$A12) -> 0 | AO12: =SUMIFS(Actual!$F:$F,Actual!$N:$N,Monitoring!AO$6,Actual!$A:$A,Monitoring!$A12) -> 0 | AP12: =AB12 -> 42857.14 | AQ12: =AD12/2 -> 0 | AR12: =AQ12 -> 0 | AS12: =SUM(AG12:AR12) -> 42857.14 | AT12: =Z12-AS12 -> 0 | AV12: =AG12 -> 0 | AW12: =AV12+AH12 -> 0 | AX12: =AW12+AI12 -> 0 | AY12: =AX12+AJ12 -> 0 | AZ12: =AY12+AK12 -> 0 | BA12: =AZ12+AL12 -> 0 | BB12: =BA12+AM12 -> 0 | BC12: =BB12+AN12 -> 0 | BD12: =BC12+AO12 -> 0 | ... BG12: =BF12+AR12 -> 42857.14 | BH12: =BH11+1 -> 6
A13: 40001214 | B13: ES NEW ADMIN OFFICE FIXED AS | C13: MALLS | D13: MALLS | F13: N | G13: Carry-over | R13: =_xlfn.XLOOKUP(A13,Malls!B:B,Malls!G:G) -> 46785.72 | T13: =_xlfn.XLOOKUP(M13,[1]Sheet1!$A:$A,[1]Sheet1!$E:$E) -> 0 | Z13: =_xlfn.XLOOKUP(A13,'SAP Report'!A:A,'SAP Report'!C:C) -> 46785.72 | AA13: =HLOOKUP($A$4,$AV$6:$BG13,(2+BH12),FALSE) -> 0 | AB13: =SUMIF('Open PR PO'!A:A,Monitoring!A13,'Open PR PO'!K:K) -> 46785.72 | AC13: =AA13+AB13 -> 46785.72 | AD13: =Z13-AC13 -> 0 | AE13: =Z13-AA13 -> 46785.72 | AG13: =SUMIFS(Actual!$F:$F,Actual!$N:$N,Monitoring!AG$6,Actual!$A:$A,Monitoring!$A13) -> 0 | AH13: =SUMIFS(Actual!$F:$F,Actual!$N:$N,Monitoring!AH$6,Actual!$A:$A,Monitoring!$A13) -> 0 | AI13: =SUMIFS(Actual!$F:$F,Actual!$N:$N,Monitoring!AI$6,Actual!$A:$A,Monitoring!$A13) -> 0 | AJ13: =SUMIFS(Actual!$F:$F,Actual!$N:$N,Monitoring!AJ$6,Actual!$A:$A,Monitoring!$A13) -> 0 | AK13: =SUMIFS(Actual!$F:$F,Actual!$N:$N,Monitoring!AK$6,Actual!$A:$A,Monitoring!$A13) -> 0 | AL13: =SUMIFS(Actual!$F:$F,Actual!$N:$N,Monitoring!AL$6,Actual!$A:$A,Monitoring!$A13) -> 0 | AM13: =SUMIFS(Actual!$F:$F,Actual!$N:$N,Monitoring!AM$6,Actual!$A:$A,Monitoring!$A13) -> 0 | AN13: =SUMIFS(Actual!$F:$F,Actual!$N:$N,Monitoring!AN$6,Actual!$A:$A,Monitoring!$A13) -> 0 | AO13: =SUMIFS(Actual!$F:$F,Actual!$N:$N,Monitoring!AO$6,Actual!$A:$A,Monitoring!$A13) -> 0 | AP13: =AB13 -> 46785.72 | AQ13: =AD13/2 -> 0 | AR13: =AQ13 -> 0 | AS13: =SUM(AG13:AR13) -> 46785.72 | AT13: =Z13-AS13 -> 0 | AV13: =AG13 -> 0 | AW13: =AV13+AH13 -> 0 | AX13: =AW13+AI13 -> 0 | AY13: =AX13+AJ13 -> 0 | AZ13: =AY13+AK13 -> 0 | BA13: =AZ13+AL13 -> 0 | BB13: =BA13+AM13 -> 0 | BC13: =BB13+AN13 -> 0 | BD13: =BC13+AO13 -> 0 | ... BG13: =BF13+AR13 -> 46785.72 | BH13: =BH12+1 -> 7
A14: 10001294 | B14: GH TIANGGE STALLS ELECTRICAL | C14: MALLS | D14: MALLS | F14: N | G14: Carry-over | R14: =_xlfn.XLOOKUP(A14,Malls!B:B,Malls!G:G)+900000 -> 4560714.3 | T14: =_xlfn.XLOOKUP(M14,[1]Sheet1!$A:$A,[1]Sheet1!$E:$E) -> 0 | X14: 0300011437 | Z14: =_xlfn.XLOOKUP(A14,'SAP Report'!A:A,'SAP Report'!C:C) -> 4560714.3 | AA14: =HLOOKUP($A$4,$AV$6:$BG14,(2+BH13),FALSE) -> 4253567.6 | AB14: =SUMIF('Open PR PO'!A:A,Monitoring!A14,'Open PR PO'!K:K) -> 0 | AC14: =AA14+AB14 -> 4253567.6 | AD14: =Z14-AC14 -> 307146.69 | AE14: =Z14-AA14 -> 307146.69 | AG14: =SUMIFS(Actual!$F:$F,Actual!$N:$N,Monitoring!AG$6,Actual!$A:$A,Monitoring!$A14) -> 0 | AH14: =SUMIFS(Actual!$F:$F,Actual!$N:$N,Monitoring!AH$6,Actual!$A:$A,Monitoring!$A14) -> 0 | AI14: =SUMIFS(Actual!$F:$F,Actual!$N:$N,Monitoring!AI$6,Actual!$A:$A,Monitoring!$A14) -> 2233035.7 | AJ14: =SUMIFS(Actual!$F:$F,Actual!$N:$N,Monitoring!AJ$6,Actual!$A:$A,Monitoring!$A14) -> 1427678.6 | AK14: =SUMIFS(Actual!$F:$F,Actual!$N:$N,Monitoring!AK$6,Actual!$A:$A,Monitoring!$A14) -> 0 | AL14: =SUMIFS(Actual!$F:$F,Actual!$N:$N,Monitoring!AL$6,Actual!$A:$A,Monitoring!$A14) -> 0 | AM14: =SUMIFS(Actual!$F:$F,Actual!$N:$N,Monitoring!AM$6,Actual!$A:$A,Monitoring!$A14) -> 584978.31 | AN14: =SUMIFS(Actual!$F:$F,Actual!$N:$N,Monitoring!AN$6,Actual!$A:$A,Monitoring!$A14) -> 7875 | AO14: =SUMIFS(Actual!$F:$F,Actual!$N:$N,Monitoring!AO$6,Actual!$A:$A,Monitoring!$A14) -> 0 | AP14: =AB14 -> 0 | AQ14: =AD14/2 -> 153573.35 | AR14: =AQ14 -> 153573.35 | AS14: =SUM(AG14:AR14) -> 4560714.3 | AT14: =Z14-AS14 -> 0 | AV14: =AG14 -> 0 | AW14: =AV14+AH14 -> 0 | AX14: =AW14+AI14 -> 2233035.7 | AY14: =AX14+AJ14 -> 3660714.3 | AZ14: =AY14+AK14 -> 3660714.3 | BA14: =AZ14+AL14 -> 3660714.3 | BB14: =BA14+AM14 -> 4245692.6 | BC14: =BB14+AN14 -> 4253567.6 | BD14: =BC14+AO14 -> 4253567.6 | ... BG14: =BF14+AR14 -> 4560714.3 | BH14: =BH13+1 -> 8
A15: 10001302 | B15: GH TENANT RECUTS | C15: MALLS | D15: MALLS | F15: N | G15: Carry-over | R15: =_xlfn.XLOOKUP(A15,Malls!B:B,Malls!G:G) -> 278743.18 | T15: =_xlfn.XLOOKUP(M15,[1]Sheet1!$A:$A,[1]Sheet1!$E:$E) -> 0 | Z15: =_xlfn.XLOOKUP(A15,'SAP Report'!A:A,'SAP Report'!C:C) -> 278743.18 | AA15: =HLOOKUP($A$4,$AV$6:$BG15,(2+BH14),FALSE) -> 0 | AB15: =SUMIF('Open PR PO'!A:A,Monitoring!A15,'Open PR PO'!K:K) -> 278743.18 | AC15: =AA15+AB15 -> 278743.18 | AD15: =Z15-AC15 -> 0 | AE15: =Z15-AA15 -> 278743.18 | AG15: =SUMIFS(Actual!$F:$F,Actual!$N:$N,Monitoring!AG$6,Actual!$A:$A,Monitoring!$A15) -> 0 | AH15: =SUMIFS(Actual!$F:$F,Actual!$N:$N,Monitoring!AH$6,Actual!$A:$A,Monitoring!$A15) -> 0 | AI15: =SUMIFS(Actual!$F:$F,Actual!$N:$N,Monitoring!AI$6,Actual!$A:$A,Monitoring!$A15) -> 0 | AJ15: =SUMIFS(Actual!$F:$F,Actual!$N:$N,Monitoring!AJ$6,Actual!$A:$A,Monitoring!$A15) -> 0 | AK15: =SUMIFS(Actual!$F:$F,Actual!$N:$N,Monitoring!AK$6,Actual!$A:$A,Monitoring!$A15) -> 0 | AL15: =SUMIFS(Actual!$F:$F,Actual!$N:$N,Monitoring!AL$6,Actual!$A:$A,Monitoring!$A15) -> 0 | AM15: =SUMIFS(Actual!$F:$F,Actual!$N:$N,Monitoring!AM$6,Actual!$A:$A,Monitoring!$A15) -> 0 | AN15: =SUMIFS(Actual!$F:$F,Actual!$N:$N,Monitoring!AN$6,Actual!$A:$A,Monitoring!$A15) -> 0 | AO15: =SUMIFS(Actual!$F:$F,Actual!$N:$N,Monitoring!AO$6,Actual!$A:$A,Monitoring!$A15) -> 0 | AP15: =AB15 -> 278743.18 | AQ15: =AD15/2 -> 0 | AR15: =AQ15 -> 0 | AS15: =SUM(AG15:AR15) -> 278743.18 | AT15: =Z15-AS15 -> 0 | AV15: =AG15 -> 0 | AW15: =AV15+AH15 -> 0 | AX15: =AW15+AI15 -> 0 | AY15: =AX15+AJ15 -> 0 | AZ15: =AY15+AK15 -> 0 | BA15: =AZ15+AL15 -> 0 | BB15: =BA15+AM15 -> 0 | BC15: =BB15+AN15 -> 0 | BD15: =BC15+AO15 -> 0 | ... BG15: =BF15+AR15 -> 278743.18 | BH15: =BH14+1 -> 9
A16: 10001305 | B16: GH ANNEX ALFRESCO AREA COLUM | C16: MALLS | D16: MALLS | F16: N | G16: Carry-over | R16: =_xlfn.XLOOKUP(A16,Malls!B:B,Malls!G:G) -> 356250 | T16: =_xlfn.XLOOKUP(M16,[1]Sheet1!$A:$A,[1]Sheet1!$E:$E) -> 0 | Z16: =_xlfn.XLOOKUP(A16,'SAP Report'!A:A,'SAP Report'!C:C) -> 356250 | AA16: =HLOOKUP($A$4,$AV$6:$BG16,(2+BH15),FALSE) -> 0 | AB16: =SUMIF('Open PR PO'!A:A,Monitoring!A16,'Open PR PO'!K:K) -> 356250 | AC16: =AA16+AB16 -> 356250 | AD16: =Z16-AC16 -> 0 | AE16: =Z16-AA16 -> 356250 | AG16: =SUMIFS(Actual!$F:$F,Actual!$N:$N,Monitoring!AG$6,Actual!$A:$A,Monitoring!$A16) -> 0 | AH16: =SUMIFS(Actual!$F:$F,Actual!$N:$N,Monitoring!AH$6,Actual!$A:$A,Monitoring!$A16) -> 0 | AI16: =SUMIFS(Actual!$F:$F,Actual!$N:$N,Monitoring!AI$6,Actual!$A:$A,Monitoring!$A16) -> 0 | AJ16: =SUMIFS(Actual!$F:$F,Actual!$N:$N,Monitoring!AJ$6,Actual!$A:$A,Monitoring!$A16) -> 0 | AK16: =SUMIFS(Actual!$F:$F,Actual!$N:$N,Monitoring!AK$6,Actual!$A:$A,Monitoring!$A16) -> 0 | AL16: =SUMIFS(Actual!$F:$F,Actual!$N:$N,Monitoring!AL$6,Actual!$A:$A,Monitoring!$A16) -> 0 | AM16: =SUMIFS(Actual!$F:$F,Actual!$N:$N,Monitoring!AM$6,Actual!$A:$A,Monitoring!$A16) -> 0 | AN16: =SUMIFS(Actual!$F:$F,Actual!$N:$N,Monitoring!AN$6,Actual!$A:$A,Monitoring!$A16) -> 0 | AO16: =SUMIFS(Actual!$F:$F,Actual!$N:$N,Monitoring!AO$6,Actual!$A:$A,Monitoring!$A16) -> 0 | AP16: =AB16 -> 356250 | AQ16: =AD16/2 -> 0 | AR16: =AQ16 -> 0 | AS16: =SUM(AG16:AR16) -> 356250 | AT16: =Z16-AS16 -> 0 | AV16: =AG16 -> 0 | AW16: =AV16+AH16 -> 0 | AX16: =AW16+AI16 -> 0 | AY16: =AX16+AJ16 -> 0 | AZ16: =AY16+AK16 -> 0 | BA16: =AZ16+AL16 -> 0 | BB16: =BA16+AM16 -> 0 | BC16: =BB16+AN16 -> 0 | BD16: =BC16+AO16 -> 0 | ... BG16: =BF16+AR16 -> 356250 | BH16: =BH15+1 -> 10
A17: 10001312 | B17: EM EAST WING CHAPEL AIRCON A | C17: MALLS | D17: MALLS | F17: N | G17: Carry-over | R17: =_xlfn.XLOOKUP(A17,Malls!B:B,Malls!G:G) -> 12232.14 | T17: =_xlfn.XLOOKUP(M17,[1]Sheet1!$A:$A,[1]Sheet1!$E:$E) -> 0 | Z17: =_xlfn.XLOOKUP(A17,'SAP Report'!A:A,'SAP Report'!C:C) -> 12232.14 | AA17: =HLOOKUP($A$4,$AV$6:$BG17,(2+BH16),FALSE) -> 0 | AB17: =SUMIF('Open PR PO'!A:A,Monitoring!A17,'Open PR PO'!K:K) -> 12232.14 | AC17: =AA17+AB17 -> 12232.14 | AD17: =Z17-AC17 -> 0 | AE17: =Z17-AA17 -> 12232.14 | AG17: =SUMIFS(Actual!$F:$F,Actual!$N:$N,Monitoring!AG$6,Actual!$A:$A,Monitoring!$A17) -> 0 | AH17: =SUMIFS(Actual!$F:$F,Actual!$N:$N,Monitoring!AH$6,Actual!$A:$A,Monitoring!$A17) -> 0 | AI17: =SUMIFS(Actual!$F:$F,Actual!$N:$N,Monitoring!AI$6,Actual!$A:$A,Monitoring!$A17) -> 0 | AJ17: =SUMIFS(Actual!$F:$F,Actual!$N:$N,Monitoring!AJ$6,Actual!$A:$A,Monitoring!$A17) -> 0 | AK17: =SUMIFS(Actual!$F:$F,Actual!$N:$N,Monitoring!AK$6,Actual!$A:$A,Monitoring!$A17) -> 0 | AL17: =SUMIFS(Actual!$F:$F,Actual!$N:$N,Monitoring!AL$6,Actual!$A:$A,Monitoring!$A17) -> 0 | AM17: =SUMIFS(Actual!$F:$F,Actual!$N:$N,Monitoring!AM$6,Actual!$A:$A,Monitoring!$A17) -> 0 | AN17: =SUMIFS(Actual!$F:$F,Actual!$N:$N,Monitoring!AN$6,Actual!$A:$A,Monitoring!$A17) -> 0 | AO17: =SUMIFS(Actual!$F:$F,Actual!$N:$N,Monitoring!AO$6,Actual!$A:$A,Monitoring!$A17) -> 0 | AP17: =AB17 -> 12232.14 | AQ17: =AD17/2 -> 0 | AR17: =AQ17 -> 0 | AS17: =SUM(AG17:AR17) -> 12232.14 | AT17: =Z17-AS17 -> 0 | AV17: =AG17 -> 0 | AW17: =AV17+AH17 -> 0 | AX17: =AW17+AI17 -> 0 | AY17: =AX17+AJ17 -> 0 | AZ17: =AY17+AK17 -> 0 | BA17: =AZ17+AL17 -> 0 | BB17: =BA17+AM17 -> 0 | BC17: =BB17+AN17 -> 0 | BD17: =BC17+AO17 -> 0 | ... BG17: =BF17+AR17 -> 12232.14 | BH17: =BH16+1 -> 11
A18: 10001315 | B18: GH MALL VIP READER SYSTEM FO | C18: MALLS | D18: MALLS | F18: N | G18: Carry-over | R18: =_xlfn.XLOOKUP(A18,Malls!B:B,Malls!G:G) -> 26321.43 | T18: =_xlfn.XLOOKUP(M18,[1]Sheet1!$A:$A,[1]Sheet1!$E:$E) -> 0 | Z18: =_xlfn.XLOOKUP(A18,'SAP Report'!A:A,'SAP Report'!C:C) -> 26321.43 | AA18: =HLOOKUP($A$4,$AV$6:$BG18,(2+BH17),FALSE) -> 133464.29 | AB18: =SUMIF('Open PR PO'!A:A,Monitoring!A18,'Open PR PO'!K:K) -> 0 | AC18: =AA18+AB18 -> 133464.29 | AD18: =Z18-AC18 -> -107142.86 | AE18: =Z18-AA18 -> -107142.86 | AG18: =SUMIFS(Actual!$F:$F,Actual!$N:$N,Monitoring!AG$6,Actual!$A:$A,Monitoring!$A18) -> 133464.29 | AH18: =SUMIFS(Actual!$F:$F,Actual!$N:$N,Monitoring!AH$6,Actual!$A:$A,Monitoring!$A18) -> 0 | AI18: =SUMIFS(Actual!$F:$F,Actual!$N:$N,Monitoring!AI$6,Actual!$A:$A,Monitoring!$A18) -> 0 | AJ18: =SUMIFS(Actual!$F:$F,Actual!$N:$N,Monitoring!AJ$6,Actual!$A:$A,Monitoring!$A18) -> 0 | AK18: =SUMIFS(Actual!$F:$F,Actual!$N:$N,Monitoring!AK$6,Actual!$A:$A,Monitoring!$A18) -> 0 | AL18: =SUMIFS(Actual!$F:$F,Actual!$N:$N,Monitoring!AL$6,Actual!$A:$A,Monitoring!$A18) -> 0 | AM18: =SUMIFS(Actual!$F:$F,Actual!$N:$N,Monitoring!AM$6,Actual!$A:$A,Monitoring!$A18) -> 0 | AN18: =SUMIFS(Actual!$F:$F,Actual!$N:$N,Monitoring!AN$6,Actual!$A:$A,Monitoring!$A18) -> 0 | AO18: =SUMIFS(Actual!$F:$F,Actual!$N:$N,Monitoring!AO$6,Actual!$A:$A,Monitoring!$A18) -> 0 | AP18: =AB18 -> 0 | AQ18: =AD18/2 -> -53571.43 | AR18: =AQ18 -> -53571.43 | AS18: =SUM(AG18:AR18) -> 26321.43 | AT18: =Z18-AS18 -> 0 | AV18: =AG18 -> 133464.29 | AW18: =AV18+AH18 -> 133464.29 | AX18: =AW18+AI18 -> 133464.29 | AY18: =AX18+AJ18 -> 133464.29 | AZ18: =AY18+AK18 -> 133464.29 | BA18: =AZ18+AL18 -> 133464.29 | BB18: =BA18+AM18 -> 133464.29 | BC18: =BB18+AN18 -> 133464.29 | BD18: =BC18+AO18 -> 133464.29 | ... BG18: =BF18+AR18 -> 26321.43 | BH18: =BH17+1 -> 12
A19: 10001342 | B19: GH EXISTING MALL PRE-WATERPR | C19: MALLS | D19: MALLS | F19: N | G19: Carry-over | R19: =_xlfn.XLOOKUP(A19,Malls!B:B,Malls!G:G) -> 341960.05 | T19: =_xlfn.XLOOKUP(M19,[1]Sheet1!$A:$A,[1]Sheet1!$E:$E) -> 0 | Z19: =_xlfn.XLOOKUP(A19,'SAP Report'!A:A,'SAP Report'!C:C) -> 341960.05 | AA19: =HLOOKUP($A$4,$AV$6:$BG19,(2+BH18),FALSE) -> 208214.29 | AB19: =SUMIF('Open PR PO'!A:A,Monitoring!A19,'Open PR PO'!K:K) -> 133745.76 | AC19: =AA19+AB19 -> 341960.05 | AD19: =Z19-AC19 -> 0 | AE19: =Z19-AA19 -> 133745.76 | AG19: =SUMIFS(Actual!$F:$F,Actual!$N:$N,Monitoring!AG$6,Actual!$A:$A,Monitoring!$A19) -> 0 | AH19: =SUMIFS(Actual!$F:$F,Actual!$N:$N,Monitoring!AH$6,Actual!$A:$A,Monitoring!$A19) -> 0 | AI19: =SUMIFS(Actual!$F:$F,Actual!$N:$N,Monitoring!AI$6,Actual!$A:$A,Monitoring!$A19) -> 0 | AJ19: =SUMIFS(Actual!$F:$F,Actual!$N:$N,Monitoring!AJ$6,Actual!$A:$A,Monitoring!$A19) -> 0 | AK19: =SUMIFS(Actual!$F:$F,Actual!$N:$N,Monitoring!AK$6,Actual!$A:$A,Monitoring!$A19) -> 0 | AL19: =SUMIFS(Actual!$F:$F,Actual!$N:$N,Monitoring!AL$6,Actual!$A:$A,Monitoring!$A19) -> 0 | AM19: =SUMIFS(Actual!$F:$F,Actual!$N:$N,Monitoring!AM$6,Actual!$A:$A,Monitoring!$A19) -> 208214.29 | AN19: =SUMIFS(Actual!$F:$F,Actual!$N:$N,Monitoring!AN$6,Actual!$A:$A,Monitoring!$A19) -> 0 | AO19: =SUMIFS(Actual!$F:$F,Actual!$N:$N,Monitoring!AO$6,Actual!$A:$A,Monitoring!$A19) -> 0 | AP19: =AB19 -> 133745.76 | AQ19: =AD19/2 -> 0 | AR19: =AQ19 -> 0 | AS19: =SUM(AG19:AR19) -> 341960.05 | AT19: =Z19-AS19 -> 0 | AV19: =AG19 -> 0 | AW19: =AV19+AH19 -> 0 | AX19: =AW19+AI19 -> 0 | AY19: =AX19+AJ19 -> 0 | AZ19: =AY19+AK19 -> 0 | BA19: =AZ19+AL19 -> 0 | BB19: =BA19+AM19 -> 208214.29 | BC19: =BB19+AN19 -> 208214.29 | BD19: =BC19+AO19 -> 208214.29 | ... BG19: =BF19+AR19 -> 341960.05 | BH19: =BH18+1 -> 13
A20: 10001348 | B20: GH VMALL CHAPEL RENOVATION | C20: MALLS | D20: MALLS | F20: N | G20: Carry-over | R20: =_xlfn.XLOOKUP(A20,Malls!B:B,Malls!G:G) -> 486257.14 | T20: =_xlfn.XLOOKUP(M20,[1]Sheet1!$A:$A,[1]Sheet1!$E:$E) -> 0 | Z20: =_xlfn.XLOOKUP(A20,'SAP Report'!A:A,'SAP Report'!C:C) -> 486257.14 | AA20: =HLOOKUP($A$4,$AV$6:$BG20,(2+BH19),FALSE) -> 0 | AB20: =SUMIF('Open PR PO'!A:A,Monitoring!A20,'Open PR PO'!K:K) -> 486257.14 | AC20: =AA20+AB20 -> 486257.14 | AD20: =Z20-AC20 -> 0 | AE20: =Z20-AA20 -> 486257.14 | AG20: =SUMIFS(Actual!$F:$F,Actual!$N:$N,Monitoring!AG$6,Actual!$A:$A,Monitoring!$A20) -> 0 | AH20: =SUMIFS(Actual!$F:$F,Actual!$N:$N,Monitoring!AH$6,Actual!$A:$A,Monitoring!$A20) -> 0 | AI20: =SUMIFS(Actual!$F:$F,Actual!$N:$N,Monitoring!AI$6,Actual!$A:$A,Monitoring!$A20) -> 0 | AJ20: =SUMIFS(Actual!$F:$F,Actual!$N:$N,Monitoring!AJ$6,Actual!$A:$A,Monitoring!$A20) -> 0 | AK20: =SUMIFS(Actual!$F:$F,Actual!$N:$N,Monitoring!AK$6,Actual!$A:$A,Monitoring!$A20) -> 0 | AL20: =SUMIFS(Actual!$F:$F,Actual!$N:$N,Monitoring!AL$6,Actual!$A:$A,Monitoring!$A20) -> 0 | AM20: =SUMIFS(Actual!$F:$F,Actual!$N:$N,Monitoring!AM$6,Actual!$A:$A,Monitoring!$A20) -> 0 | AN20: =SUMIFS(Actual!$F:$F,Actual!$N:$N,Monitoring!AN$6,Actual!$A:$A,Monitoring!$A20) -> 0 | AO20: =SUMIFS(Actual!$F:$F,Actual!$N:$N,Monitoring!AO$6,Actual!$A:$A,Monitoring!$A20) -> 0 | AP20: =AB20 -> 486257.14 | AQ20: =AD20/2 -> 0 | AR20: =AQ20 -> 0 | AS20: =SUM(AG20:AR20) -> 486257.14 | AT20: =Z20-AS20 -> 0 | AV20: =AG20 -> 0 | AW20: =AV20+AH20 -> 0 | AX20: =AW20+AI20 -> 0 | AY20: =AX20+AJ20 -> 0 | AZ20: =AY20+AK20 -> 0 | BA20: =AZ20+AL20 -> 0 | BB20: =BA20+AM20 -> 0 | BC20: =BB20+AN20 -> 0 | BD20: =BC20+AO20 -> 0 | ... BG20: =BF20+AR20 -> 486257.14 | BH20: =BH19+1 -> 14
A21: 10001374 | B21: GH MRF IMPROVEMENTS AND FAÇA | C21: MALLS | D21: MALLS | F21: N | G21: Carry-over | R21: =_xlfn.XLOOKUP(A21,Malls!B:B,Malls!G:G) -> 1316964.3 | T21: =_xlfn.XLOOKUP(M21,[1]Sheet1!$A:$A,[1]Sheet1!$E:$E) -> 0 | Z21: =_xlfn.XLOOKUP(A21,'SAP Report'!A:A,'SAP Report'!C:C) -> 1316964.3 | AA21: =HLOOKUP($A$4,$AV$6:$BG21,(2+BH20),FALSE) -> 1316964.3 | AB21: =SUMIF('Open PR PO'!A:A,Monitoring!A21,'Open PR PO'!K:K) -> 0 | AC21: =AA21+AB21 -> 1316964.3 | AD21: =Z21-AC21 -> 0.01 | AE21: =Z21-AA21 -> 0.01 | AG21: =SUMIFS(Actual!$F:$F,Actual!$N:$N,Monitoring!AG$6,Actual!$A:$A,Monitoring!$A21) -> 0 | AH21: =SUMIFS(Actual!$F:$F,Actual!$N:$N,Monitoring!AH$6,Actual!$A:$A,Monitoring!$A21) -> 363616.07 | AI21: =SUMIFS(Actual!$F:$F,Actual!$N:$N,Monitoring!AI$6,Actual!$A:$A,Monitoring!$A21) -> 828125 | AJ21: =SUMIFS(Actual!$F:$F,Actual!$N:$N,Monitoring!AJ$6,Actual!$A:$A,Monitoring!$A21) -> 125223.21 | AK21: =SUMIFS(Actual!$F:$F,Actual!$N:$N,Monitoring!AK$6,Actual!$A:$A,Monitoring!$A21) -> 0 | AL21: =SUMIFS(Actual!$F:$F,Actual!$N:$N,Monitoring!AL$6,Actual!$A:$A,Monitoring!$A21) -> 0 | AM21: =SUMIFS(Actual!$F:$F,Actual!$N:$N,Monitoring!AM$6,Actual!$A:$A,Monitoring!$A21) -> 0 | AN21: =SUMIFS(Actual!$F:$F,Actual!$N:$N,Monitoring!AN$6,Actual!$A:$A,Monitoring!$A21) -> 0 | AO21: =SUMIFS(Actual!$F:$F,Actual!$N:$N,Monitoring!AO$6,Actual!$A:$A,Monitoring!$A21) -> 0 | AP21: =AB21 -> 0 | AQ21: =AD21/2 -> 0.005 | AR21: =AQ21 -> 0.005 | AS21: =SUM(AG21:AR21) -> 1316964.3 | AT21: =Z21-AS21 -> 0 | AV21: =AG21 -> 0 | AW21: =AV21+AH21 -> 363616.07 | AX21: =AW21+AI21 -> 1191741.1 | AY21: =AX21+AJ21 -> 1316964.3 | AZ21: =AY21+AK21 -> 1316964.3 | BA21: =AZ21+AL21 -> 1316964.3 | BB21: =BA21+AM21 -> 1316964.3 | BC21: =BB21+AN21 -> 1316964.3 | BD21: =BC21+AO21 -> 1316964.3 | ... BG21: =BF21+AR21 -> 1316964.3 | BH21: =BH20+1 -> 15
A22: 10001298 | B22: CC DRAINAGE IMPROVEMENT PH1A | C22: ESTATES | D22: ESTATES | F22: N | G22: Carry-over | R22: =Z22 -> 7190.4 | Z22: =_xlfn.XLOOKUP(A22,'SAP Report'!A:A,'SAP Report'!C:C) -> 7190.4 | AA22: =HLOOKUP($A$4,$AV$6:$BG22,(2+BH21),FALSE) -> -0.01 | AB22: =SUMIF('Open PR PO'!A:A,Monitoring!A22,'Open PR PO'!K:K) -> 7190.4 | AC22: =AA22+AB22 -> 7190.39 | AD22: =Z22-AC22 -> 0.01 | AE22: =Z22-AA22 -> 7190.41 | AG22: =SUMIFS(Actual!$F:$F,Actual!$N:$N,Monitoring!AG$6,Actual!$A:$A,Monitoring!$A22) -> 0 | AH22: =SUMIFS(Actual!$F:$F,Actual!$N:$N,Monitoring!AH$6,Actual!$A:$A,Monitoring!$A22) -> 0 | AI22: =SUMIFS(Actual!$F:$F,Actual!$N:$N,Monitoring!AI$6,Actual!$A:$A,Monitoring!$A22) -> 0 | AJ22: =SUMIFS(Actual!$F:$F,Actual!$N:$N,Monitoring!AJ$6,Actual!$A:$A,Monitoring!$A22) -> 0 | AK22: =SUMIFS(Actual!$F:$F,Actual!$N:$N,Monitoring!AK$6,Actual!$A:$A,Monitoring!$A22) -> 0 | AL22: =SUMIFS(Actual!$F:$F,Actual!$N:$N,Monitoring!AL$6,Actual!$A:$A,Monitoring!$A22) -> -0.01 | AM22: =SUMIFS(Actual!$F:$F,Actual!$N:$N,Monitoring!AM$6,Actual!$A:$A,Monitoring!$A22) -> 0 | AN22: =SUMIFS(Actual!$F:$F,Actual!$N:$N,Monitoring!AN$6,Actual!$A:$A,Monitoring!$A22) -> 0 | AO22: =SUMIFS(Actual!$F:$F,Actual!$N:$N,Monitoring!AO$6,Actual!$A:$A,Monitoring!$A22) -> 0 | AP22: =AB22 -> 7190.4 | AQ22: =AD22/2 -> 0.005 | AR22: =AQ22 -> 0.005 | AS22: =SUM(AG22:AR22) -> 7190.4 | AT22: =Z22-AS22 -> 0 | AV22: =AG22 -> 0 | AW22: =AV22+AH22 -> 0 | AX22: =AW22+AI22 -> 0 | AY22: =AX22+AJ22 -> 0 | AZ22: =AY22+AK22 -> 0 | BA22: =AZ22+AL22 -> -0.01 | BB22: =BA22+AM22 -> -0.01 | BC22: =BB22+AN22 -> -0.01 | BD22: =BC22+AO22 -> -0.01 | ... BG22: =BF22+AR22 -> 7190.4 | BH22: =BH21+1 -> 16
A23: 10001322 | B23: CC DRAINAGE IMPROVEMENT PHASE2 | C23: ESTATES | D23: ESTATES | F23: N | G23: Carry-over | R23: =Z23 -> 15000000 | Z23: =_xlfn.XLOOKUP(A23,'SAP Report'!A:A,'SAP Report'!C:C) -> 15000000 | AA23: =HLOOKUP($A$4,$AV$6:$BG23,(2+BH22),FALSE) -> 6300000 | AB23: =SUMIF('Open PR PO'!A:A,Monitoring!A23,'Open PR PO'!K:K) -> 8700000 | AC23: =AA23+AB23 -> 15000000 | AD23: =Z23-AC23 -> 0 | AE23: =Z23-AA23 -> 8700000 | AG23: =SUMIFS(Actual!$F:$F,Actual!$N:$N,Monitoring!AG$6,Actual!$A:$A,Monitoring!$A23) -> 0 | AH23: =SUMIFS(Actual!$F:$F,Actual!$N:$N,Monitoring!AH$6,Actual!$A:$A,Monitoring!$A23) -> 0 | AI23: =SUMIFS(Actual!$F:$F,Actual!$N:$N,Monitoring!AI$6,Actual!$A:$A,Monitoring!$A23) -> 0 | AJ23: =SUMIFS(Actual!$F:$F,Actual!$N:$N,Monitoring!AJ$6,Actual!$A:$A,Monitoring!$A23) -> 0 | AK23: =SUMIFS(Actual!$F:$F,Actual!$N:$N,Monitoring!AK$6,Actual!$A:$A,Monitoring!$A23) -> 6750000 | AL23: =SUMIFS(Actual!$F:$F,Actual!$N:$N,Monitoring!AL$6,Actual!$A:$A,Monitoring!$A23) -> 0 | AM23: =SUMIFS(Actual!$F:$F,Actual!$N:$N,Monitoring!AM$6,Actual!$A:$A,Monitoring!$A23) -> -450000 | AN23: =SUMIFS(Actual!$F:$F,Actual!$N:$N,Monitoring!AN$6,Actual!$A:$A,Monitoring!$A23) -> 0 | AO23: =SUMIFS(Actual!$F:$F,Actual!$N:$N,Monitoring!AO$6,Actual!$A:$A,Monitoring!$A23) -> 0 | AP23: =AB23 -> 8700000 | AQ23: =AD23/2 -> 0 | AR23: =AQ23 -> 0 | AS23: =SUM(AG23:AR23) -> 15000000 | AT23: =Z23-AS23 -> 0 | AV23: =AG23 -> 0 | AW23: =AV23+AH23 -> 0 | AX23: =AW23+AI23 -> 0 | AY23: =AX23+AJ23 -> 0 | AZ23: =AY23+AK23 -> 6750000 | BA23: =AZ23+AL23 -> 6750000 | BB23: =BA23+AM23 -> 6300000 | BC23: =BB23+AN23 -> 6300000 | BD23: =BC23+AO23 -> 6300000 | ... BG23: =BF23+AR23 -> 15000000 | BH23: =BH22+1 -> 17
A24: 10001362 | B24: CC STP REHAB AND REPAIR | C24: ESTATES | D24: ESTATES | F24: N | G24: Carry-over | R24: =Z24 -> 366071.43 | Z24: =_xlfn.XLOOKUP(A24,'SAP Report'!A:A,'SAP Report'!C:C) -> 366071.43 | AA24: =HLOOKUP($A$4,$AV$6:$BG24,(2+BH23),FALSE) -> 366071.43 | AB24: =SUMIF('Open PR PO'!A:A,Monitoring!A24,'Open PR PO'!K:K) -> 0 | AC24: =AA24+AB24 -> 366071.43 | AD24: =Z24-AC24 -> 0 | AE24: =Z24-AA24 -> 0 | AG24: =SUMIFS(Actual!$F:$F,Actual!$N:$N,Monitoring!AG$6,Actual!$A:$A,Monitoring!$A24) -> 0 | AH24: =SUMIFS(Actual!$F:$F,Actual!$N:$N,Monitoring!AH$6,Actual!$A:$A,Monitoring!$A24) -> 0 | AI24: =SUMIFS(Actual!$F:$F,Actual!$N:$N,Monitoring!AI$6,Actual!$A:$A,Monitoring!$A24) -> 0 | AJ24: =SUMIFS(Actual!$F:$F,Actual!$N:$N,Monitoring!AJ$6,Actual!$A:$A,Monitoring!$A24) -> 0 | AK24: =SUMIFS(Actual!$F:$F,Actual!$N:$N,Monitoring!AK$6,Actual!$A:$A,Monitoring!$A24) -> 0 | AL24: =SUMIFS(Actual!$F:$F,Actual!$N:$N,Monitoring!AL$6,Actual!$A:$A,Monitoring!$A24) -> 0 | AM24: =SUMIFS(Actual!$F:$F,Actual!$N:$N,Monitoring!AM$6,Actual!$A:$A,Monitoring!$A24) -> 366071.43 | AN24: =SUMIFS(Actual!$F:$F,Actual!$N:$N,Monitoring!AN$6,Actual!$A:$A,Monitoring!$A24) -> 0 | AO24: =SUMIFS(Actual!$F:$F,Actual!$N:$N,Monitoring!AO$6,Actual!$A:$A,Monitoring!$A24) -> 0 | AP24: =AB24 -> 0 | AQ24: =AD24/2 -> 0 | AR24: =AQ24 -> 0 | AS24: =SUM(AG24:AR24) -> 366071.43 | AT24: =Z24-AS24 -> 0 | AV24: =AG24 -> 0 | AW24: =AV24+AH24 -> 0 | AX24: =AW24+AI24 -> 0 | AY24: =AX24+AJ24 -> 0 | AZ24: =AY24+AK24 -> 0 | BA24: =AZ24+AL24 -> 0 | BB24: =BA24+AM24 -> 366071.43 | BC24: =BB24+AN24 -> 366071.43 | BD24: =BC24+AO24 -> 366071.43 | ... BG24: =BF24+AR24 -> 366071.43 | BH24: =BH23+1 -> 18
A25: 10001372 | B25: ORTIGAS PARKLANE PARKING SYS | C25: ESTATES | D25: ESTATES | F25: N | G25: Carry-over | R25: =Z25 -> 321428.57 | Z25: =_xlfn.XLOOKUP(A25,'SAP Report'!A:A,'SAP Report'!C:C) -> 321428.57 | AA25: =HLOOKUP($A$4,$AV$6:$BG25,(2+BH24),FALSE) -> 0 | AB25: =SUMIF('Open PR PO'!A:A,Monitoring!A25,'Open PR PO'!K:K) -> 321428.57 | AC25: =AA25+AB25 -> 321428.57 | AD25: =Z25-AC25 -> 0 | AE25: =Z25-AA25 -> 321428.57 | AG25: =SUMIFS(Actual!$F:$F,Actual!$N:$N,Monitoring!AG$6,Actual!$A:$A,Monitoring!$A25) -> 0 | AH25: =SUMIFS(Actual!$F:$F,Actual!$N:$N,Monitoring!AH$6,Actual!$A:$A,Monitoring!$A25) -> 0 | AI25: =SUMIFS(Actual!$F:$F,Actual!$N:$N,Monitoring!AI$6,Actual!$A:$A,Monitoring!$A25) -> 0 | AJ25: =SUMIFS(Actual!$F:$F,Actual!$N:$N,Monitoring!AJ$6,Actual!$A:$A,Monitoring!$A25) -> 0 | AK25: =SUMIFS(Actual!$F:$F,Actual!$N:$N,Monitoring!AK$6,Actual!$A:$A,Monitoring!$A25) -> 0 | AL25: =SUMIFS(Actual!$F:$F,Actual!$N:$N,Monitoring!AL$6,Actual!$A:$A,Monitoring!$A25) -> 0 | AM25: =SUMIFS(Actual!$F:$F,Actual!$N:$N,Monitoring!AM$6,Actual!$A:$A,Monitoring!$A25) -> 0 | AN25: =SUMIFS(Actual!$F:$F,Actual!$N:$N,Monitoring!AN$6,Actual!$A:$A,Monitoring!$A25) -> 0 | AO25: =SUMIFS(Actual!$F:$F,Actual!$N:$N,Monitoring!AO$6,Actual!$A:$A,Monitoring!$A25) -> 0 | AP25: =AB25 -> 321428.57 | AQ25: =AD25/2 -> 0 | AR25: =AQ25 -> 0 | AS25: =SUM(AG25:AR25) -> 321428.57 | AT25: =Z25-AS25 -> 0 | AV25: =AG25 -> 0 | AW25: =AV25+AH25 -> 0 | AX25: =AW25+AI25 -> 0 | AY25: =AX25+AJ25 -> 0 | AZ25: =AY25+AK25 -> 0 | BA25: =AZ25+AL25 -> 0 | BB25: =BA25+AM25 -> 0 | BC25: =BB25+AN25 -> 0 | BD25: =BC25+AO25 -> 0 | ... BG25: =BF25+AR25 -> 321428.57 | BH25: =BH24+1 -> 19
A26: 10001320 | B26: THE STRIP SEISMIC ACCELEROGR | C26: ESTATES | D26: ESTATES | F26: N | G26: Carry-over | R26: =Z26 -> 875000 | Z26: =_xlfn.XLOOKUP(A26,'SAP Report'!A:A,'SAP Report'!C:C) -> 875000 | AA26: =HLOOKUP($A$4,$AV$6:$BG26,(2+BH25),FALSE) -> 0 | AB26: =SUMIF('Open PR PO'!A:A,Monitoring!A26,'Open PR PO'!K:K) -> 875000 | AC26: =AA26+AB26 -> 875000 | AD26: =Z26-AC26 -> 0 | AE26: =Z26-AA26 -> 875000 | AG26: =SUMIFS(Actual!$F:$F,Actual!$N:$N,Monitoring!AG$6,Actual!$A:$A,Monitoring!$A26) -> 0 | AH26: =SUMIFS(Actual!$F:$F,Actual!$N:$N,Monitoring!AH$6,Actual!$A:$A,Monitoring!$A26) -> 0 | AI26: =SUMIFS(Actual!$F:$F,Actual!$N:$N,Monitoring!AI$6,Actual!$A:$A,Monitoring!$A26) -> 0 | AJ26: =SUMIFS(Actual!$F:$F,Actual!$N:$N,Monitoring!AJ$6,Actual!$A:$A,Monitoring!$A26) -> 0 | AK26: =SUMIFS(Actual!$F:$F,Actual!$N:$N,Monitoring!AK$6,Actual!$A:$A,Monitoring!$A26) -> 0 | AL26: =SUMIFS(Actual!$F:$F,Actual!$N:$N,Monitoring!AL$6,Actual!$A:$A,Monitoring!$A26) -> 0 | AM26: =SUMIFS(Actual!$F:$F,Actual!$N:$N,Monitoring!AM$6,Actual!$A:$A,Monitoring!$A26) -> 0 | AN26: =SUMIFS(Actual!$F:$F,Actual!$N:$N,Monitoring!AN$6,Actual!$A:$A,Monitoring!$A26) -> 0 | AO26: =SUMIFS(Actual!$F:$F,Actual!$N:$N,Monitoring!AO$6,Actual!$A:$A,Monitoring!$A26) -> 0 | AP26: =AB26 -> 875000 | AQ26: =AD26/2 -> 0 | AR26: =AQ26 -> 0 | AS26: =SUM(AG26:AR26) -> 875000 | AT26: =Z26-AS26 -> 0 | AV26: =AG26 -> 0 | AW26: =AV26+AH26 -> 0 | AX26: =AW26+AI26 -> 0 | AY26: =AX26+AJ26 -> 0 | AZ26: =AY26+AK26 -> 0 | BA26: =AZ26+AL26 -> 0 | BB26: =BA26+AM26 -> 0 | BC26: =BB26+AN26 -> 0 | BD26: =BC26+AO26 -> 0 | ... BG26: =BF26+AR26 -> 875000 | BH26: =BH25+1 -> 20
A27: 10001378 | B27: THE STRIP VARIOUS TENANCY PR | C27: ESTATES | D27: ESTATES | F27: N | G27: Carry-over | R27: =Z27 -> 1178571.4 | Z27: =_xlfn.XLOOKUP(A27,'SAP Report'!A:A,'SAP Report'!C:C) -> 1178571.4 | AA27: =HLOOKUP($A$4,$AV$6:$BG27,(2+BH26),FALSE) -> 346071.43 | AB27: =SUMIF('Open PR PO'!A:A,Monitoring!A27,'Open PR PO'!K:K) -> 832500 | AC27: =AA27+AB27 -> 1178571.4 | AD27: =Z27-AC27 -> 0 | AE27: =Z27-AA27 -> 832500 | AG27: =SUMIFS(Actual!$F:$F,Actual!$N:$N,Monitoring!AG$6,Actual!$A:$A,Monitoring!$A27) -> 0 | AH27: =SUMIFS(Actual!$F:$F,Actual!$N:$N,Monitoring!AH$6,Actual!$A:$A,Monitoring!$A27) -> 0 | AI27: =SUMIFS(Actual!$F:$F,Actual!$N:$N,Monitoring!AI$6,Actual!$A:$A,Monitoring!$A27) -> 0 | AJ27: =SUMIFS(Actual!$F:$F,Actual!$N:$N,Monitoring!AJ$6,Actual!$A:$A,Monitoring!$A27) -> 0 | AK27: =SUMIFS(Actual!$F:$F,Actual!$N:$N,Monitoring!AK$6,Actual!$A:$A,Monitoring!$A27) -> 346071.43 | AL27: =SUMIFS(Actual!$F:$F,Actual!$N:$N,Monitoring!AL$6,Actual!$A:$A,Monitoring!$A27) -> 0 | AM27: =SUMIFS(Actual!$F:$F,Actual!$N:$N,Monitoring!AM$6,Actual!$A:$A,Monitoring!$A27) -> 0 | AN27: =SUMIFS(Actual!$F:$F,Actual!$N:$N,Monitoring!AN$6,Actual!$A:$A,Monitoring!$A27) -> 0 | AO27: =SUMIFS(Actual!$F:$F,Actual!$N:$N,Monitoring!AO$6,Actual!$A:$A,Monitoring!$A27) -> 0 | AP27: =AB27 -> 832500 | AQ27: =AD27/2 -> 0 | AR27: =AQ27 -> 0 | AS27: =SUM(AG27:AR27) -> 1178571.4 | AT27: =Z27-AS27 -> 0 | AV27: =AG27 -> 0 | AW27: =AV27+AH27 -> 0 | AX27: =AW27+AI27 -> 0 | AY27: =AX27+AJ27 -> 0 | AZ27: =AY27+AK27 -> 346071.43 | BA27: =AZ27+AL27 -> 346071.43 | BB27: =BA27+AM27 -> 346071.43 | BC27: =BB27+AN27 -> 346071.43 | BD27: =BC27+AO27 -> 346071.43 | ... BG27: =BF27+AR27 -> 1178571.4 | BH27: =BH26+1 -> 21
A28: 10001308 | B28: CC PASIG CIVIC CENTER | C28: ESTATES | D28: ESTATES | F28: Y | G28: Carry-over | R28: =Z28 -> 25714286 | Z28: =_xlfn.XLOOKUP(A28,'SAP Report'!A:A,'SAP Report'!C:C) -> 25714286 | AA28: =HLOOKUP($A$4,$AV$6:$BG28,(2+BH27),FALSE) -> 0 | AB28: =SUMIF('Open PR PO'!A:A,Monitoring!A28,'Open PR PO'!K:K) -> 0 | AC28: =AA28+AB28 -> 0 | AD28: =Z28-AC28 -> 25714286 | AE28: =Z28-AA28 -> 25714286 | AG28: =SUMIFS(Actual!$F:$F,Actual!$N:$N,Monitoring!AG$6,Actual!$A:$A,Monitoring!$A28) -> 0 | AH28: =SUMIFS(Actual!$F:$F,Actual!$N:$N,Monitoring!AH$6,Actual!$A:$A,Monitoring!$A28) -> 0 | AI28: =SUMIFS(Actual!$F:$F,Actual!$N:$N,Monitoring!AI$6,Actual!$A:$A,Monitoring!$A28) -> 0 | AJ28: =SUMIFS(Actual!$F:$F,Actual!$N:$N,Monitoring!AJ$6,Actual!$A:$A,Monitoring!$A28) -> 0 | AK28: =SUMIFS(Actual!$F:$F,Actual!$N:$N,Monitoring!AK$6,Actual!$A:$A,Monitoring!$A28) -> 0 | AL28: =SUMIFS(Actual!$F:$F,Actual!$N:$N,Monitoring!AL$6,Actual!$A:$A,Monitoring!$A28) -> 0 | AM28: =SUMIFS(Actual!$F:$F,Actual!$N:$N,Monitoring!AM$6,Actual!$A:$A,Monitoring!$A28) -> 0 | AN28: =SUMIFS(Actual!$F:$F,Actual!$N:$N,Monitoring!AN$6,Actual!$A:$A,Monitoring!$A28) -> 0 | AO28: =SUMIFS(Actual!$F:$F,Actual!$N:$N,Monitoring!AO$6,Actual!$A:$A,Monitoring!$A28) -> 0 | AP28: =AB28 -> 0 | AQ28: =AD28/2 -> 12857143 | AR28: =AQ28 -> 12857143 | AS28: =SUM(AG28:AR28) -> 25714286 | AT28: =Z28-AS28 -> 0 | AV28: =AG28 -> 0 | AW28: =AV28+AH28 -> 0 | AX28: =AW28+AI28 -> 0 | AY28: =AX28+AJ28 -> 0 | AZ28: =AY28+AK28 -> 0 | BA28: =AZ28+AL28 -> 0 | BB28: =BA28+AM28 -> 0 | BC28: =BB28+AN28 -> 0 | BD28: =BC28+AO28 -> 0 | ... BG28: =BF28+AR28 -> 25714286 | BH28: =BH27+1 -> 22
A29: 10001341 | B29: CC PARK REDEVELOPMENT | C29: ESTATES | D29: ESTATES | F29: Y | G29: Carry-over | R29: =Z29 -> 50718878 | Z29: =_xlfn.XLOOKUP(A29,'SAP Report'!A:A,'SAP Report'!C:C) -> 50718878 | AA29: =HLOOKUP($A$4,$AV$6:$BG29,(2+BH28),FALSE) -> 24715944 | AB29: =SUMIF('Open PR PO'!A:A,Monitoring!A29,'Open PR PO'!K:K) -> 20320127 | AC29: =AA29+AB29 -> 45036072 | AD29: =Z29-AC29 -> 5682806.2 | AE29: =Z29-AA29 -> 26002934 | AG29: =SUMIFS(Actual!$F:$F,Actual!$N:$N,Monitoring!AG$6,Actual!$A:$A,Monitoring!$A29) -> 54884.55 | AH29: =SUMIFS(Actual!$F:$F,Actual!$N:$N,Monitoring!AH$6,Actual!$A:$A,Monitoring!$A29) -> 274 | AI29: =SUMIFS(Actual!$F:$F,Actual!$N:$N,Monitoring!AI$6,Actual!$A:$A,Monitoring!$A29) -> 1555428.6 | AJ29: =SUMIFS(Actual!$F:$F,Actual!$N:$N,Monitoring!AJ$6,Actual!$A:$A,Monitoring!$A29) -> 3596250 | AK29: =SUMIFS(Actual!$F:$F,Actual!$N:$N,Monitoring!AK$6,Actual!$A:$A,Monitoring!$A29) -> 0 | AL29: =SUMIFS(Actual!$F:$F,Actual!$N:$N,Monitoring!AL$6,Actual!$A:$A,Monitoring!$A29) -> 2611607.1 | AM29: =SUMIFS(Actual!$F:$F,Actual!$N:$N,Monitoring!AM$6,Actual!$A:$A,Monitoring!$A29) -> 11514286 | AN29: =SUMIFS(Actual!$F:$F,Actual!$N:$N,Monitoring!AN$6,Actual!$A:$A,Monitoring!$A29) -> 3669866.1 | AO29: =SUMIFS(Actual!$F:$F,Actual!$N:$N,Monitoring!AO$6,Actual!$A:$A,Monitoring!$A29) -> 1713348.2 | AP29: =AB29 -> 20320127 | AQ29: =AD29/2 -> 2841403.1 | AR29: =AQ29 -> 2841403.1 | AS29: =SUM(AG29:AR29) -> 50718878 | AT29: =Z29-AS29 -> 0 | AV29: =AG29 -> 54884.55 | AW29: =AV29+AH29 -> 55158.55 | AX29: =AW29+AI29 -> 1610587.1 | AY29: =AX29+AJ29 -> 5206837.1 | AZ29: =AY29+AK29 -> 5206837.1 | BA29: =AZ29+AL29 -> 7818444.2 | BB29: =BA29+AM29 -> 19332730 | BC29: =BB29+AN29 -> 23002596 | BD29: =BC29+AO29 -> 24715944 | ... BG29: =BF29+AR29 -> 50718878 | BH29: =BH28+1 -> 23
A30: 10001350 | B30: CAPITOL COMMONS IMPROVEMENTS | C30: ESTATES | D30: ESTATES | F30: Y | G30: Carry-over | R30: =Z30 -> 20168929 | Z30: =_xlfn.XLOOKUP(A30,'SAP Report'!A:A,'SAP Report'!C:C) -> 20168929 | AA30: =HLOOKUP($A$4,$AV$6:$BG30,(2+BH29),FALSE) -> 11986161 | AB30: =SUMIF('Open PR PO'!A:A,Monitoring!A30,'Open PR PO'!K:K) -> 3966040.4 | AC30: =AA30+AB30 -> 15952201 | AD30: =Z30-AC30 -> 4216727.5 | AE30: =Z30-AA30 -> 8182767.9 | AG30: =SUMIFS(Actual!$F:$F,Actual!$N:$N,Monitoring!AG$6,Actual!$A:$A,Monitoring!$A30) -> 4134285.7 | AH30: =SUMIFS(Actual!$F:$F,Actual!$N:$N,Monitoring!AH$6,Actual!$A:$A,Monitoring!$A30) -> 0 | AI30: =SUMIFS(Actual!$F:$F,Actual!$N:$N,Monitoring!AI$6,Actual!$A:$A,Monitoring!$A30) -> 6914375 | AJ30: =SUMIFS(Actual!$F:$F,Actual!$N:$N,Monitoring!AJ$6,Actual!$A:$A,Monitoring!$A30) -> 142857.14 | AK30: =SUMIFS(Actual!$F:$F,Actual!$N:$N,Monitoring!AK$6,Actual!$A:$A,Monitoring!$A30) -> 0 | AL30: =SUMIFS(Actual!$F:$F,Actual!$N:$N,Monitoring!AL$6,Actual!$A:$A,Monitoring!$A30) -> 80357.14 | AM30: =SUMIFS(Actual!$F:$F,Actual!$N:$N,Monitoring!AM$6,Actual!$A:$A,Monitoring!$A30) -> 714285.71 | AN30: =SUMIFS(Actual!$F:$F,Actual!$N:$N,Monitoring!AN$6,Actual!$A:$A,Monitoring!$A30) -> 0 | AO30: =SUMIFS(Actual!$F:$F,Actual!$N:$N,Monitoring!AO$6,Actual!$A:$A,Monitoring!$A30) -> 0 | AP30: =AB30 -> 3966040.4 | AQ30: =AD30/2 -> 2108363.7 | AR30: =AQ30 -> 2108363.7 | AS30: =SUM(AG30:AR30) -> 20168929 | AT30: =Z30-AS30 -> 0 | AV30: =AG30 -> 4134285.7 | AW30: =AV30+AH30 -> 4134285.7 | AX30: =AW30+AI30 -> 11048661 | AY30: =AX30+AJ30 -> 11191518 | AZ30: =AY30+AK30 -> 11191518 | BA30: =AZ30+AL30 -> 11271875 | BB30: =BA30+AM30 -> 11986161 | BC30: =BB30+AN30 -> 11986161 | BD30: =BC30+AO30 -> 11986161 | ... BG30: =BF30+AR30 -> 20168929 | BH30: =BH29+1 -> 24
A31: 10001220 | B31: GH ESTATES LIFT STATION | C31: ESTATES | D31: ESTATES | F31: Y | G31: Carry-over | R31: =Z31 -> 99196.43 | Z31: =_xlfn.XLOOKUP(A31,'SAP Report'!A:A,'SAP Report'!C:C) -> 99196.43 | AA31: =HLOOKUP($A$4,$AV$6:$BG31,(2+BH30),FALSE) -> 0 | AB31: =SUMIF('Open PR PO'!A:A,Monitoring!A31,'Open PR PO'!K:K) -> 99196.43 | AC31: =AA31+AB31 -> 99196.43 | AD31: =Z31-AC31 -> 0 | AE31: =Z31-AA31 -> 99196.43 | AG31: =SUMIFS(Actual!$F:$F,Actual!$N:$N,Monitoring!AG$6,Actual!$A:$A,Monitoring!$A31) -> 0 | AH31: =SUMIFS(Actual!$F:$F,Actual!$N:$N,Monitoring!AH$6,Actual!$A:$A,Monitoring!$A31) -> 0 | AI31: =SUMIFS(Actual!$F:$F,Actual!$N:$N,Monitoring!AI$6,Actual!$A:$A,Monitoring!$A31) -> 0 | AJ31: =SUMIFS(Actual!$F:$F,Actual!$N:$N,Monitoring!AJ$6,Actual!$A:$A,Monitoring!$A31) -> 0 | AK31: =SUMIFS(Actual!$F:$F,Actual!$N:$N,Monitoring!AK$6,Actual!$A:$A,Monitoring!$A31) -> 0 | AL31: =SUMIFS(Actual!$F:$F,Actual!$N:$N,Monitoring!AL$6,Actual!$A:$A,Monitoring!$A31) -> 0 | AM31: =SUMIFS(Actual!$F:$F,Actual!$N:$N,Monitoring!AM$6,Actual!$A:$A,Monitoring!$A31) -> 0 | AN31: =SUMIFS(Actual!$F:$F,Actual!$N:$N,Monitoring!AN$6,Actual!$A:$A,Monitoring!$A31) -> 0 | AO31: =SUMIFS(Actual!$F:$F,Actual!$N:$N,Monitoring!AO$6,Actual!$A:$A,Monitoring!$A31) -> 0 | AP31: =AB31 -> 99196.43 | AQ31: =AD31/2 -> 0 | AR31: =AQ31 -> 0 | AS31: =SUM(AG31:AR31) -> 99196.43 | AT31: =Z31-AS31 -> 0 | AV31: =AG31 -> 0 | AW31: =AV31+AH31 -> 0 | AX31: =AW31+AI31 -> 0 | AY31: =AX31+AJ31 -> 0 | AZ31: =AY31+AK31 -> 0 | BA31: =AZ31+AL31 -> 0 | BB31: =BA31+AM31 -> 0 | BC31: =BB31+AN31 -> 0 | BD31: =BC31+AO31 -> 0 | ... BG31: =BF31+AR31 -> 99196.43 | BH31: =BH30+1 -> 25
A32: 10000820 | B32: GH IMPROVEMENT OF VMALL PARK | C32: ESTATES | D32: ESTATES | F32: Y | G32: Carry-over | R32: =Z32 -> 278125 | Z32: =_xlfn.XLOOKUP(A32,'SAP Report'!A:A,'SAP Report'!C:C) -> 278125 | AA32: =HLOOKUP($A$4,$AV$6:$BG32,(2+BH31),FALSE) -> 0 | AB32: =SUMIF('Open PR PO'!A:A,Monitoring!A32,'Open PR PO'!K:K) -> 278125 | AC32: =AA32+AB32 -> 278125 | AD32: =Z32-AC32 -> 0 | AE32: =Z32-AA32 -> 278125 | AG32: =SUMIFS(Actual!$F:$F,Actual!$N:$N,Monitoring!AG$6,Actual!$A:$A,Monitoring!$A32) -> 0 | AH32: =SUMIFS(Actual!$F:$F,Actual!$N:$N,Monitoring!AH$6,Actual!$A:$A,Monitoring!$A32) -> 0 | AI32: =SUMIFS(Actual!$F:$F,Actual!$N:$N,Monitoring!AI$6,Actual!$A:$A,Monitoring!$A32) -> 0 | AJ32: =SUMIFS(Actual!$F:$F,Actual!$N:$N,Monitoring!AJ$6,Actual!$A:$A,Monitoring!$A32) -> 0 | AK32: =SUMIFS(Actual!$F:$F,Actual!$N:$N,Monitoring!AK$6,Actual!$A:$A,Monitoring!$A32) -> 0 | AL32: =SUMIFS(Actual!$F:$F,Actual!$N:$N,Monitoring!AL$6,Actual!$A:$A,Monitoring!$A32) -> 0 | AM32: =SUMIFS(Actual!$F:$F,Actual!$N:$N,Monitoring!AM$6,Actual!$A:$A,Monitoring!$A32) -> 0 | AN32: =SUMIFS(Actual!$F:$F,Actual!$N:$N,Monitoring!AN$6,Actual!$A:$A,Monitoring!$A32) -> 0 | AO32: =SUMIFS(Actual!$F:$F,Actual!$N:$N,Monitoring!AO$6,Actual!$A:$A,Monitoring!$A32) -> 0 | AP32: =AB32 -> 278125 | AQ32: =AD32/2 -> 0 | AR32: =AQ32 -> 0 | AS32: =SUM(AG32:AR32) -> 278125 | AT32: =Z32-AS32 -> 0 | AV32: =AG32 -> 0 | AW32: =AV32+AH32 -> 0 | AX32: =AW32+AI32 -> 0 | AY32: =AX32+AJ32 -> 0 | AZ32: =AY32+AK32 -> 0 | BA32: =AZ32+AL32 -> 0 | BB32: =BA32+AM32 -> 0 | BC32: =BB32+AN32 -> 0 | BD32: =BC32+AO32 -> 0 | ... BG32: =BF32+AR32 -> 278125 | BH32: =BH31+1 -> 26
A33: 10001021 | B33: GH PH1 STREETSCAPE PROJECT | C33: ESTATES | D33: ESTATES | F33: Y | G33: Carry-over | R33: =Z33 -> 4855625 | Z33: =_xlfn.XLOOKUP(A33,'SAP Report'!A:A,'SAP Report'!C:C) -> 4855625 | AA33: =HLOOKUP($A$4,$AV$6:$BG33,(2+BH32),FALSE) -> 0 | AB33: =SUMIF('Open PR PO'!A:A,Monitoring!A33,'Open PR PO'!K:K) -> 4855625 | AC33: =AA33+AB33 -> 4855625 | AD33: =Z33-AC33 -> 0 | AE33: =Z33-AA33 -> 4855625 | AG33: =SUMIFS(Actual!$F:$F,Actual!$N:$N,Monitoring!AG$6,Actual!$A:$A,Monitoring!$A33) -> 0 | AH33: =SUMIFS(Actual!$F:$F,Actual!$N:$N,Monitoring!AH$6,Actual!$A:$A,Monitoring!$A33) -> 0 | AI33: =SUMIFS(Actual!$F:$F,Actual!$N:$N,Monitoring!AI$6,Actual!$A:$A,Monitoring!$A33) -> 0 | AJ33: =SUMIFS(Actual!$F:$F,Actual!$N:$N,Monitoring!AJ$6,Actual!$A:$A,Monitoring!$A33) -> 0 | AK33: =SUMIFS(Actual!$F:$F,Actual!$N:$N,Monitoring!AK$6,Actual!$A:$A,Monitoring!$A33) -> 0 | AL33: =SUMIFS(Actual!$F:$F,Actual!$N:$N,Monitoring!AL$6,Actual!$A:$A,Monitoring!$A33) -> 0 | AM33: =SUMIFS(Actual!$F:$F,Actual!$N:$N,Monitoring!AM$6,Actual!$A:$A,Monitoring!$A33) -> 0 | AN33: =SUMIFS(Actual!$F:$F,Actual!$N:$N,Monitoring!AN$6,Actual!$A:$A,Monitoring!$A33) -> 0 | AO33: =SUMIFS(Actual!$F:$F,Actual!$N:$N,Monitoring!AO$6,Actual!$A:$A,Monitoring!$A33) -> 0 | AP33: =AB33 -> 4855625 | AQ33: =AD33/2 -> 0 | AR33: =AQ33 -> 0 | AS33: =SUM(AG33:AR33) -> 4855625 | AT33: =Z33-AS33 -> 0 | AV33: =AG33 -> 0 | AW33: =AV33+AH33 -> 0 | AX33: =AW33+AI33 -> 0 | AY33: =AX33+AJ33 -> 0 | AZ33: =AY33+AK33 -> 0 | BA33: =AZ33+AL33 -> 0 | BB33: =BA33+AM33 -> 0 | BC33: =BB33+AN33 -> 0 | BD33: =BC33+AO33 -> 0 | ... BG33: =BF33+AR33 -> 4855625 | BH33: =BH32+1 -> 27
... A38: 10001311 | B38: SC2&3 WATER PROOFING OF ROOF | C38: OFFICES | D38: OFFICES | F38: N | G38: Carry-over | R38: =Z38 -> 3660714.3 | Z38: =_xlfn.XLOOKUP(A38,'SAP Report'!A:A,'SAP Report'!C:C) -> 3660714.3 | AA38: =HLOOKUP($A$4,$AV$6:$BG38,(2+BH37),FALSE) -> 3161591.1 | AB38: =SUMIF('Open PR PO'!A:A,Monitoring!A38,'Open PR PO'!K:K) -> 499123.19 | AC38: =AA38+AB38 -> 3660714.3 | AD38: =Z38-AC38 -> 0 | AE38: =Z38-AA38 -> 499123.19 | AG38: =SUMIFS(Actual!$F:$F,Actual!$N:$N,Monitoring!AG$6,Actual!$A:$A,Monitoring!$A38) -> 0 | AH38: =SUMIFS(Actual!$F:$F,Actual!$N:$N,Monitoring!AH$6,Actual!$A:$A,Monitoring!$A38) -> 0 | AI38: =SUMIFS(Actual!$F:$F,Actual!$N:$N,Monitoring!AI$6,Actual!$A:$A,Monitoring!$A38) -> 3161591.1 | AJ38: =SUMIFS(Actual!$F:$F,Actual!$N:$N,Monitoring!AJ$6,Actual!$A:$A,Monitoring!$A38) -> 0 | AK38: =SUMIFS(Actual!$F:$F,Actual!$N:$N,Monitoring!AK$6,Actual!$A:$A,Monitoring!$A38) -> 0 | AL38: =SUMIFS(Actual!$F:$F,Actual!$N:$N,Monitoring!AL$6,Actual!$A:$A,Monitoring!$A38) -> 0 | AM38: =SUMIFS(Actual!$F:$F,Actual!$N:$N,Monitoring!AM$6,Actual!$A:$A,Monitoring!$A38) -> 0 | AN38: =SUMIFS(Actual!$F:$F,Actual!$N:$N,Monitoring!AN$6,Actual!$A:$A,Monitoring!$A38) -> 0 | AO38: =SUMIFS(Actual!$F:$F,Actual!$N:$N,Monitoring!AO$6,Actual!$A:$A,Monitoring!$A38) -> 0 | AP38: =AB38 -> 499123.19 | AQ38: =AD38/2 -> 0 | AR38: =AQ38 -> 0 | AS38: =SUM(AG38:AR38) -> 3660714.3 | AT38: =Z38-AS38 -> 0 | AV38: =AG38 -> 0 | AW38: =AV38+AH38 -> 0 | AX38: =AW38+AI38 -> 3161591.1 | AY38: =AX38+AJ38 -> 3161591.1 | AZ38: =AY38+AK38 -> 3161591.1 | BA38: =AZ38+AL38 -> 3161591.1 | BB38: =BA38+AM38 -> 3161591.1 | BC38: =BB38+AN38 -> 3161591.1 | BD38: =BC38+AO38 -> 3161591.1 | ... BG38: =BF38+AR38 -> 3660714.3 | BH38: =BH37+1 -> 32
A39: 10001314 | B39: GH TOWER BIR FIT-OUT | C39: OFFICES | D39: OFFICES | F39: Y | G39: Carry-over | R39: =Z39-1397102.59 -> 8820595.1 | X39: 0300011427 | Z39: =_xlfn.XLOOKUP(A39,'SAP Report'!A:A,'SAP Report'!C:C) -> 10217698 | AA39: =HLOOKUP($A$4,$AV$6:$BG39,(2+BH38),FALSE) -> 8096919.1 | AB39: =SUMIF('Open PR PO'!A:A,Monitoring!A39,'Open PR PO'!K:K) -> 1429857.2 | AC39: =AA39+AB39 -> 9526776.2 | AD39: =Z39-AC39 -> 690921.41 | AE39: =Z39-AA39 -> 2120778.6 | AG39: =SUMIFS(Actual!$F:$F,Actual!$N:$N,Monitoring!AG$6,Actual!$A:$A,Monitoring!$A39) -> 136104.46 | AH39: =SUMIFS(Actual!$F:$F,Actual!$N:$N,Monitoring!AH$6,Actual!$A:$A,Monitoring!$A39) -> 3091517.7 | AI39: =SUMIFS(Actual!$F:$F,Actual!$N:$N,Monitoring!AI$6,Actual!$A:$A,Monitoring!$A39) -> 1251288.2 | AJ39: =SUMIFS(Actual!$F:$F,Actual!$N:$N,Monitoring!AJ$6,Actual!$A:$A,Monitoring!$A39) -> 3505591.4 | AK39: =SUMIFS(Actual!$F:$F,Actual!$N:$N,Monitoring!AK$6,Actual!$A:$A,Monitoring!$A39) -> 0 | AL39: =SUMIFS(Actual!$F:$F,Actual!$N:$N,Monitoring!AL$6,Actual!$A:$A,Monitoring!$A39) -> 0 | AM39: =SUMIFS(Actual!$F:$F,Actual!$N:$N,Monitoring!AM$6,Actual!$A:$A,Monitoring!$A39) -> 53571.43 | AN39: =SUMIFS(Actual!$F:$F,Actual!$N:$N,Monitoring!AN$6,Actual!$A:$A,Monitoring!$A39) -> 58845.94 | AO39: =SUMIFS(Actual!$F:$F,Actual!$N:$N,Monitoring!AO$6,Actual!$A:$A,Monitoring!$A39) -> 0 | AP39: =AB39 -> 1429857.2 | AQ39: =AD39/2 -> 345460.71 | AR39: =AQ39 -> 345460.71 | AS39: =SUM(AG39:AR39) -> 10217698 | AT39: =Z39-AS39 -> 0 | AV39: =AG39 -> 136104.46 | AW39: =AV39+AH39 -> 3227622.1 | AX39: =AW39+AI39 -> 4478910.3 | AY39: =AX39+AJ39 -> 7984501.7 | AZ39: =AY39+AK39 -> 7984501.7 | BA39: =AZ39+AL39 -> 7984501.7 | BB39: =BA39+AM39 -> 8038073.2 | BC39: =BB39+AN39 -> 8096919.1 | BD39: =BC39+AO39 -> 8096919.1 | ... BG39: =BF39+AR39 -> 10217698 | BH39: =BH38+1 -> 33
A40: 10001340 | B40: IBP ACP REPLACEMENT & PUMP R | C40: OFFICES | D40: OFFICES | F40: N | G40: Carry-over | R40: =Z40 -> 285714.29 | Z40: =_xlfn.XLOOKUP(A40,'SAP Report'!A:A,'SAP Report'!C:C) -> 285714.29 | AA40: =HLOOKUP($A$4,$AV$6:$BG40,(2+BH39),FALSE) -> 285714.29 | AB40: =SUMIF('Open PR PO'!A:A,Monitoring!A40,'Open PR PO'!K:K) -> 0 | AC40: =AA40+AB40 -> 285714.29 | AD40: =Z40-AC40 -> 0 | AE40: =Z40-AA40 -> 0 | AG40: =SUMIFS(Actual!$F:$F,Actual!$N:$N,Monitoring!AG$6,Actual!$A:$A,Monitoring!$A40) -> 0 | AH40: =SUMIFS(Actual!$F:$F,Actual!$N:$N,Monitoring!AH$6,Actual!$A:$A,Monitoring!$A40) -> 0 | AI40: =SUMIFS(Actual!$F:$F,Actual!$N:$N,Monitoring!AI$6,Actual!$A:$A,Monitoring!$A40) -> 285714.29 | AJ40: =SUMIFS(Actual!$F:$F,Actual!$N:$N,Monitoring!AJ$6,Actual!$A:$A,Monitoring!$A40) -> 0 | AK40: =SUMIFS(Actual!$F:$F,Actual!$N:$N,Monitoring!AK$6,Actual!$A:$A,Monitoring!$A40) -> 0 | AL40: =SUMIFS(Actual!$F:$F,Actual!$N:$N,Monitoring!AL$6,Actual!$A:$A,Monitoring!$A40) -> 0 | AM40: =SUMIFS(Actual!$F:$F,Actual!$N:$N,Monitoring!AM$6,Actual!$A:$A,Monitoring!$A40) -> 0 | AN40: =SUMIFS(Actual!$F:$F,Actual!$N:$N,Monitoring!AN$6,Actual!$A:$A,Monitoring!$A40) -> 0 | AO40: =SUMIFS(Actual!$F:$F,Actual!$N:$N,Monitoring!AO$6,Actual!$A:$A,Monitoring!$A40) -> 0 | AP40: =AB40 -> 0 | AQ40: =AD40/2 -> 0 | AR40: =AQ40 -> 0 | AS40: =SUM(AG40:AR40) -> 285714.29 | AT40: =Z40-AS40 -> 0 | AV40: =AG40 -> 0 | AW40: =AV40+AH40 -> 0 | AX40: =AW40+AI40 -> 285714.29 | AY40: =AX40+AJ40 -> 285714.29 | AZ40: =AY40+AK40 -> 285714.29 | BA40: =AZ40+AL40 -> 285714.29 | BB40: =BA40+AM40 -> 285714.29 | BC40: =BB40+AN40 -> 285714.29 | BD40: =BC40+AO40 -> 285714.29 | ... BG40: =BF40+AR40 -> 285714.29 | BH40: =BH39+1 -> 34
A41: 10001360 | B41: ESWW WATERPROOFING | C41: OFFICES | D41: OFFICES | F41: N | G41: Carry-over | R41: =Z41 -> 2437500 | Z41: =_xlfn.XLOOKUP(A41,'SAP Report'!A:A,'SAP Report'!C:C) -> 2437500 | AA41: =HLOOKUP($A$4,$AV$6:$BG41,(2+BH40),FALSE) -> 2437500 | AB41: =SUMIF('Open PR PO'!A:A,Monitoring!A41,'Open PR PO'!K:K) -> 0 | AC41: =AA41+AB41 -> 2437500 | AD41: =Z41-AC41 -> 0 | AE41: =Z41-AA41 -> 0 | AG41: =SUMIFS(Actual!$F:$F,Actual!$N:$N,Monitoring!AG$6,Actual!$A:$A,Monitoring!$A41) -> 0 | AH41: =SUMIFS(Actual!$F:$F,Actual!$N:$N,Monitoring!AH$6,Actual!$A:$A,Monitoring!$A41) -> 0 | AI41: =SUMIFS(Actual!$F:$F,Actual!$N:$N,Monitoring!AI$6,Actual!$A:$A,Monitoring!$A41) -> 2437500 | AJ41: =SUMIFS(Actual!$F:$F,Actual!$N:$N,Monitoring!AJ$6,Actual!$A:$A,Monitoring!$A41) -> 0 | AK41: =SUMIFS(Actual!$F:$F,Actual!$N:$N,Monitoring!AK$6,Actual!$A:$A,Monitoring!$A41) -> 0 | AL41: =SUMIFS(Actual!$F:$F,Actual!$N:$N,Monitoring!AL$6,Actual!$A:$A,Monitoring!$A41) -> 0 | AM41: =SUMIFS(Actual!$F:$F,Actual!$N:$N,Monitoring!AM$6,Actual!$A:$A,Monitoring!$A41) -> 0 | AN41: =SUMIFS(Actual!$F:$F,Actual!$N:$N,Monitoring!AN$6,Actual!$A:$A,Monitoring!$A41) -> 0 | AO41: =SUMIFS(Actual!$F:$F,Actual!$N:$N,Monitoring!AO$6,Actual!$A:$A,Monitoring!$A41) -> 0 | AP41: =AB41 -> 0 | AQ41: =AD41/2 -> 0 | AR41: =AQ41 -> 0 | AS41: =SUM(AG41:AR41) -> 2437500 | AT41: =Z41-AS41 -> 0 | AV41: =AG41 -> 0 | AW41: =AV41+AH41 -> 0 | AX41: =AW41+AI41 -> 2437500 | AY41: =AX41+AJ41 -> 2437500 | AZ41: =AY41+AK41 -> 2437500 | BA41: =AZ41+AL41 -> 2437500 | BB41: =BA41+AM41 -> 2437500 | BC41: =BB41+AN41 -> 2437500 | BD41: =BC41+AO41 -> 2437500 | ... BG41: =BF41+AR41 -> 2437500 | BH41: =BH40+1 -> 35
A42: 10001361 | B42: SC2&3 REHAB OF VRF | C42: OFFICES | D42: OFFICES | F42: N | G42: Carry-over | R42: =Z42 -> 2901785.7 | Z42: =_xlfn.XLOOKUP(A42,'SAP Report'!A:A,'SAP Report'!C:C) -> 2901785.7 | AA42: =HLOOKUP($A$4,$AV$6:$BG42,(2+BH41),FALSE) -> 2901785.7 | AB42: =SUMIF('Open PR PO'!A:A,Monitoring!A42,'Open PR PO'!K:K) -> 0 | AC42: =AA42+AB42 -> 2901785.7 | AD42: =Z42-AC42 -> 0 | AE42: =Z42-AA42 -> 0 | AG42: =SUMIFS(Actual!$F:$F,Actual!$N:$N,Monitoring!AG$6,Actual!$A:$A,Monitoring!$A42) -> 0 | AH42: =SUMIFS(Actual!$F:$F,Actual!$N:$N,Monitoring!AH$6,Actual!$A:$A,Monitoring!$A42) -> 2089285.7 | AI42: =SUMIFS(Actual!$F:$F,Actual!$N:$N,Monitoring!AI$6,Actual!$A:$A,Monitoring!$A42) -> 0 | AJ42: =SUMIFS(Actual!$F:$F,Actual!$N:$N,Monitoring!AJ$6,Actual!$A:$A,Monitoring!$A42) -> 812500 | AK42: =SUMIFS(Actual!$F:$F,Actual!$N:$N,Monitoring!AK$6,Actual!$A:$A,Monitoring!$A42) -> 0 | AL42: =SUMIFS(Actual!$F:$F,Actual!$N:$N,Monitoring!AL$6,Actual!$A:$A,Monitoring!$A42) -> 0 | AM42: =SUMIFS(Actual!$F:$F,Actual!$N:$N,Monitoring!AM$6,Actual!$A:$A,Monitoring!$A42) -> 0 | AN42: =SUMIFS(Actual!$F:$F,Actual!$N:$N,Monitoring!AN$6,Actual!$A:$A,Monitoring!$A42) -> 0 | AO42: =SUMIFS(Actual!$F:$F,Actual!$N:$N,Monitoring!AO$6,Actual!$A:$A,Monitoring!$A42) -> 0 | AP42: =AB42 -> 0 | AQ42: =AD42/2 -> 0 | AR42: =AQ42 -> 0 | AS42: =SUM(AG42:AR42) -> 2901785.7 | AT42: =Z42-AS42 -> 0 | AV42: =AG42 -> 0 | AW42: =AV42+AH42 -> 2089285.7 | AX42: =AW42+AI42 -> 2089285.7 | AY42: =AX42+AJ42 -> 2901785.7 | AZ42: =AY42+AK42 -> 2901785.7 | BA42: =AZ42+AL42 -> 2901785.7 | BB42: =BA42+AM42 -> 2901785.7 | BC42: =BB42+AN42 -> 2901785.7 | BD42: =BC42+AO42 -> 2901785.7 | ... BG42: =BF42+AR42 -> 2901785.7 | BH42: =BH41+1 -> 36
A43: 10001363 | B43: SC5 ISOLATION VALVES REPLACE | C43: OFFICES | D43: OFFICES | F43: N | G43: Carry-over | R43: =Z43 -> 714285.71 | Z43: =_xlfn.XLOOKUP(A43,'SAP Report'!A:A,'SAP Report'!C:C) -> 714285.71 | AA43: =HLOOKUP($A$4,$AV$6:$BG43,(2+BH42),FALSE) -> 714285.71 | AB43: =SUMIF('Open PR PO'!A:A,Monitoring!A43,'Open PR PO'!K:K) -> 0 | AC43: =AA43+AB43 -> 714285.71 | AD43: =Z43-AC43 -> 0 | AE43: =Z43-AA43 -> 0 | AG43: =SUMIFS(Actual!$F:$F,Actual!$N:$N,Monitoring!AG$6,Actual!$A:$A,Monitoring!$A43) -> 0 | AH43: =SUMIFS(Actual!$F:$F,Actual!$N:$N,Monitoring!AH$6,Actual!$A:$A,Monitoring!$A43) -> 0 | AI43: =SUMIFS(Actual!$F:$F,Actual!$N:$N,Monitoring!AI$6,Actual!$A:$A,Monitoring!$A43) -> 0 | AJ43: =SUMIFS(Actual!$F:$F,Actual!$N:$N,Monitoring!AJ$6,Actual!$A:$A,Monitoring!$A43) -> 714285.71 | AK43: =SUMIFS(Actual!$F:$F,Actual!$N:$N,Monitoring!AK$6,Actual!$A:$A,Monitoring!$A43) -> 0 | AL43: =SUMIFS(Actual!$F:$F,Actual!$N:$N,Monitoring!AL$6,Actual!$A:$A,Monitoring!$A43) -> 0 | AM43: =SUMIFS(Actual!$F:$F,Actual!$N:$N,Monitoring!AM$6,Actual!$A:$A,Monitoring!$A43) -> 0 | AN43: =SUMIFS(Actual!$F:$F,Actual!$N:$N,Monitoring!AN$6,Actual!$A:$A,Monitoring!$A43) -> 0 | AO43: =SUMIFS(Actual!$F:$F,Actual!$N:$N,Monitoring!AO$6,Actual!$A:$A,Monitoring!$A43) -> 0 | AP43: =AB43 -> 0 | AQ43: =AD43/2 -> 0 | AR43: =AQ43 -> 0 | AS43: =SUM(AG43:AR43) -> 714285.71 | AT43: =Z43-AS43 -> 0 | AV43: =AG43 -> 0 | AW43: =AV43+AH43 -> 0 | AX43: =AW43+AI43 -> 0 | AY43: =AX43+AJ43 -> 714285.71 | AZ43: =AY43+AK43 -> 714285.71 | BA43: =AZ43+AL43 -> 714285.71 | BB43: =BA43+AM43 -> 714285.71 | BC43: =BB43+AN43 -> 714285.71 | BD43: =BC43+AO43 -> 714285.71 | ... BG43: =BF43+AR43 -> 714285.71 | BH43: =BH42+1 -> 37
A44: 10001381 | B44: SC3 REHABILITATION OF TURNST | C44: OFFICES | D44: OFFICES | F44: N | G44: Carry-over | R44: =Z44 -> 968800 | Z44: =_xlfn.XLOOKUP(A44,'SAP Report'!A:A,'SAP Report'!C:C) -> 968800 | AA44: =HLOOKUP($A$4,$AV$6:$BG44,(2+BH43),FALSE) -> 625000 | AB44: =SUMIF('Open PR PO'!A:A,Monitoring!A44,'Open PR PO'!K:K) -> 0 | AC44: =AA44+AB44 -> 625000 | AD44: =Z44-AC44 -> 343800 | AE44: =Z44-AA44 -> 343800 | AG44: =SUMIFS(Actual!$F:$F,Actual!$N:$N,Monitoring!AG$6,Actual!$A:$A,Monitoring!$A44) -> 0 | AH44: =SUMIFS(Actual!$F:$F,Actual!$N:$N,Monitoring!AH$6,Actual!$A:$A,Monitoring!$A44) -> 0 | AI44: =SUMIFS(Actual!$F:$F,Actual!$N:$N,Monitoring!AI$6,Actual!$A:$A,Monitoring!$A44) -> 0 | AJ44: =SUMIFS(Actual!$F:$F,Actual!$N:$N,Monitoring!AJ$6,Actual!$A:$A,Monitoring!$A44) -> 625000 | AK44: =SUMIFS(Actual!$F:$F,Actual!$N:$N,Monitoring!AK$6,Actual!$A:$A,Monitoring!$A44) -> 0 | AL44: =SUMIFS(Actual!$F:$F,Actual!$N:$N,Monitoring!AL$6,Actual!$A:$A,Monitoring!$A44) -> 0 | AM44: =SUMIFS(Actual!$F:$F,Actual!$N:$N,Monitoring!AM$6,Actual!$A:$A,Monitoring!$A44) -> 0 | AN44: =SUMIFS(Actual!$F:$F,Actual!$N:$N,Monitoring!AN$6,Actual!$A:$A,Monitoring!$A44) -> 0 | AO44: =SUMIFS(Actual!$F:$F,Actual!$N:$N,Monitoring!AO$6,Actual!$A:$A,Monitoring!$A44) -> 0 | AP44: =AB44 -> 0 | AQ44: =AD44/2 -> 171900 | AR44: =AQ44 -> 171900 | AS44: =SUM(AG44:AR44) -> 968800 | AT44: =Z44-AS44 -> 0 | AV44: =AG44 -> 0 | AW44: =AV44+AH44 -> 0 | AX44: =AW44+AI44 -> 0 | AY44: =AX44+AJ44 -> 625000 | AZ44: =AY44+AK44 -> 625000 | BA44: =AZ44+AL44 -> 625000 | BB44: =BA44+AM44 -> 625000 | BC44: =BB44+AN44 -> 625000 | BD44: =BC44+AO44 -> 625000 | ... BG44: =BF44+AR44 -> 968800 | BH44: =BH43+1 -> 38
A45: 40001062 | B45: SAP PRD ENHANCEMENT | C45: CORPORATE | D45: Corporate - IT | F45: N | G45: Carry-over | R45: =Z45 -> 250000 | Z45: =_xlfn.XLOOKUP(A45,'SAP Report'!A:A,'SAP Report'!C:C) -> 250000 | AA45: =HLOOKUP($A$4,$AV$6:$BG45,(2+BH44),FALSE) -> 250000 | AB45: =SUMIF('Open PR PO'!A:A,Monitoring!A45,'Open PR PO'!K:K) -> 0 | AC45: =AA45+AB45 -> 250000 | AD45: =Z45-AC45 -> 0 | AE45: =Z45-AA45 -> 0 | AG45: =SUMIFS(Actual!$F:$F,Actual!$N:$N,Monitoring!AG$6,Actual!$A:$A,Monitoring!$A45) -> 250000 | AH45: =SUMIFS(Actual!$F:$F,Actual!$N:$N,Monitoring!AH$6,Actual!$A:$A,Monitoring!$A45) -> 0 | AI45: =SUMIFS(Actual!$F:$F,Actual!$N:$N,Monitoring!AI$6,Actual!$A:$A,Monitoring!$A45) -> 0 | AJ45: =SUMIFS(Actual!$F:$F,Actual!$N:$N,Monitoring!AJ$6,Actual!$A:$A,Monitoring!$A45) -> 0 | AK45: =SUMIFS(Actual!$F:$F,Actual!$N:$N,Monitoring!AK$6,Actual!$A:$A,Monitoring!$A45) -> 0 | AL45: =SUMIFS(Actual!$F:$F,Actual!$N:$N,Monitoring!AL$6,Actual!$A:$A,Monitoring!$A45) -> 0 | AM45: =SUMIFS(Actual!$F:$F,Actual!$N:$N,Monitoring!AM$6,Actual!$A:$A,Monitoring!$A45) -> 0 | AN45: =SUMIFS(Actual!$F:$F,Actual!$N:$N,Monitoring!AN$6,Actual!$A:$A,Monitoring!$A45) -> 0 | AO45: =SUMIFS(Actual!$F:$F,Actual!$N:$N,Monitoring!AO$6,Actual!$A:$A,Monitoring!$A45) -> 0 | AP45: =AB45 -> 0 | AQ45: =AD45/2 -> 0 | AR45: =AQ45 -> 0 | AS45: =SUM(AG45:AR45) -> 250000 | AT45: =Z45-AS45 -> 0 | AV45: =AG45 -> 250000 | AW45: =AV45+AH45 -> 250000 | AX45: =AW45+AI45 -> 250000 | AY45: =AX45+AJ45 -> 250000 | AZ45: =AY45+AK45 -> 250000 | BA45: =AZ45+AL45 -> 250000 | BB45: =BA45+AM45 -> 250000 | BC45: =BB45+AN45 -> 250000 | BD45: =BC45+AO45 -> 250000 | ... BG45: =BF45+AR45 -> 250000 | BH45: =BH44+1 -> 39
A46: 40001209 | B46: SAP PRD ENHANCEMENT - EOPT | C46: CORPORATE | D46: Corporate - IT | F46: N | G46: Carry-over | R46: =Z46 -> 459375 | Z46: =_xlfn.XLOOKUP(A46,'SAP Report'!A:A,'SAP Report'!C:C) -> 459375 | AA46: =HLOOKUP($A$4,$AV$6:$BG46,(2+BH45),FALSE) -> 100000 | AB46: =SUMIF('Open PR PO'!A:A,Monitoring!A46,'Open PR PO'!K:K) -> 0 | AC46: =AA46+AB46 -> 100000 | AD46: =Z46-AC46 -> 359375 | AE46: =Z46-AA46 -> 359375 | AG46: =SUMIFS(Actual!$F:$F,Actual!$N:$N,Monitoring!AG$6,Actual!$A:$A,Monitoring!$A46) -> 100000 | AH46: =SUMIFS(Actual!$F:$F,Actual!$N:$N,Monitoring!AH$6,Actual!$A:$A,Monitoring!$A46) -> 0 | AI46: =SUMIFS(Actual!$F:$F,Actual!$N:$N,Monitoring!AI$6,Actual!$A:$A,Monitoring!$A46) -> 0 | AJ46: =SUMIFS(Actual!$F:$F,Actual!$N:$N,Monitoring!AJ$6,Actual!$A:$A,Monitoring!$A46) -> 0 | AK46: =SUMIFS(Actual!$F:$F,Actual!$N:$N,Monitoring!AK$6,Actual!$A:$A,Monitoring!$A46) -> 0 | AL46: =SUMIFS(Actual!$F:$F,Actual!$N:$N,Monitoring!AL$6,Actual!$A:$A,Monitoring!$A46) -> 0 | AM46: =SUMIFS(Actual!$F:$F,Actual!$N:$N,Monitoring!AM$6,Actual!$A:$A,Monitoring!$A46) -> 0 | AN46: =SUMIFS(Actual!$F:$F,Actual!$N:$N,Monitoring!AN$6,Actual!$A:$A,Monitoring!$A46) -> 0 | AO46: =SUMIFS(Actual!$F:$F,Actual!$N:$N,Monitoring!AO$6,Actual!$A:$A,Monitoring!$A46) -> 0 | AP46: =AB46 -> 0 | AQ46: =AD46/2 -> 179687.5 | AR46: =AQ46 -> 179687.5 | AS46: =SUM(AG46:AR46) -> 459375 | AT46: =Z46-AS46 -> 0 | AV46: =AG46 -> 100000 | AW46: =AV46+AH46 -> 100000 | AX46: =AW46+AI46 -> 100000 | AY46: =AX46+AJ46 -> 100000 | AZ46: =AY46+AK46 -> 100000 | BA46: =AZ46+AL46 -> 100000 | BB46: =BA46+AM46 -> 100000 | BC46: =BB46+AN46 -> 100000 | BD46: =BC46+AO46 -> 100000 | ... BG46: =BF46+AR46 -> 459375 | BH46: =BH45+1 -> 40
A47: 40001210 | B47: SAP PRD ENHANCEMENT - EOPT - | C47: CORPORATE | D47: Corporate - IT | F47: N | G47: Carry-over | R47: =Z47 -> 253125 | Z47: =_xlfn.XLOOKUP(A47,'SAP Report'!A:A,'SAP Report'!C:C) -> 253125 | AA47: =HLOOKUP($A$4,$AV$6:$BG47,(2+BH46),FALSE) -> 0 | AB47: =SUMIF('Open PR PO'!A:A,Monitoring!A47,'Open PR PO'!K:K) -> 0 | AC47: =AA47+AB47 -> 0 | AD47: =Z47-AC47 -> 253125 | AE47: =Z47-AA47 -> 253125 | AG47: =SUMIFS(Actual!$F:$F,Actual!$N:$N,Monitoring!AG$6,Actual!$A:$A,Monitoring!$A47) -> 0 | AH47: =SUMIFS(Actual!$F:$F,Actual!$N:$N,Monitoring!AH$6,Actual!$A:$A,Monitoring!$A47) -> 0 | AI47: =SUMIFS(Actual!$F:$F,Actual!$N:$N,Monitoring!AI$6,Actual!$A:$A,Monitoring!$A47) -> 0 | AJ47: =SUMIFS(Actual!$F:$F,Actual!$N:$N,Monitoring!AJ$6,Actual!$A:$A,Monitoring!$A47) -> 0 | AK47: =SUMIFS(Actual!$F:$F,Actual!$N:$N,Monitoring!AK$6,Actual!$A:$A,Monitoring!$A47) -> 0 | AL47: =SUMIFS(Actual!$F:$F,Actual!$N:$N,Monitoring!AL$6,Actual!$A:$A,Monitoring!$A47) -> 0 | AM47: =SUMIFS(Actual!$F:$F,Actual!$N:$N,Monitoring!AM$6,Actual!$A:$A,Monitoring!$A47) -> 0 | AN47: =SUMIFS(Actual!$F:$F,Actual!$N:$N,Monitoring!AN$6,Actual!$A:$A,Monitoring!$A47) -> 0 | AO47: =SUMIFS(Actual!$F:$F,Actual!$N:$N,Monitoring!AO$6,Actual!$A:$A,Monitoring!$A47) -> 0 | AP47: =AB47 -> 0 | AQ47: =AD47/2 -> 126562.5 | AR47: =AQ47 -> 126562.5 | AS47: =SUM(AG47:AR47) -> 253125 | AT47: =Z47-AS47 -> 0 | AV47: =AG47 -> 0 | AW47: =AV47+AH47 -> 0 | AX47: =AW47+AI47 -> 0 | AY47: =AX47+AJ47 -> 0 | AZ47: =AY47+AK47 -> 0 | BA47: =AZ47+AL47 -> 0 | BB47: =BA47+AM47 -> 0 | BC47: =BB47+AN47 -> 0 | BD47: =BC47+AO47 -> 0 | ... BG47: =BF47+AR47 -> 253125 | BH47: =BH46+1 -> 41
A48: 40001232 | B48: SAP PRD ENHANCEMENT - EOPT | C48: CORPORATE | D48: Corporate - IT | F48: N | G48: Carry-over | R48: =Z48 -> 937500 | Z48: =_xlfn.XLOOKUP(A48,'SAP Report'!A:A,'SAP Report'!C:C) -> 937500 | AA48: =HLOOKUP($A$4,$AV$6:$BG48,(2+BH47),FALSE) -> 0 | AB48: =SUMIF('Open PR PO'!A:A,Monitoring!A48,'Open PR PO'!K:K) -> 937500 | AC48: =AA48+AB48 -> 937500 | AD48: =Z48-AC48 -> 0 | AE48: =Z48-AA48 -> 937500 | AG48: =SUMIFS(Actual!$F:$F,Actual!$N:$N,Monitoring!AG$6,Actual!$A:$A,Monitoring!$A48) -> 0 | AH48: =SUMIFS(Actual!$F:$F,Actual!$N:$N,Monitoring!AH$6,Actual!$A:$A,Monitoring!$A48) -> 0 | AI48: =SUMIFS(Actual!$F:$F,Actual!$N:$N,Monitoring!AI$6,Actual!$A:$A,Monitoring!$A48) -> 0 | AJ48: =SUMIFS(Actual!$F:$F,Actual!$N:$N,Monitoring!AJ$6,Actual!$A:$A,Monitoring!$A48) -> 0 | AK48: =SUMIFS(Actual!$F:$F,Actual!$N:$N,Monitoring!AK$6,Actual!$A:$A,Monitoring!$A48) -> 0 | AL48: =SUMIFS(Actual!$F:$F,Actual!$N:$N,Monitoring!AL$6,Actual!$A:$A,Monitoring!$A48) -> 0 | AM48: =SUMIFS(Actual!$F:$F,Actual!$N:$N,Monitoring!AM$6,Actual!$A:$A,Monitoring!$A48) -> 0 | AN48: =SUMIFS(Actual!$F:$F,Actual!$N:$N,Monitoring!AN$6,Actual!$A:$A,Monitoring!$A48) -> 0 | AO48: =SUMIFS(Actual!$F:$F,Actual!$N:$N,Monitoring!AO$6,Actual!$A:$A,Monitoring!$A48) -> 0 | AP48: =AB48 -> 937500 | AQ48: =AD48/2 -> 0 | AR48: =AQ48 -> 0 | AS48: =SUM(AG48:AR48) -> 937500 | AT48: =Z48-AS48 -> 0 | AV48: =AG48 -> 0 | AW48: =AV48+AH48 -> 0 | AX48: =AW48+AI48 -> 0 | AY48: =AX48+AJ48 -> 0 | AZ48: =AY48+AK48 -> 0 | BA48: =AZ48+AL48 -> 0 | BB48: =BA48+AM48 -> 0 | BC48: =BB48+AN48 -> 0 | BD48: =BC48+AO48 -> 0 | ... BG48: =BF48+AR48 -> 937500 | BH48: =BH47+1 -> 42
A49: 40000863 | B49: SELLER’S & BUYER'S PORTAL | C49: RESIDENTIAL | D49: RESIDENTIAL | F49: N | G49: Carry-over | R49: =Z49 -> 2112000 | Z49: =_xlfn.XLOOKUP(A49,'SAP Report'!A:A,'SAP Report'!C:C) -> 2112000 | AA49: =HLOOKUP($A$4,$AV$6:$BG49,(2+BH48),FALSE) -> 0 | AB49: =SUMIF('Open PR PO'!A:A,Monitoring!A49,'Open PR PO'!K:K) -> 2112000 | AC49: =AA49+AB49 -> 2112000 | AD49: =Z49-AC49 -> 0 | AE49: =Z49-AA49 -> 2112000 | AG49: =SUMIFS(Actual!$F:$F,Actual!$N:$N,Monitoring!AG$6,Actual!$A:$A,Monitoring!$A49) -> 0 | AH49: =SUMIFS(Actual!$F:$F,Actual!$N:$N,Monitoring!AH$6,Actual!$A:$A,Monitoring!$A49) -> 0 | AI49: =SUMIFS(Actual!$F:$F,Actual!$N:$N,Monitoring!AI$6,Actual!$A:$A,Monitoring!$A49) -> 0 | AJ49: =SUMIFS(Actual!$F:$F,Actual!$N:$N,Monitoring!AJ$6,Actual!$A:$A,Monitoring!$A49) -> 0 | AK49: =SUMIFS(Actual!$F:$F,Actual!$N:$N,Monitoring!AK$6,Actual!$A:$A,Monitoring!$A49) -> 0 | AL49: =SUMIFS(Actual!$F:$F,Actual!$N:$N,Monitoring!AL$6,Actual!$A:$A,Monitoring!$A49) -> 0 | AM49: =SUMIFS(Actual!$F:$F,Actual!$N:$N,Monitoring!AM$6,Actual!$A:$A,Monitoring!$A49) -> 0 | AN49: =SUMIFS(Actual!$F:$F,Actual!$N:$N,Monitoring!AN$6,Actual!$A:$A,Monitoring!$A49) -> 0 | AO49: =SUMIFS(Actual!$F:$F,Actual!$N:$N,Monitoring!AO$6,Actual!$A:$A,Monitoring!$A49) -> 0 | AP49: =AB49 -> 2112000 | AQ49: =AD49/2 -> 0 | AR49: =AQ49 -> 0 | AS49: =SUM(AG49:AR49) -> 2112000 | AT49: =Z49-AS49 -> 0 | AV49: =AG49 -> 0 | AW49: =AV49+AH49 -> 0 | AX49: =AW49+AI49 -> 0 | AY49: =AX49+AJ49 -> 0 | AZ49: =AY49+AK49 -> 0 | BA49: =AZ49+AL49 -> 0 | BB49: =BA49+AM49 -> 0 | BC49: =BB49+AN49 -> 0 | BD49: =BC49+AO49 -> 0 | ... BG49: =BF49+AR49 -> 2112000 | BH49: =BH48+1 -> 43
A50: 40001147 | B50: INTEGRATED PROPERTY SALES SY | C50: RESIDENTIAL | D50: RESIDENTIAL | F50: N | G50: Carry-over | R50: =Z50 -> 513411.97 | Z50: =_xlfn.XLOOKUP(A50,'SAP Report'!A:A,'SAP Report'!C:C) -> 513411.97 | AA50: =HLOOKUP($A$4,$AV$6:$BG50,(2+BH49),FALSE) -> 0 | AB50: =SUMIF('Open PR PO'!A:A,Monitoring!A50,'Open PR PO'!K:K) -> 22446.66 | AC50: =AA50+AB50 -> 22446.66 | AD50: =Z50-AC50 -> 490965.31 | AE50: =Z50-AA50 -> 513411.97 | AG50: =SUMIFS(Actual!$F:$F,Actual!$N:$N,Monitoring!AG$6,Actual!$A:$A,Monitoring!$A50) -> 0 | AH50: =SUMIFS(Actual!$F:$F,Actual!$N:$N,Monitoring!AH$6,Actual!$A:$A,Monitoring!$A50) -> 0 | AI50: =SUMIFS(Actual!$F:$F,Actual!$N:$N,Monitoring!AI$6,Actual!$A:$A,Monitoring!$A50) -> 0 | AJ50: =SUMIFS(Actual!$F:$F,Actual!$N:$N,Monitoring!AJ$6,Actual!$A:$A,Monitoring!$A50) -> 0 | AK50: =SUMIFS(Actual!$F:$F,Actual!$N:$N,Monitoring!AK$6,Actual!$A:$A,Monitoring!$A50) -> 0 | AL50: =SUMIFS(Actual!$F:$F,Actual!$N:$N,Monitoring!AL$6,Actual!$A:$A,Monitoring!$A50) -> 0 | AM50: =SUMIFS(Actual!$F:$F,Actual!$N:$N,Monitoring!AM$6,Actual!$A:$A,Monitoring!$A50) -> 0 | AN50: =SUMIFS(Actual!$F:$F,Actual!$N:$N,Monitoring!AN$6,Actual!$A:$A,Monitoring!$A50) -> 0 | AO50: =SUMIFS(Actual!$F:$F,Actual!$N:$N,Monitoring!AO$6,Actual!$A:$A,Monitoring!$A50) -> 0 | AP50: =AB50 -> 22446.66 | AQ50: =AD50/2 -> 245482.65 | AR50: =AQ50 -> 245482.65 | AS50: =SUM(AG50:AR50) -> 513411.97 | AT50: =Z50-AS50 -> 0 | AV50: =AG50 -> 0 | AW50: =AV50+AH50 -> 0 | AX50: =AW50+AI50 -> 0 | AY50: =AX50+AJ50 -> 0 | AZ50: =AY50+AK50 -> 0 | BA50: =AZ50+AL50 -> 0 | BB50: =BA50+AM50 -> 0 | BC50: =BB50+AN50 -> 0 | BD50: =BC50+AO50 -> 0 | ... BG50: =BF50+AR50 -> 513411.97 | BH50: =BH49+1 -> 44
A51: 40001171 | B51: RBU EST-NW&SW SALES OFFICES | C51: RESIDENTIAL | D51: RESIDENTIAL | F51: N | G51: Carry-over | R51: =Z51 -> 43158.94 | Z51: =_xlfn.XLOOKUP(A51,'SAP Report'!A:A,'SAP Report'!C:C) -> 43158.94 | AA51: =HLOOKUP($A$4,$AV$6:$BG51,(2+BH50),FALSE) -> 0 | AB51: =SUMIF('Open PR PO'!A:A,Monitoring!A51,'Open PR PO'!K:K) -> 43158.94 | AC51: =AA51+AB51 -> 43158.94 | AD51: =Z51-AC51 -> 0 | AE51: =Z51-AA51 -> 43158.94 | AG51: =SUMIFS(Actual!$F:$F,Actual!$N:$N,Monitoring!AG$6,Actual!$A:$A,Monitoring!$A51) -> 0 | AH51: =SUMIFS(Actual!$F:$F,Actual!$N:$N,Monitoring!AH$6,Actual!$A:$A,Monitoring!$A51) -> 0 | AI51: =SUMIFS(Actual!$F:$F,Actual!$N:$N,Monitoring!AI$6,Actual!$A:$A,Monitoring!$A51) -> 0 | AJ51: =SUMIFS(Actual!$F:$F,Actual!$N:$N,Monitoring!AJ$6,Actual!$A:$A,Monitoring!$A51) -> 0 | AK51: =SUMIFS(Actual!$F:$F,Actual!$N:$N,Monitoring!AK$6,Actual!$A:$A,Monitoring!$A51) -> 0 | AL51: =SUMIFS(Actual!$F:$F,Actual!$N:$N,Monitoring!AL$6,Actual!$A:$A,Monitoring!$A51) -> 0 | AM51: =SUMIFS(Actual!$F:$F,Actual!$N:$N,Monitoring!AM$6,Actual!$A:$A,Monitoring!$A51) -> 0 | AN51: =SUMIFS(Actual!$F:$F,Actual!$N:$N,Monitoring!AN$6,Actual!$A:$A,Monitoring!$A51) -> 0 | AO51: =SUMIFS(Actual!$F:$F,Actual!$N:$N,Monitoring!AO$6,Actual!$A:$A,Monitoring!$A51) -> 0 | AP51: =AB51 -> 43158.94 | AQ51: =AD51/2 -> 0 | AR51: =AQ51 -> 0 | AS51: =SUM(AG51:AR51) -> 43158.94 | AT51: =Z51-AS51 -> 0 | AV51: =AG51 -> 0 | AW51: =AV51+AH51 -> 0 | AX51: =AW51+AI51 -> 0 | AY51: =AX51+AJ51 -> 0 | AZ51: =AY51+AK51 -> 0 | BA51: =AZ51+AL51 -> 0 | BB51: =BA51+AM51 -> 0 | BC51: =BB51+AN51 -> 0 | BD51: =BC51+AO51 -> 0 | ... BG51: =BF51+AR51 -> 43158.94 | BH51: =BH50+1 -> 45
... A60: 10001143 | B60: CCIC EXTERIOR WALL & CEILING | C60: RESIDENTIAL | D60: RESIDENTIAL | F60: N | G60: Carry-over | R60: =Z60 -> 308303.57 | Z60: =_xlfn.XLOOKUP(A60,'SAP Report'!A:A,'SAP Report'!C:C) -> 308303.57 | AA60: =HLOOKUP($A$4,$AV$6:$BG60,(2+BH59),FALSE) -> 0 | AB60: =SUMIF('Open PR PO'!A:A,Monitoring!A60,'Open PR PO'!K:K) -> 0 | AC60: =AA60+AB60 -> 0 | AD60: =Z60-AC60 -> 308303.57 | AE60: =Z60-AA60 -> 308303.57 | AG60: =SUMIFS(Actual!$F:$F,Actual!$N:$N,Monitoring!AG$6,Actual!$A:$A,Monitoring!$A60) -> 0 | AH60: =SUMIFS(Actual!$F:$F,Actual!$N:$N,Monitoring!AH$6,Actual!$A:$A,Monitoring!$A60) -> 0 | AI60: =SUMIFS(Actual!$F:$F,Actual!$N:$N,Monitoring!AI$6,Actual!$A:$A,Monitoring!$A60) -> 0 | AJ60: =SUMIFS(Actual!$F:$F,Actual!$N:$N,Monitoring!AJ$6,Actual!$A:$A,Monitoring!$A60) -> 0 | AK60: =SUMIFS(Actual!$F:$F,Actual!$N:$N,Monitoring!AK$6,Actual!$A:$A,Monitoring!$A60) -> 0 | AL60: =SUMIFS(Actual!$F:$F,Actual!$N:$N,Monitoring!AL$6,Actual!$A:$A,Monitoring!$A60) -> 0 | AM60: =SUMIFS(Actual!$F:$F,Actual!$N:$N,Monitoring!AM$6,Actual!$A:$A,Monitoring!$A60) -> 0 | AN60: =SUMIFS(Actual!$F:$F,Actual!$N:$N,Monitoring!AN$6,Actual!$A:$A,Monitoring!$A60) -> 0 | AO60: =SUMIFS(Actual!$F:$F,Actual!$N:$N,Monitoring!AO$6,Actual!$A:$A,Monitoring!$A60) -> 0 | AP60: =AB60 -> 0 | AQ60: =AD60/2 -> 154151.79 | AR60: =AQ60 -> 154151.79 | AS60: =SUM(AG60:AR60) -> 308303.57 | AT60: =Z60-AS60 -> 0 | AV60: =AG60 -> 0 | AW60: =AV60+AH60 -> 0 | AX60: =AW60+AI60 -> 0 | AY60: =AX60+AJ60 -> 0 | AZ60: =AY60+AK60 -> 0 | BA60: =AZ60+AL60 -> 0 | BB60: =BA60+AM60 -> 0 | BC60: =BB60+AN60 -> 0 | BD60: =BC60+AO60 -> 0 | ... BG60: =BF60+AR60 -> 308303.57 | BH60: =BH59+1 -> 54
A61: 40001261 | B61: =J61 -> 2026 BYD TANG DMI B.BORJA | C61: CORPORATE | D61: Corporate - HR | E61: Car Plan | F61: N | G61: New | H61: MGM-2026B-NPC001 | I61: 1501 | J61: 2026 BYD TANG DMI B.BORJA | K61: =LEN(J61) -> 25 | L61: =LEFT(M61,2)&"00" -> 8100 | M61: 81123102 | N61: =_xlfn.XLOOKUP(M61,[2]Sheet1!$A:$A,[2]Sheet1!$D:$D) -> ADMIN SERVICES | O61: BENJAMIN BORJA | P61: MDIA | Q61: TID-0000067130 | R61: =2048000-219428.57 -> 1828571.4 | S61: 01/20/2026 | T61: =_xlfn.XLOOKUP(M61,[2]Sheet1!$A:$A,[2]Sheet1!$E:$E) -> CORPORATE | U61: 01/20/2026 | V61: 01/31/2026 | W61: 01/22/2026 | X61: 0300011298/ 0300011421 | Z61: =_xlfn.XLOOKUP(A61,'SAP Report'!A:A,'SAP Report'!C:C) -> 1828571.4 | AA61: =HLOOKUP($A$4,$AV$6:$BG61,(2+BH60),FALSE) -> 1828571.4 | AB61: =SUMIF('Open PR PO'!A:A,Monitoring!A61,'Open PR PO'!K:K) -> 0 | AC61: =AA61+AB61 -> 1828571.4 | AD61: =Z61-AC61 -> 0 | AE61: =Z61-AA61 -> 0 | AG61: =SUMIFS(Actual!$F:$F,Actual!$N:$N,Monitoring!AG$6,Actual!$A:$A,Monitoring!$A61) -> 0 | AH61: =SUMIFS(Actual!$F:$F,Actual!$N:$N,Monitoring!AH$6,Actual!$A:$A,Monitoring!$A61) -> 1828571.4 | AI61: =SUMIFS(Actual!$F:$F,Actual!$N:$N,Monitoring!AI$6,Actual!$A:$A,Monitoring!$A61) -> 0 | AJ61: =SUMIFS(Actual!$F:$F,Actual!$N:$N,Monitoring!AJ$6,Actual!$A:$A,Monitoring!$A61) -> 0 | AK61: =SUMIFS(Actual!$F:$F,Actual!$N:$N,Monitoring!AK$6,Actual!$A:$A,Monitoring!$A61) -> 0 | AL61: =SUMIFS(Actual!$F:$F,Actual!$N:$N,Monitoring!AL$6,Actual!$A:$A,Monitoring!$A61) -> 0 | AM61: =SUMIFS(Actual!$F:$F,Actual!$N:$N,Monitoring!AM$6,Actual!$A:$A,Monitoring!$A61) -> 0 | AN61: =SUMIFS(Actual!$F:$F,Actual!$N:$N,Monitoring!AN$6,Actual!$A:$A,Monitoring!$A61) -> 0 | AO61: =SUMIFS(Actual!$F:$F,Actual!$N:$N,Monitoring!AO$6,Actual!$A:$A,Monitoring!$A61) -> 0 | AP61: =AB61 -> 0 | AQ61: =AD61/2 -> 0 | AR61: =AQ61 -> 0 | AS61: =SUM(AG61:AR61) -> 1828571.4 | AT61: =Z61-AS61 -> 0 | AV61: =AG61 -> 0 | AW61: =AV61+AH61 -> 1828571.4 | AX61: =AW61+AI61 -> 1828571.4 | AY61: =AX61+AJ61 -> 1828571.4 | AZ61: =AY61+AK61 -> 1828571.4 | BA61: =AZ61+AL61 -> 1828571.4 | BB61: =BA61+AM61 -> 1828571.4 | BC61: =BB61+AN61 -> 1828571.4 | BD61: =BC61+AO61 -> 1828571.4 | ... BG61: =BF61+AR61 -> 1828571.4 | BH61: =BH60+1 -> 55
A62: 10001385 | B62: =J62 -> GH AUTOMATIC SLIDING DOOR | C62: MALLS | D62: MALLS | E62: Malls Improvements | F62: N | G62: New | H62: JLC-2026B-NPC016 | I62: 1110 | J62: GH AUTOMATIC SLIDING DOOR | K62: =LEN(J62) -> 25 | L62: =LEFT(M62,2)&"00" -> 8100 | M62: 81221701 | N62: =_xlfn.XLOOKUP(M62,[2]Sheet1!$A:$A,[2]Sheet1!$D:$D) -> GH PHASE 1 MALL | O62: JUN SIOSON/ DOMINIC VILLANUEVA | P62: JAMES CANDELARIA | Q62: TID-0000067151/ TID-0000082623 | R62: =5000000+500000 -> 5500000 | S62: 01/20/2026 | T62: =_xlfn.XLOOKUP(M62,[2]Sheet1!$A:$A,[2]Sheet1!$E:$E) -> MALLS | U62: 46023 | V62: 03/31/2026 | W62: 01/27/2026 | X62: 0300011305/ 0300011480 | Z62: =_xlfn.XLOOKUP(A62,'SAP Report'!A:A,'SAP Report'!C:C) -> 5500000 | AA62: =HLOOKUP($A$4,$AV$6:$BG62,(2+BH61),FALSE) -> 2053571.4 | AB62: =SUMIF('Open PR PO'!A:A,Monitoring!A62,'Open PR PO'!K:K) -> 3237276.8 | AC62: =AA62+AB62 -> 5290848.2 | AD62: =Z62-AC62 -> 209151.79 | AE62: =Z62-AA62 -> 3446428.6 | AG62: =SUMIFS(Actual!$F:$F,Actual!$N:$N,Monitoring!AG$6,Actual!$A:$A,Monitoring!$A62) -> 0 | AH62: =SUMIFS(Actual!$F:$F,Actual!$N:$N,Monitoring!AH$6,Actual!$A:$A,Monitoring!$A62) -> 0 | AI62: =SUMIFS(Actual!$F:$F,Actual!$N:$N,Monitoring!AI$6,Actual!$A:$A,Monitoring!$A62) -> 0 | AJ62: =SUMIFS(Actual!$F:$F,Actual!$N:$N,Monitoring!AJ$6,Actual!$A:$A,Monitoring!$A62) -> 0 | AK62: =SUMIFS(Actual!$F:$F,Actual!$N:$N,Monitoring!AK$6,Actual!$A:$A,Monitoring!$A62) -> 0 | AL62: =SUMIFS(Actual!$F:$F,Actual!$N:$N,Monitoring!AL$6,Actual!$A:$A,Monitoring!$A62) -> 0 | AM62: =SUMIFS(Actual!$F:$F,Actual!$N:$N,Monitoring!AM$6,Actual!$A:$A,Monitoring!$A62) -> 2053571.4 | AN62: =SUMIFS(Actual!$F:$F,Actual!$N:$N,Monitoring!AN$6,Actual!$A:$A,Monitoring!$A62) -> 0 | AO62: =SUMIFS(Actual!$F:$F,Actual!$N:$N,Monitoring!AO$6,Actual!$A:$A,Monitoring!$A62) -> 0 | AP62: =AB62 -> 3237276.8 | AQ62: =AD62/2 -> 104575.9 | AR62: =AQ62 -> 104575.9 | AS62: =SUM(AG62:AR62) -> 5500000 | AT62: =Z62-AS62 -> 0 | AV62: =AG62 -> 0 | AW62: =AV62+AH62 -> 0 | AX62: =AW62+AI62 -> 0 | AY62: =AX62+AJ62 -> 0 | AZ62: =AY62+AK62 -> 0 | BA62: =AZ62+AL62 -> 0 | BB62: =BA62+AM62 -> 2053571.4 | BC62: =BB62+AN62 -> 2053571.4 | BD62: =BC62+AO62 -> 2053571.4 | ... BG62: =BF62+AR62 -> 5500000 | BH62: =BH61+1 -> 56
A63: 10001386 | B63: =J63 -> ES PARKING LIGHTINGS & BARRIER UPGRADE | C63: MALLS | D63: MALLS | E63: Parking | F63: N | G63: New | H63: RFT-2026B-NPC006 | I63: 1110 | J63: ES PARKING LIGHTINGS & BARRIER UPGRADE | K63: =LEN(J63) -> 38 | L63: =LEFT(M63,2)&"00" -> 8100 | M63: 81225102 | N63: =_xlfn.XLOOKUP(M63,[2]Sheet1!$A:$A,[2]Sheet1!$D:$D) -> ESTANCIA PARKING | O63: ROWENA MISLOS | P63: RANDY TORRES | Q63: TID-0000067740 | R63: 2000000 | S63: 01/29/2026 | T63: =_xlfn.XLOOKUP(M63,[2]Sheet1!$A:$A,[2]Sheet1!$E:$E) -> MALLS | U63: 01/01/2026 | V63: 08/31/2026 | W63: 02/05/2026 | X63: 0300011308 | Z63: =_xlfn.XLOOKUP(A63,'SAP Report'!A:A,'SAP Report'!C:C) -> 2000000 | AA63: =HLOOKUP($A$4,$AV$6:$BG63,(2+BH62),FALSE) -> 300000 | AB63: =SUMIF('Open PR PO'!A:A,Monitoring!A63,'Open PR PO'!K:K) -> 104738 | AC63: =AA63+AB63 -> 404738 | AD63: =Z63-AC63 -> 1595262 | AE63: =Z63-AA63 -> 1700000 | AG63: =SUMIFS(Actual!$F:$F,Actual!$N:$N,Monitoring!AG$6,Actual!$A:$A,Monitoring!$A63) -> 0 | AH63: =SUMIFS(Actual!$F:$F,Actual!$N:$N,Monitoring!AH$6,Actual!$A:$A,Monitoring!$A63) -> 0 | AI63: =SUMIFS(Actual!$F:$F,Actual!$N:$N,Monitoring!AI$6,Actual!$A:$A,Monitoring!$A63) -> 0 | AJ63: =SUMIFS(Actual!$F:$F,Actual!$N:$N,Monitoring!AJ$6,Actual!$A:$A,Monitoring!$A63) -> 0 | AK63: =SUMIFS(Actual!$F:$F,Actual!$N:$N,Monitoring!AK$6,Actual!$A:$A,Monitoring!$A63) -> 0 | AL63: =SUMIFS(Actual!$F:$F,Actual!$N:$N,Monitoring!AL$6,Actual!$A:$A,Monitoring!$A63) -> 266071.42 | AM63: =SUMIFS(Actual!$F:$F,Actual!$N:$N,Monitoring!AM$6,Actual!$A:$A,Monitoring!$A63) -> 25000.01 | AN63: =SUMIFS(Actual!$F:$F,Actual!$N:$N,Monitoring!AN$6,Actual!$A:$A,Monitoring!$A63) -> 8928.57 | AO63: =SUMIFS(Actual!$F:$F,Actual!$N:$N,Monitoring!AO$6,Actual!$A:$A,Monitoring!$A63) -> 0 | AP63: =AB63 -> 104738 | AQ63: =AD63/2 -> 797631 | AR63: =AQ63 -> 797631 | AS63: =SUM(AG63:AR63) -> 2000000 | AT63: =Z63-AS63 -> 0 | AV63: =AG63 -> 0 | AW63: =AV63+AH63 -> 0 | AX63: =AW63+AI63 -> 0 | AY63: =AX63+AJ63 -> 0 | AZ63: =AY63+AK63 -> 0 | BA63: =AZ63+AL63 -> 266071.42 | BB63: =BA63+AM63 -> 291071.43 | BC63: =BB63+AN63 -> 300000 | BD63: =BC63+AO63 -> 300000 | ... BG63: =BF63+AR63 -> 2000000 | BH63: =BH62+1 -> 57
A64: 10001387 | B64: =J64 -> ES UPGRADE OF MALL ENTRANCES | C64: MALLS | D64: MALLS | E64: Malls Improvements | F64: N | G64: New | H64: RFT-2026B-NPC021 | I64: 1100 | J64: ES UPGRADE OF MALL ENTRANCES | K64: =LEN(J64) -> 28 | L64: =LEFT(M64,2)&"00" -> 8100 | M64: 81225201 | N64: =_xlfn.XLOOKUP(M64,[2]Sheet1!$A:$A,[2]Sheet1!$D:$D) -> ESTANCIA EXP - MALL | O64: ROWENA MISLOS | P64: RANDY TORRES | Q64: TID-0000067736/ TID-0000076680 | R64: =4000000-645000 -> 3355000 | S64: 01/29/2026 | T64: =_xlfn.XLOOKUP(M64,[2]Sheet1!$A:$A,[2]Sheet1!$E:$E) -> MALLS | U64: 01/01/2026 | V64: 06/30/2026 | W64: 02/05/2026 | X64: 0300011309 | Z64: =_xlfn.XLOOKUP(A64,'SAP Report'!A:A,'SAP Report'!C:C) -> 3355000 | AA64: =HLOOKUP($A$4,$AV$6:$BG64,(2+BH63),FALSE) -> 49316.69 | AB64: =SUMIF('Open PR PO'!A:A,Monitoring!A64,'Open PR PO'!K:K) -> 469548.71 | AC64: =AA64+AB64 -> 518865.4 | AD64: =Z64-AC64 -> 2836134.6 | AE64: =Z64-AA64 -> 3305683.3 | AG64: =SUMIFS(Actual!$F:$F,Actual!$N:$N,Monitoring!AG$6,Actual!$A:$A,Monitoring!$A64) -> 0 | AH64: =SUMIFS(Actual!$F:$F,Actual!$N:$N,Monitoring!AH$6,Actual!$A:$A,Monitoring!$A64) -> 0 | AI64: =SUMIFS(Actual!$F:$F,Actual!$N:$N,Monitoring!AI$6,Actual!$A:$A,Monitoring!$A64) -> 1227.4 | AJ64: =SUMIFS(Actual!$F:$F,Actual!$N:$N,Monitoring!AJ$6,Actual!$A:$A,Monitoring!$A64) -> 0 | AK64: =SUMIFS(Actual!$F:$F,Actual!$N:$N,Monitoring!AK$6,Actual!$A:$A,Monitoring!$A64) -> 48089.29 | AL64: =SUMIFS(Actual!$F:$F,Actual!$N:$N,Monitoring!AL$6,Actual!$A:$A,Monitoring!$A64) -> 0 | AM64: =SUMIFS(Actual!$F:$F,Actual!$N:$N,Monitoring!AM$6,Actual!$A:$A,Monitoring!$A64) -> 0 | AN64: =SUMIFS(Actual!$F:$F,Actual!$N:$N,Monitoring!AN$6,Actual!$A:$A,Monitoring!$A64) -> 0 | AO64: =SUMIFS(Actual!$F:$F,Actual!$N:$N,Monitoring!AO$6,Actual!$A:$A,Monitoring!$A64) -> 0 | AP64: =AB64 -> 469548.71 | AQ64: =AD64/2 -> 1418067.3 | AR64: =AQ64 -> 1418067.3 | AS64: =SUM(AG64:AR64) -> 3355000 | AT64: =Z64-AS64 -> 0 | AV64: =AG64 -> 0 | AW64: =AV64+AH64 -> 0 | AX64: =AW64+AI64 -> 1227.4 | AY64: =AX64+AJ64 -> 1227.4 | AZ64: =AY64+AK64 -> 49316.69 | BA64: =AZ64+AL64 -> 49316.69 | BB64: =BA64+AM64 -> 49316.69 | BC64: =BB64+AN64 -> 49316.69 | BD64: =BC64+AO64 -> 49316.69 | ... BG64: =BF64+AR64 -> 3355000 | BH64: =BH63+1 -> 58
A65: 10001388 | B65: =J65 -> ES UPGRADE OF MALL COMMON CRS | C65: MALLS | D65: MALLS | E65: CR | F65: N | G65: New | H65: RFT-2026B-NPC022 | I65: 1100 | J65: ES UPGRADE OF MALL COMMON CRS | K65: =LEN(J65) -> 29 | L65: =LEFT(M65,2)&"00" -> 8100 | M65: 81225201 | N65: =_xlfn.XLOOKUP(M65,[2]Sheet1!$A:$A,[2]Sheet1!$D:$D) -> ESTANCIA EXP - MALL | O65: ROWENA MISLOS | P65: RANDY TORRES | Q65: TID-0000067735 | R65: 5000000 | S65: 01/29/2026 | T65: =_xlfn.XLOOKUP(M65,[2]Sheet1!$A:$A,[2]Sheet1!$E:$E) -> MALLS | U65: 01/01/2026 | V65: 06/30/2026 | W65: 02/05/2026 | X65: 0300011310 | Z65: =_xlfn.XLOOKUP(A65,'SAP Report'!A:A,'SAP Report'!C:C) -> 5000000 | AA65: =HLOOKUP($A$4,$AV$6:$BG65,(2+BH64),FALSE) -> 843125.13 | AB65: =SUMIF('Open PR PO'!A:A,Monitoring!A65,'Open PR PO'!K:K) -> 3688102.2 | AC65: =AA65+AB65 -> 4531227.3 | AD65: =Z65-AC65 -> 468772.69 | AE65: =Z65-AA65 -> 4156874.9 | AG65: =SUMIFS(Actual!$F:$F,Actual!$N:$N,Monitoring!AG$6,Actual!$A:$A,Monitoring!$A65) -> 0 | AH65: =SUMIFS(Actual!$F:$F,Actual!$N:$N,Monitoring!AH$6,Actual!$A:$A,Monitoring!$A65) -> 0 | AI65: =SUMIFS(Actual!$F:$F,Actual!$N:$N,Monitoring!AI$6,Actual!$A:$A,Monitoring!$A65) -> 0 | AJ65: =SUMIFS(Actual!$F:$F,Actual!$N:$N,Monitoring!AJ$6,Actual!$A:$A,Monitoring!$A65) -> 0 | AK65: =SUMIFS(Actual!$F:$F,Actual!$N:$N,Monitoring!AK$6,Actual!$A:$A,Monitoring!$A65) -> 38531.25 | AL65: =SUMIFS(Actual!$F:$F,Actual!$N:$N,Monitoring!AL$6,Actual!$A:$A,Monitoring!$A65) -> 0 | AM65: =SUMIFS(Actual!$F:$F,Actual!$N:$N,Monitoring!AM$6,Actual!$A:$A,Monitoring!$A65) -> 0 | AN65: =SUMIFS(Actual!$F:$F,Actual!$N:$N,Monitoring!AN$6,Actual!$A:$A,Monitoring!$A65) -> 804593.88 | AO65: =SUMIFS(Actual!$F:$F,Actual!$N:$N,Monitoring!AO$6,Actual!$A:$A,Monitoring!$A65) -> 0 | AP65: =AB65 -> 3688102.2 | AQ65: =AD65/2 -> 234386.35 | AR65: =AQ65 -> 234386.35 | AS65: =SUM(AG65:AR65) -> 5000000 | AT65: =Z65-AS65 -> 0 | AV65: =AG65 -> 0 | AW65: =AV65+AH65 -> 0 | AX65: =AW65+AI65 -> 0 | AY65: =AX65+AJ65 -> 0 | AZ65: =AY65+AK65 -> 38531.25 | BA65: =AZ65+AL65 -> 38531.25 | BB65: =BA65+AM65 -> 38531.25 | BC65: =BB65+AN65 -> 843125.13 | BD65: =BC65+AO65 -> 843125.13 | ... BG65: =BF65+AR65 -> 5000000 | BH65: =BH64+1 -> 59
A66: 10001389 | B66: =J66 -> ES EW FACILITY ENHANCEMENTS | C66: MALLS | D66: MALLS | E66: Malls Improvements | F66: N | G66: New | H66: RFT-2026B-NPC023 | I66: 1100 | J66: ES EW FACILITY ENHANCEMENTS | K66: =LEN(J66) -> 27 | L66: =LEFT(M66,2)&"00" -> 8100 | M66: 81225201 | N66: =_xlfn.XLOOKUP(M66,[2]Sheet1!$A:$A,[2]Sheet1!$D:$D) -> ESTANCIA EXP - MALL | O66: ROWENA MISLOS | P66: RANDY TORRES | Q66: TID-0000067737 | R66: 3000000 | S66: 01/29/2026 | T66: =_xlfn.XLOOKUP(M66,[2]Sheet1!$A:$A,[2]Sheet1!$E:$E) -> MALLS | U66: 01/01/2026 | V66: 06/30/2026 | W66: 02/05/2026 | X66: 0300011311 | Z66: =_xlfn.XLOOKUP(A66,'SAP Report'!A:A,'SAP Report'!C:C) -> 3000000 | AA66: =HLOOKUP($A$4,$AV$6:$BG66,(2+BH65),FALSE) -> 700173.93 | AB66: =SUMIF('Open PR PO'!A:A,Monitoring!A66,'Open PR PO'!K:K) -> 1484187.5 | AC66: =AA66+AB66 -> 2184361.4 | AD66: =Z66-AC66 -> 815638.57 | AE66: =Z66-AA66 -> 2299826.1 | AG66: =SUMIFS(Actual!$F:$F,Actual!$N:$N,Monitoring!AG$6,Actual!$A:$A,Monitoring!$A66) -> 0 | AH66: =SUMIFS(Actual!$F:$F,Actual!$N:$N,Monitoring!AH$6,Actual!$A:$A,Monitoring!$A66) -> 0 | AI66: =SUMIFS(Actual!$F:$F,Actual!$N:$N,Monitoring!AI$6,Actual!$A:$A,Monitoring!$A66) -> 2540 | AJ66: =SUMIFS(Actual!$F:$F,Actual!$N:$N,Monitoring!AJ$6,Actual!$A:$A,Monitoring!$A66) -> 0 | AK66: =SUMIFS(Actual!$F:$F,Actual!$N:$N,Monitoring!AK$6,Actual!$A:$A,Monitoring!$A66) -> 10000 | AL66: =SUMIFS(Actual!$F:$F,Actual!$N:$N,Monitoring!AL$6,Actual!$A:$A,Monitoring!$A66) -> 50000 | AM66: =SUMIFS(Actual!$F:$F,Actual!$N:$N,Monitoring!AM$6,Actual!$A:$A,Monitoring!$A66) -> 98214.29 | AN66: =SUMIFS(Actual!$F:$F,Actual!$N:$N,Monitoring!AN$6,Actual!$A:$A,Monitoring!$A66) -> 539419.64 | AO66: =SUMIFS(Actual!$F:$F,Actual!$N:$N,Monitoring!AO$6,Actual!$A:$A,Monitoring!$A66) -> 0 | AP66: =AB66 -> 1484187.5 | AQ66: =AD66/2 -> 407819.29 | AR66: =AQ66 -> 407819.29 | AS66: =SUM(AG66:AR66) -> 3000000 | AT66: =Z66-AS66 -> 0 | AV66: =AG66 -> 0 | AW66: =AV66+AH66 -> 0 | AX66: =AW66+AI66 -> 2540 | AY66: =AX66+AJ66 -> 2540 | AZ66: =AY66+AK66 -> 12540 | BA66: =AZ66+AL66 -> 62540 | BB66: =BA66+AM66 -> 160754.29 | BC66: =BB66+AN66 -> 700173.93 | BD66: =BC66+AO66 -> 700173.93 | ... BG66: =BF66+AR66 -> 3000000 | BH66: =BH65+1 -> 60
A67: 10001390 | B67: =J67 -> ES REFRESH OF AL FRESCO | C67: MALLS | D67: MALLS | E67: Malls Improvements | F67: N | G67: New | H67: RFT-2026B-NPC024 | I67: 1100 | J67: ES REFRESH OF AL FRESCO | K67: =LEN(J67) -> 23 | L67: =LEFT(M67,2)&"00" -> 8100 | M67: 81225201 | N67: =_xlfn.XLOOKUP(M67,[2]Sheet1!$A:$A,[2]Sheet1!$D:$D) -> ESTANCIA EXP - MALL | O67: ROWENA MISLOS | P67: RANDY TORRES | Q67: TID-0000067738/ TID-0000081551 | R67: =4000000-1000000 -> 3000000 | S67: 01/29/2026 | T67: =_xlfn.XLOOKUP(M67,[2]Sheet1!$A:$A,[2]Sheet1!$E:$E) -> MALLS | U67: 01/01/2026 | V67: 06/30/2026 | W67: 02/05/2026 | X67: 0300011312/ 0300011475 | Z67: =_xlfn.XLOOKUP(A67,'SAP Report'!A:A,'SAP Report'!C:C) -> 3000000 | AA67: =HLOOKUP($A$4,$AV$6:$BG67,(2+BH66),FALSE) -> 1076321.4 | AB67: =SUMIF('Open PR PO'!A:A,Monitoring!A67,'Open PR PO'!K:K) -> 614678.57 | AC67: =AA67+AB67 -> 1691000 | AD67: =Z67-AC67 -> 1309000 | AE67: =Z67-AA67 -> 1923678.6 | AG67: =SUMIFS(Actual!$F:$F,Actual!$N:$N,Monitoring!AG$6,Actual!$A:$A,Monitoring!$A67) -> 0 | AH67: =SUMIFS(Actual!$F:$F,Actual!$N:$N,Monitoring!AH$6,Actual!$A:$A,Monitoring!$A67) -> 0 | AI67: =SUMIFS(Actual!$F:$F,Actual!$N:$N,Monitoring!AI$6,Actual!$A:$A,Monitoring!$A67) -> 0 | AJ67: =SUMIFS(Actual!$F:$F,Actual!$N:$N,Monitoring!AJ$6,Actual!$A:$A,Monitoring!$A67) -> 0 | AK67: =SUMIFS(Actual!$F:$F,Actual!$N:$N,Monitoring!AK$6,Actual!$A:$A,Monitoring!$A67) -> 98000 | AL67: =SUMIFS(Actual!$F:$F,Actual!$N:$N,Monitoring!AL$6,Actual!$A:$A,Monitoring!$A67) -> 210000 | AM67: =SUMIFS(Actual!$F:$F,Actual!$N:$N,Monitoring!AM$6,Actual!$A:$A,Monitoring!$A67) -> 171000 | AN67: =SUMIFS(Actual!$F:$F,Actual!$N:$N,Monitoring!AN$6,Actual!$A:$A,Monitoring!$A67) -> 409821.43 | AO67: =SUMIFS(Actual!$F:$F,Actual!$N:$N,Monitoring!AO$6,Actual!$A:$A,Monitoring!$A67) -> 187500 | AP67: =AB67 -> 614678.57 | AQ67: =AD67/2 -> 654500 | AR67: =AQ67 -> 654500 | AS67: =SUM(AG67:AR67) -> 3000000 | AT67: =Z67-AS67 -> 0 | AV67: =AG67 -> 0 | AW67: =AV67+AH67 -> 0 | AX67: =AW67+AI67 -> 0 | AY67: =AX67+AJ67 -> 0 | AZ67: =AY67+AK67 -> 98000 | BA67: =AZ67+AL67 -> 308000 | BB67: =BA67+AM67 -> 479000 | BC67: =BB67+AN67 -> 888821.43 | BD67: =BC67+AO67 -> 1076321.4 | ... BG67: =BF67+AR67 -> 3000000 | BH67: =BH66+1 -> 61
A68: 10001391 | B68: =J68 -> ES REPAINTING & IMPROVEMENT OF PARKING SIGNAGES | C68: MALLS | D68: MALLS | E68: Parking | F68: N | G68: New | H68: RFT-2026B-NPC026 | I68: 1110 | J68: ES REPAINTING & IMPROVEMENT OF PARKING SIGNAGES | K68: =LEN(J68) -> 47 | L68: =LEFT(M68,2)&"00" -> 8100 | M68: 81225102 | N68: =_xlfn.XLOOKUP(M68,[2]Sheet1!$A:$A,[2]Sheet1!$D:$D) -> ESTANCIA PARKING | O68: ROWENA MISLOS | P68: RANDY TORRES | Q68: TID-0000067741 | R68: 1000000 | S68: 01/29/2026 | T68: =_xlfn.XLOOKUP(M68,[2]Sheet1!$A:$A,[2]Sheet1!$E:$E) -> MALLS | U68: 01/01/2026 | V68: 06/30/2026 | W68: 02/05/2026 | X68: 0300011313 | Z68: =_xlfn.XLOOKUP(A68,'SAP Report'!A:A,'SAP Report'!C:C) -> 1000000 | AA68: =HLOOKUP($A$4,$AV$6:$BG68,(2+BH67),FALSE) -> 283779.72 | AB68: =SUMIF('Open PR PO'!A:A,Monitoring!A68,'Open PR PO'!K:K) -> 0 | AC68: =AA68+AB68 -> 283779.72 | AD68: =Z68-AC68 -> 716220.28 | AE68: =Z68-AA68 -> 716220.28 | AG68: =SUMIFS(Actual!$F:$F,Actual!$N:$N,Monitoring!AG$6,Actual!$A:$A,Monitoring!$A68) -> 0 | AH68: =SUMIFS(Actual!$F:$F,Actual!$N:$N,Monitoring!AH$6,Actual!$A:$A,Monitoring!$A68) -> 0 | AI68: =SUMIFS(Actual!$F:$F,Actual!$N:$N,Monitoring!AI$6,Actual!$A:$A,Monitoring!$A68) -> 0 | AJ68: =SUMIFS(Actual!$F:$F,Actual!$N:$N,Monitoring!AJ$6,Actual!$A:$A,Monitoring!$A68) -> 0 | AK68: =SUMIFS(Actual!$F:$F,Actual!$N:$N,Monitoring!AK$6,Actual!$A:$A,Monitoring!$A68) -> 0 | AL68: =SUMIFS(Actual!$F:$F,Actual!$N:$N,Monitoring!AL$6,Actual!$A:$A,Monitoring!$A68) -> 0 | AM68: =SUMIFS(Actual!$F:$F,Actual!$N:$N,Monitoring!AM$6,Actual!$A:$A,Monitoring!$A68) -> 57047.58 | AN68: =SUMIFS(Actual!$F:$F,Actual!$N:$N,Monitoring!AN$6,Actual!$A:$A,Monitoring!$A68) -> 151285.71 | AO68: =SUMIFS(Actual!$F:$F,Actual!$N:$N,Monitoring!AO$6,Actual!$A:$A,Monitoring!$A68) -> 75446.43 | AP68: =AB68 -> 0 | AQ68: =AD68/2 -> 358110.14 | AR68: =AQ68 -> 358110.14 | AS68: =SUM(AG68:AR68) -> 1000000 | AT68: =Z68-AS68 -> 0 | AV68: =AG68 -> 0 | AW68: =AV68+AH68 -> 0 | AX68: =AW68+AI68 -> 0 | AY68: =AX68+AJ68 -> 0 | AZ68: =AY68+AK68 -> 0 | BA68: =AZ68+AL68 -> 0 | BB68: =BA68+AM68 -> 57047.58 | BC68: =BB68+AN68 -> 208333.29 | BD68: =BC68+AO68 -> 283779.72 | ... BG68: =BF68+AR68 -> 1000000 | BH68: =BH67+1 -> 62
A69: 10001392 | B69: =J69 -> ES EW PARKING SIGNAGES REPAINTING & IMPROVEMENT | C69: MALLS | D69: MALLS | E69: Parking | F69: N | G69: New | H69: RFT-2026B-NPC027 | I69: 1110 | J69: ES EW PARKING SIGNAGES REPAINTING & IMPROVEMENT | K69: =LEN(J69) -> 47 | L69: =LEFT(M69,2)&"00" -> 8100 | M69: 81225102 | N69: =_xlfn.XLOOKUP(M69,[2]Sheet1!$A:$A,[2]Sheet1!$D:$D) -> ESTANCIA PARKING | O69: ROWENA MISLOS | P69: RANDY TORRES | Q69: TID-0000067742/ TID-0000073905 | R69: =1000000-1000000 -> 0 | S69: 01/29/2026 | T69: =_xlfn.XLOOKUP(M69,[2]Sheet1!$A:$A,[2]Sheet1!$E:$E) -> MALLS | U69: 01/01/2026 | V69: 06/30/2026 | W69: 02/05/2026 | X69: 0300011314/ '0300011420 | Z69: =_xlfn.XLOOKUP(A69,'SAP Report'!A:A,'SAP Report'!C:C) -> 0 | AA69: =HLOOKUP($A$4,$AV$6:$BG69,(2+BH68),FALSE) -> 0 | AB69: =SUMIF('Open PR PO'!A:A,Monitoring!A69,'Open PR PO'!K:K) -> 0 | AC69: =AA69+AB69 -> 0 | AD69: =Z69-AC69 -> 0 | AE69: =Z69-AA69 -> 0 | AG69: =SUMIFS(Actual!$F:$F,Actual!$N:$N,Monitoring!AG$6,Actual!$A:$A,Monitoring!$A69) -> 0 | AH69: =SUMIFS(Actual!$F:$F,Actual!$N:$N,Monitoring!AH$6,Actual!$A:$A,Monitoring!$A69) -> 0 | AI69: =SUMIFS(Actual!$F:$F,Actual!$N:$N,Monitoring!AI$6,Actual!$A:$A,Monitoring!$A69) -> 0 | AJ69: =SUMIFS(Actual!$F:$F,Actual!$N:$N,Monitoring!AJ$6,Actual!$A:$A,Monitoring!$A69) -> 0 | AK69: =SUMIFS(Actual!$F:$F,Actual!$N:$N,Monitoring!AK$6,Actual!$A:$A,Monitoring!$A69) -> 0 | AL69: =SUMIFS(Actual!$F:$F,Actual!$N:$N,Monitoring!AL$6,Actual!$A:$A,Monitoring!$A69) -> 0 | AM69: =SUMIFS(Actual!$F:$F,Actual!$N:$N,Monitoring!AM$6,Actual!$A:$A,Monitoring!$A69) -> 0 | AN69: =SUMIFS(Actual!$F:$F,Actual!$N:$N,Monitoring!AN$6,Actual!$A:$A,Monitoring!$A69) -> 0 | AO69: =SUMIFS(Actual!$F:$F,Actual!$N:$N,Monitoring!AO$6,Actual!$A:$A,Monitoring!$A69) -> 0 | AP69: =AB69 -> 0 | AQ69: =AD69/2 -> 0 | AR69: =AQ69 -> 0 | AS69: =SUM(AG69:AR69) -> 0 | AT69: =Z69-AS69 -> 0 | AV69: =AG69 -> 0 | AW69: =AV69+AH69 -> 0 | AX69: =AW69+AI69 -> 0 | AY69: =AX69+AJ69 -> 0 | AZ69: =AY69+AK69 -> 0 | BA69: =AZ69+AL69 -> 0 | BB69: =BA69+AM69 -> 0 | BC69: =BB69+AN69 -> 0 | BD69: =BC69+AO69 -> 0 | ... BG69: =BF69+AR69 -> 0 | BH69: =BH68+1 -> 63
A70: 10001393 | B70: =J70 -> ES 2026 SPACE RE-CUT & STUB-OUT | C70: MALLS | D70: MALLS | E70: Space Recut | F70: N | G70: New | H70: RFT-2026B-NPC001 | I70: 1100 | J70: ES 2026 SPACE RE-CUT & STUB-OUT | K70: =LEN(J70) -> 31 | L70: =LEFT(M70,2)&"00" -> 8100 | M70: 81225201 | N70: =_xlfn.XLOOKUP(M70,[2]Sheet1!$A:$A,[2]Sheet1!$D:$D) -> ESTANCIA EXP - MALL | O70: ROWENA MISLOS | P70: RANDY TORRES | Q70: TID-0000067731 | R70: 1500000 | S70: 01/29/2026 | T70: =_xlfn.XLOOKUP(M70,[2]Sheet1!$A:$A,[2]Sheet1!$E:$E) -> MALLS | U70: 01/01/2026 | V70: 12/31/2026 | W70: 02/05/2026 | X70: 0300011315 | Z70: =_xlfn.XLOOKUP(A70,'SAP Report'!A:A,'SAP Report'!C:C) -> 1500000 | AA70: =HLOOKUP($A$4,$AV$6:$BG70,(2+BH69),FALSE) -> 1373767.4 | AB70: =SUMIF('Open PR PO'!A:A,Monitoring!A70,'Open PR PO'!K:K) -> 71428.57 | AC70: =AA70+AB70 -> 1445196 | AD70: =Z70-AC70 -> 54804.04 | AE70: =Z70-AA70 -> 126232.61 | AG70: =SUMIFS(Actual!$F:$F,Actual!$N:$N,Monitoring!AG$6,Actual!$A:$A,Monitoring!$A70) -> 0 | AH70: =SUMIFS(Actual!$F:$F,Actual!$N:$N,Monitoring!AH$6,Actual!$A:$A,Monitoring!$A70) -> 0 | AI70: =SUMIFS(Actual!$F:$F,Actual!$N:$N,Monitoring!AI$6,Actual!$A:$A,Monitoring!$A70) -> 568422.72 | AJ70: =SUMIFS(Actual!$F:$F,Actual!$N:$N,Monitoring!AJ$6,Actual!$A:$A,Monitoring!$A70) -> 126667.02 | AK70: =SUMIFS(Actual!$F:$F,Actual!$N:$N,Monitoring!AK$6,Actual!$A:$A,Monitoring!$A70) -> 211598.55 | AL70: =SUMIFS(Actual!$F:$F,Actual!$N:$N,Monitoring!AL$6,Actual!$A:$A,Monitoring!$A70) -> 118159.66 | AM70: =SUMIFS(Actual!$F:$F,Actual!$N:$N,Monitoring!AM$6,Actual!$A:$A,Monitoring!$A70) -> 226034.52 | AN70: =SUMIFS(Actual!$F:$F,Actual!$N:$N,Monitoring!AN$6,Actual!$A:$A,Monitoring!$A70) -> 122884.92 | AO70: =SUMIFS(Actual!$F:$F,Actual!$N:$N,Monitoring!AO$6,Actual!$A:$A,Monitoring!$A70) -> 0 | AP70: =AB70 -> 71428.57 | AQ70: =AD70/2 -> 27402.02 | AR70: =AQ70 -> 27402.02 | AS70: =SUM(AG70:AR70) -> 1500000 | AT70: =Z70-AS70 -> 0 | AV70: =AG70 -> 0 | AW70: =AV70+AH70 -> 0 | AX70: =AW70+AI70 -> 568422.72 | AY70: =AX70+AJ70 -> 695089.74 | AZ70: =AY70+AK70 -> 906688.29 | BA70: =AZ70+AL70 -> 1024847.9 | BB70: =BA70+AM70 -> 1250882.5 | BC70: =BB70+AN70 -> 1373767.4 | BD70: =BC70+AO70 -> 1373767.4 | ... BG70: =BF70+AR70 -> 1500000 | BH70: =BH69+1 -> 64
A71: 10001394 | B71: =J71 -> ES EW 2026 SPACE RE-CUT & STUB-OUT | C71: MALLS | D71: MALLS | E71: Space Recut | F71: N | G71: New | H71: RFT-2026B-NPC008 | I71: 1100 | J71: ES EW 2026 SPACE RE-CUT & STUB-OUT | K71: =LEN(J71) -> 34 | L71: =LEFT(M71,2)&"00" -> 8100 | M71: 81225201 | N71: =_xlfn.XLOOKUP(M71,[2]Sheet1!$A:$A,[2]Sheet1!$D:$D) -> ESTANCIA EXP - MALL | O71: ROWENA MISLOS | P71: RANDY TORRES | Q71: TID-0000067733/ TID-0000081551 | R71: =3000000+1000000 -> 4000000 | S71: 01/29/2026 | T71: =_xlfn.XLOOKUP(M71,[2]Sheet1!$A:$A,[2]Sheet1!$E:$E) -> MALLS | U71: 01/01/2026 | V71: 12/31/2026 | W71: 02/05/2026 | X71: 0300011316/ 0300011476 | Z71: =_xlfn.XLOOKUP(A71,'SAP Report'!A:A,'SAP Report'!C:C) -> 4000000 | AA71: =HLOOKUP($A$4,$AV$6:$BG71,(2+BH70),FALSE) -> 1098009.3 | AB71: =SUMIF('Open PR PO'!A:A,Monitoring!A71,'Open PR PO'!K:K) -> 2270763.5 | AC71: =AA71+AB71 -> 3368772.8 | AD71: =Z71-AC71 -> 631227.16 | AE71: =Z71-AA71 -> 2901990.7 | AG71: =SUMIFS(Actual!$F:$F,Actual!$N:$N,Monitoring!AG$6,Actual!$A:$A,Monitoring!$A71) -> 0 | AH71: =SUMIFS(Actual!$F:$F,Actual!$N:$N,Monitoring!AH$6,Actual!$A:$A,Monitoring!$A71) -> 25000 | AI71: =SUMIFS(Actual!$F:$F,Actual!$N:$N,Monitoring!AI$6,Actual!$A:$A,Monitoring!$A71) -> 1469.41 | AJ71: =SUMIFS(Actual!$F:$F,Actual!$N:$N,Monitoring!AJ$6,Actual!$A:$A,Monitoring!$A71) -> 323252.57 | AK71: =SUMIFS(Actual!$F:$F,Actual!$N:$N,Monitoring!AK$6,Actual!$A:$A,Monitoring!$A71) -> -1143.84 | AL71: =SUMIFS(Actual!$F:$F,Actual!$N:$N,Monitoring!AL$6,Actual!$A:$A,Monitoring!$A71) -> 333391.09 | AM71: =SUMIFS(Actual!$F:$F,Actual!$N:$N,Monitoring!AM$6,Actual!$A:$A,Monitoring!$A71) -> 133538.25 | AN71: =SUMIFS(Actual!$F:$F,Actual!$N:$N,Monitoring!AN$6,Actual!$A:$A,Monitoring!$A71) -> 20894.72 | AO71: =SUMIFS(Actual!$F:$F,Actual!$N:$N,Monitoring!AO$6,Actual!$A:$A,Monitoring!$A71) -> 261607.14 | AP71: =AB71 -> 2270763.5 | AQ71: =AD71/2 -> 315613.58 | AR71: =AQ71 -> 315613.58 | AS71: =SUM(AG71:AR71) -> 4000000 | AT71: =Z71-AS71 -> 0 | AV71: =AG71 -> 0 | AW71: =AV71+AH71 -> 25000 | AX71: =AW71+AI71 -> 26469.41 | AY71: =AX71+AJ71 -> 349721.98 | AZ71: =AY71+AK71 -> 348578.14 | BA71: =AZ71+AL71 -> 681969.23 | BB71: =BA71+AM71 -> 815507.48 | BC71: =BB71+AN71 -> 836402.2 | BD71: =BC71+AO71 -> 1098009.3 | ... BG71: =BF71+AR71 -> 4000000 | BH71: =BH70+1 -> 65
A72: 10001395 | B72: =J72 -> GH TENANT SPACE RE-CUT & UTILITIES STUB-OUT | C72: MALLS | D72: MALLS | E72: Space Recut | F72: N | G72: New | H72: JLC-2026B-NPC001 | I72: 1100 | J72: GH TENANT SPACE RE-CUT & UTILITIES STUB-OUT | K72: =LEN(J72) -> 43 | L72: =LEFT(M72,2)&"00" -> 8100 | M72: 81221201 | N72: =_xlfn.XLOOKUP(M72,[2]Sheet1!$A:$A,[2]Sheet1!$D:$D) -> GSC OLD BLDGS | O72: JUN SIOSON | P72: JAMES CANDELARIA | Q72: TID-0000068113/ TID-0000079802/ TID-0000083133 | R72: =5000000+500000+712500 -> 6212500 | S72: 46114 | T72: =_xlfn.XLOOKUP(M72,[2]Sheet1!$A:$A,[2]Sheet1!$E:$E) -> MALLS | U72: 01/01/2026 | V72: 10/31/2026 | W72: 02/05/2026 | X72: 0300011317/ 0300011461/ 0300011491 | Z72: =_xlfn.XLOOKUP(A72,'SAP Report'!A:A,'SAP Report'!C:C) -> 6212500 | AA72: =HLOOKUP($A$4,$AV$6:$BG72,(2+BH71),FALSE) -> 4193750 | AB72: =SUMIF('Open PR PO'!A:A,Monitoring!A72,'Open PR PO'!K:K) -> 858035.72 | AC72: =AA72+AB72 -> 5051785.7 | AD72: =Z72-AC72 -> 1160714.3 | AE72: =Z72-AA72 -> 2018750 | AG72: =SUMIFS(Actual!$F:$F,Actual!$N:$N,Monitoring!AG$6,Actual!$A:$A,Monitoring!$A72) -> 0 | AH72: =SUMIFS(Actual!$F:$F,Actual!$N:$N,Monitoring!AH$6,Actual!$A:$A,Monitoring!$A72) -> 0 | AI72: =SUMIFS(Actual!$F:$F,Actual!$N:$N,Monitoring!AI$6,Actual!$A:$A,Monitoring!$A72) -> 0 | AJ72: =SUMIFS(Actual!$F:$F,Actual!$N:$N,Monitoring!AJ$6,Actual!$A:$A,Monitoring!$A72) -> 2233035.7 | AK72: =SUMIFS(Actual!$F:$F,Actual!$N:$N,Monitoring!AK$6,Actual!$A:$A,Monitoring!$A72) -> 294642.86 | AL72: =SUMIFS(Actual!$F:$F,Actual!$N:$N,Monitoring!AL$6,Actual!$A:$A,Monitoring!$A72) -> 0 | AM72: =SUMIFS(Actual!$F:$F,Actual!$N:$N,Monitoring!AM$6,Actual!$A:$A,Monitoring!$A72) -> 589285.72 | AN72: =SUMIFS(Actual!$F:$F,Actual!$N:$N,Monitoring!AN$6,Actual!$A:$A,Monitoring!$A72) -> 169642.86 | AO72: =SUMIFS(Actual!$F:$F,Actual!$N:$N,Monitoring!AO$6,Actual!$A:$A,Monitoring!$A72) -> 907142.85 | AP72: =AB72 -> 858035.72 | AQ72: =AD72/2 -> 580357.14 | AR72: =AQ72 -> 580357.14 | AS72: =SUM(AG72:AR72) -> 6212500 | AT72: =Z72-AS72 -> 0 | AV72: =AG72 -> 0 | AW72: =AV72+AH72 -> 0 | AX72: =AW72+AI72 -> 0 | AY72: =AX72+AJ72 -> 2233035.7 | AZ72: =AY72+AK72 -> 2527678.6 | BA72: =AZ72+AL72 -> 2527678.6 | BB72: =BA72+AM72 -> 3116964.3 | BC72: =BB72+AN72 -> 3286607.1 | BD72: =BC72+AO72 -> 4193750 | ... BG72: =BF72+AR72 -> 6212500 | BH72: =BH71+1 -> 66
A73: 40001262 | B73: =J73 -> LAMINATED CABINETS FOR MS. CAROL MILLS | C73: CORPORATE | D73: Corporate - Admin | E73: Furniture & Fixtures | F73: N | G73: New | H73: LPA-2026B-NPC001 | I73: 1300 | J73: LAMINATED CABINETS FOR MS. CAROL MILLS | K73: =LEN(J73) -> 38 | L73: =LEFT(M73,2)&"00" -> 8100 | M73: 81123102 | N73: =_xlfn.XLOOKUP(M73,[2]Sheet1!$A:$A,[2]Sheet1!$D:$D) -> ADMIN SERVICES | O73: CAROL TENEDERO | P73: LINO ARBOLEDA | Q73: TID-0000068582 | R73: 138392.86 | S73: 46297 | T73: =_xlfn.XLOOKUP(M73,[2]Sheet1!$A:$A,[2]Sheet1!$E:$E) -> CORPORATE | U73: 46023 | V73: 01/31/2026 | W73: 46358 | X73: 0300011318 | Z73: =_xlfn.XLOOKUP(A73,'SAP Report'!A:A,'SAP Report'!C:C) -> 138392.86 | AA73: =HLOOKUP($A$4,$AV$6:$BG73,(2+BH72),FALSE) -> 138392.86 | AB73: =SUMIF('Open PR PO'!A:A,Monitoring!A73,'Open PR PO'!K:K) -> 0 | AC73: =AA73+AB73 -> 138392.86 | AD73: =Z73-AC73 -> 0 | AE73: =Z73-AA73 -> 0 | AG73: =SUMIFS(Actual!$F:$F,Actual!$N:$N,Monitoring!AG$6,Actual!$A:$A,Monitoring!$A73) -> 0 | AH73: =SUMIFS(Actual!$F:$F,Actual!$N:$N,Monitoring!AH$6,Actual!$A:$A,Monitoring!$A73) -> 138392.86 | AI73: =SUMIFS(Actual!$F:$F,Actual!$N:$N,Monitoring!AI$6,Actual!$A:$A,Monitoring!$A73) -> 0 | AJ73: =SUMIFS(Actual!$F:$F,Actual!$N:$N,Monitoring!AJ$6,Actual!$A:$A,Monitoring!$A73) -> 0 | AK73: =SUMIFS(Actual!$F:$F,Actual!$N:$N,Monitoring!AK$6,Actual!$A:$A,Monitoring!$A73) -> 0 | AL73: =SUMIFS(Actual!$F:$F,Actual!$N:$N,Monitoring!AL$6,Actual!$A:$A,Monitoring!$A73) -> 0 | AM73: =SUMIFS(Actual!$F:$F,Actual!$N:$N,Monitoring!AM$6,Actual!$A:$A,Monitoring!$A73) -> 0 | AN73: =SUMIFS(Actual!$F:$F,Actual!$N:$N,Monitoring!AN$6,Actual!$A:$A,Monitoring!$A73) -> 0 | AO73: =SUMIFS(Actual!$F:$F,Actual!$N:$N,Monitoring!AO$6,Actual!$A:$A,Monitoring!$A73) -> 0 | AP73: =AB73 -> 0 | AQ73: =AD73/2 -> 0 | AR73: =AQ73 -> 0 | AS73: =SUM(AG73:AR73) -> 138392.86 | AT73: =Z73-AS73 -> 0 | AV73: =AG73 -> 0 | AW73: =AV73+AH73 -> 138392.86 | AX73: =AW73+AI73 -> 138392.86 | AY73: =AX73+AJ73 -> 138392.86 | AZ73: =AY73+AK73 -> 138392.86 | BA73: =AZ73+AL73 -> 138392.86 | BB73: =BA73+AM73 -> 138392.86 | BC73: =BB73+AN73 -> 138392.86 | BD73: =BC73+AO73 -> 138392.86 | ... BG73: =BF73+AR73 -> 138392.86 | BH73: =BH72+1 -> 67
A74: 10001396 | B74: =J74 -> IBP TOWER CONFERENCE ROOM | C74: OFFICES | D74: OFFICES | E74: Offices Improvements | F74: N | G74: New | H74: WPD-2026B-NPC029 | I74: 1100 | J74: IBP TOWER CONFERENCE ROOM | K74: =LEN(J74) -> 25 | L74: =LEFT(M74,2)&"00" -> 8100 | M74: 81321301 | N74: =_xlfn.XLOOKUP(M74,[2]Sheet1!$A:$A,[2]Sheet1!$D:$D) -> IBP TOWER | O74: RONNEL MESANA | P74: WILBERT DIMZON | Q74: TID-0000068738 | R74: 409178.55 | S74: 46328 | T74: =_xlfn.XLOOKUP(M74,[2]Sheet1!$A:$A,[2]Sheet1!$E:$E) -> OFFICES | U74: 01/01/2026 | V74: 04/30/2026 | W74: 46358 | X74: 0300011319 | Z74: =_xlfn.XLOOKUP(A74,'SAP Report'!A:A,'SAP Report'!C:C) -> 409178.55 | AA74: =HLOOKUP($A$4,$AV$6:$BG74,(2+BH73),FALSE) -> 0 | AB74: =SUMIF('Open PR PO'!A:A,Monitoring!A74,'Open PR PO'!K:K) -> 401785.71 | AC74: =AA74+AB74 -> 401785.71 | AD74: =Z74-AC74 -> 7392.84 | AE74: =Z74-AA74 -> 409178.55 | AG74: =SUMIFS(Actual!$F:$F,Actual!$N:$N,Monitoring!AG$6,Actual!$A:$A,Monitoring!$A74) -> 0 | AH74: =SUMIFS(Actual!$F:$F,Actual!$N:$N,Monitoring!AH$6,Actual!$A:$A,Monitoring!$A74) -> 0 | AI74: =SUMIFS(Actual!$F:$F,Actual!$N:$N,Monitoring!AI$6,Actual!$A:$A,Monitoring!$A74) -> 0 | AJ74: =SUMIFS(Actual!$F:$F,Actual!$N:$N,Monitoring!AJ$6,Actual!$A:$A,Monitoring!$A74) -> 0 | AK74: =SUMIFS(Actual!$F:$F,Actual!$N:$N,Monitoring!AK$6,Actual!$A:$A,Monitoring!$A74) -> 0 | AL74: =SUMIFS(Actual!$F:$F,Actual!$N:$N,Monitoring!AL$6,Actual!$A:$A,Monitoring!$A74) -> 0 | AM74: =SUMIFS(Actual!$F:$F,Actual!$N:$N,Monitoring!AM$6,Actual!$A:$A,Monitoring!$A74) -> 0 | AN74: =SUMIFS(Actual!$F:$F,Actual!$N:$N,Monitoring!AN$6,Actual!$A:$A,Monitoring!$A74) -> 0 | AO74: =SUMIFS(Actual!$F:$F,Actual!$N:$N,Monitoring!AO$6,Actual!$A:$A,Monitoring!$A74) -> 0 | AP74: =AB74 -> 401785.71 | AQ74: =AD74/2 -> 3696.42 | AR74: =AQ74 -> 3696.42 | AS74: =SUM(AG74:AR74) -> 409178.55 | AT74: =Z74-AS74 -> 0 | AV74: =AG74 -> 0 | AW74: =AV74+AH74 -> 0 | AX74: =AW74+AI74 -> 0 | AY74: =AX74+AJ74 -> 0 | AZ74: =AY74+AK74 -> 0 | BA74: =AZ74+AL74 -> 0 | BB74: =BA74+AM74 -> 0 | BC74: =BB74+AN74 -> 0 | BD74: =BC74+AO74 -> 0 | ... BG74: =BF74+AR74 -> 409178.55 | BH74: =BH73+1 -> 68
A75: 10001397 | B75: =J75 -> IBP TOWER PRV REPLACEMENT | C75: OFFICES | D75: OFFICES | E75: Water/ Plumbing | F75: N | G75: New | H75: WPD-2026B-NPC010 | I75: 1110 | J75: IBP TOWER PRV REPLACEMENT | K75: =LEN(J75) -> 25 | L75: =LEFT(M75,2)&"00" -> 8100 | M75: 81321301 | N75: =_xlfn.XLOOKUP(M75,[2]Sheet1!$A:$A,[2]Sheet1!$D:$D) -> IBP TOWER | O75: RONNEL MESANA | P75: WILBERT DIMZON | Q75: TID-0000068737 | R75: 350000 | S75: 46328 | T75: =_xlfn.XLOOKUP(M75,[2]Sheet1!$A:$A,[2]Sheet1!$E:$E) -> OFFICES | U75: 01/01/2026 | V75: 04/30/2026 | W75: 46358 | X75: 0300011320 | Z75: =_xlfn.XLOOKUP(A75,'SAP Report'!A:A,'SAP Report'!C:C) -> 350000 | AA75: =HLOOKUP($A$4,$AV$6:$BG75,(2+BH74),FALSE) -> 133928.57 | AB75: =SUMIF('Open PR PO'!A:A,Monitoring!A75,'Open PR PO'!K:K) -> 0 | AC75: =AA75+AB75 -> 133928.57 | AD75: =Z75-AC75 -> 216071.43 | AE75: =Z75-AA75 -> 216071.43 | AG75: =SUMIFS(Actual!$F:$F,Actual!$N:$N,Monitoring!AG$6,Actual!$A:$A,Monitoring!$A75) -> 0 | AH75: =SUMIFS(Actual!$F:$F,Actual!$N:$N,Monitoring!AH$6,Actual!$A:$A,Monitoring!$A75) -> 0 | AI75: =SUMIFS(Actual!$F:$F,Actual!$N:$N,Monitoring!AI$6,Actual!$A:$A,Monitoring!$A75) -> 0 | AJ75: =SUMIFS(Actual!$F:$F,Actual!$N:$N,Monitoring!AJ$6,Actual!$A:$A,Monitoring!$A75) -> 0 | AK75: =SUMIFS(Actual!$F:$F,Actual!$N:$N,Monitoring!AK$6,Actual!$A:$A,Monitoring!$A75) -> 0 | AL75: =SUMIFS(Actual!$F:$F,Actual!$N:$N,Monitoring!AL$6,Actual!$A:$A,Monitoring!$A75) -> 0 | AM75: =SUMIFS(Actual!$F:$F,Actual!$N:$N,Monitoring!AM$6,Actual!$A:$A,Monitoring!$A75) -> 0 | AN75: =SUMIFS(Actual!$F:$F,Actual!$N:$N,Monitoring!AN$6,Actual!$A:$A,Monitoring!$A75) -> 133928.57 | AO75: =SUMIFS(Actual!$F:$F,Actual!$N:$N,Monitoring!AO$6,Actual!$A:$A,Monitoring!$A75) -> 0 | AP75: =AB75 -> 0 | AQ75: =AD75/2 -> 108035.71 | AR75: =AQ75 -> 108035.71 | AS75: =SUM(AG75:AR75) -> 350000 | AT75: =Z75-AS75 -> 0 | AV75: =AG75 -> 0 | AW75: =AV75+AH75 -> 0 | AX75: =AW75+AI75 -> 0 | AY75: =AX75+AJ75 -> 0 | AZ75: =AY75+AK75 -> 0 | BA75: =AZ75+AL75 -> 0 | BB75: =BA75+AM75 -> 0 | BC75: =BB75+AN75 -> 133928.57 | BD75: =BC75+AO75 -> 133928.57 | ... BG75: =BF75+AR75 -> 350000 | BH75: =BH74+1 -> 69
A76: 10001398 | B76: =J76 -> IBP TOWER UPS REPLACEMENT | C76: OFFICES | D76: OFFICES | E76: Electrical | F76: N | G76: New | H76: WPD-2026B-NPC009 | I76: 1110 | J76: IBP TOWER UPS REPLACEMENT | K76: =LEN(J76) -> 25 | L76: =LEFT(M76,2)&"00" -> 8100 | M76: 81321301 | N76: =_xlfn.XLOOKUP(M76,[2]Sheet1!$A:$A,[2]Sheet1!$D:$D) -> IBP TOWER | O76: RONNEL MESANA | P76: WILBERT DIMZON | Q76: TID-0000068736 | R76: 211000 | S76: 46328 | T76: =_xlfn.XLOOKUP(M76,[2]Sheet1!$A:$A,[2]Sheet1!$E:$E) -> OFFICES | U76: 01/01/2026 | V76: 04/30/2026 | W76: 46358 | X76: 0300011321 | Z76: =_xlfn.XLOOKUP(A76,'SAP Report'!A:A,'SAP Report'!C:C) -> 211000 | AA76: =HLOOKUP($A$4,$AV$6:$BG76,(2+BH75),FALSE) -> 168000 | AB76: =SUMIF('Open PR PO'!A:A,Monitoring!A76,'Open PR PO'!K:K) -> 0 | AC76: =AA76+AB76 -> 168000 | AD76: =Z76-AC76 -> 43000 | AE76: =Z76-AA76 -> 43000 | AG76: =SUMIFS(Actual!$F:$F,Actual!$N:$N,Monitoring!AG$6,Actual!$A:$A,Monitoring!$A76) -> 0 | AH76: =SUMIFS(Actual!$F:$F,Actual!$N:$N,Monitoring!AH$6,Actual!$A:$A,Monitoring!$A76) -> 0 | AI76: =SUMIFS(Actual!$F:$F,Actual!$N:$N,Monitoring!AI$6,Actual!$A:$A,Monitoring!$A76) -> 0 | AJ76: =SUMIFS(Actual!$F:$F,Actual!$N:$N,Monitoring!AJ$6,Actual!$A:$A,Monitoring!$A76) -> 168000 | AK76: =SUMIFS(Actual!$F:$F,Actual!$N:$N,Monitoring!AK$6,Actual!$A:$A,Monitoring!$A76) -> 0 | AL76: =SUMIFS(Actual!$F:$F,Actual!$N:$N,Monitoring!AL$6,Actual!$A:$A,Monitoring!$A76) -> 0 | AM76: =SUMIFS(Actual!$F:$F,Actual!$N:$N,Monitoring!AM$6,Actual!$A:$A,Monitoring!$A76) -> 0 | AN76: =SUMIFS(Actual!$F:$F,Actual!$N:$N,Monitoring!AN$6,Actual!$A:$A,Monitoring!$A76) -> 0 | AO76: =SUMIFS(Actual!$F:$F,Actual!$N:$N,Monitoring!AO$6,Actual!$A:$A,Monitoring!$A76) -> 0 | AP76: =AB76 -> 0 | AQ76: =AD76/2 -> 21500 | AR76: =AQ76 -> 21500 | AS76: =SUM(AG76:AR76) -> 211000 | AT76: =Z76-AS76 -> 0 | AV76: =AG76 -> 0 | AW76: =AV76+AH76 -> 0 | AX76: =AW76+AI76 -> 0 | AY76: =AX76+AJ76 -> 168000 | AZ76: =AY76+AK76 -> 168000 | BA76: =AZ76+AL76 -> 168000 | BB76: =BA76+AM76 -> 168000 | BC76: =BB76+AN76 -> 168000 | BD76: =BC76+AO76 -> 168000 | ... BG76: =BF76+AR76 -> 211000 | BH76: =BH75+1 -> 70
A77: 10001399 | B77: =J77 -> IBP TOWER WATERPROOFING ROOFDECK | C77: OFFICES | D77: OFFICES | E77: Waterproofing | F77: N | G77: New | H77: WPD-2026B-NPC008 | I77: 1100 | J77: IBP TOWER WATERPROOFING ROOFDECK | K77: =LEN(J77) -> 32 | L77: =LEFT(M77,2)&"00" -> 8100 | M77: 81321301 | N77: =_xlfn.XLOOKUP(M77,[2]Sheet1!$A:$A,[2]Sheet1!$D:$D) -> IBP TOWER | O77: RONNEL MESANA | P77: WILBERT DIMZON | Q77: TID-0000068735 | R77: 3000000 | S77: 46328 | T77: =_xlfn.XLOOKUP(M77,[2]Sheet1!$A:$A,[2]Sheet1!$E:$E) -> OFFICES | U77: 01/01/2026 | V77: 04/30/2026 | W77: 46358 | X77: 0300011322 | Z77: =_xlfn.XLOOKUP(A77,'SAP Report'!A:A,'SAP Report'!C:C) -> 3000000 | AA77: =HLOOKUP($A$4,$AV$6:$BG77,(2+BH76),FALSE) -> 0 | AB77: =SUMIF('Open PR PO'!A:A,Monitoring!A77,'Open PR PO'!K:K) -> 2455357.1 | AC77: =AA77+AB77 -> 2455357.1 | AD77: =Z77-AC77 -> 544642.86 | AE77: =Z77-AA77 -> 3000000 | AG77: =SUMIFS(Actual!$F:$F,Actual!$N:$N,Monitoring!AG$6,Actual!$A:$A,Monitoring!$A77) -> 0 | AH77: =SUMIFS(Actual!$F:$F,Actual!$N:$N,Monitoring!AH$6,Actual!$A:$A,Monitoring!$A77) -> 0 | AI77: =SUMIFS(Actual!$F:$F,Actual!$N:$N,Monitoring!AI$6,Actual!$A:$A,Monitoring!$A77) -> 0 | AJ77: =SUMIFS(Actual!$F:$F,Actual!$N:$N,Monitoring!AJ$6,Actual!$A:$A,Monitoring!$A77) -> 0 | AK77: =SUMIFS(Actual!$F:$F,Actual!$N:$N,Monitoring!AK$6,Actual!$A:$A,Monitoring!$A77) -> 0 | AL77: =SUMIFS(Actual!$F:$F,Actual!$N:$N,Monitoring!AL$6,Actual!$A:$A,Monitoring!$A77) -> 0 | AM77: =SUMIFS(Actual!$F:$F,Actual!$N:$N,Monitoring!AM$6,Actual!$A:$A,Monitoring!$A77) -> 0 | AN77: =SUMIFS(Actual!$F:$F,Actual!$N:$N,Monitoring!AN$6,Actual!$A:$A,Monitoring!$A77) -> 0 | AO77: =SUMIFS(Actual!$F:$F,Actual!$N:$N,Monitoring!AO$6,Actual!$A:$A,Monitoring!$A77) -> 0 | AP77: =AB77 -> 2455357.1 | AQ77: =AD77/2 -> 272321.43 | AR77: =AQ77 -> 272321.43 | AS77: =SUM(AG77:AR77) -> 3000000 | AT77: =Z77-AS77 -> 0 | AV77: =AG77 -> 0 | AW77: =AV77+AH77 -> 0 | AX77: =AW77+AI77 -> 0 | AY77: =AX77+AJ77 -> 0 | AZ77: =AY77+AK77 -> 0 | BA77: =AZ77+AL77 -> 0 | BB77: =BA77+AM77 -> 0 | BC77: =BB77+AN77 -> 0 | BD77: =BC77+AO77 -> 0 | ... BG77: =BF77+AR77 -> 3000000 | BH77: =BH76+1 -> 71
