Workbook

Sheet GAE
E1: Dropdown list | F1: Dropdown list | G1: Dropdown list | L1: Automatic | M1: Automatic
A2: CD | B2: YY | C2: Num | D2: Budget Code | E2: Expense Category | F2: Expense Line Item | G2: Company | H2: Description | I2: Department | J2: Centralized Dept Requestor/Reviewer | K2: Centralized Dept Head | L2: Cost Center (CC) | M2: GL Account (GL) | N2: Additional Field (required) | O2: Spend Grid Computation | P2: Spend Grid Frequency | Q2: Sample charges | R2: Visible only to (Department)
A3: =_xlfn.XLOOKUP(I3,Lookup!A:A,Lookup!B:B) -> AS | B3: 27 | C3: 1 | D3: =A3&-B3&-C3 -> AS-27-1 | E3: Admin Staff | F3: Company Driver | I3: Administrative Services | J3: Carolina C. Tenedero | K3: Carolina C. Tenedero | L3: 81123102 | M3: 52041499 | N3: Headcount, Rate per Month (w/ OT) | O3: Headcount x Rate per Month (w/ OT) | P3: Monthly | R3: Admin Services
A4: =_xlfn.XLOOKUP(I4,Lookup!A:A,Lookup!B:B) -> AS | B4: 27 | C4: =C3+1 -> 2 | D4: =A4&-B4&-C4 -> AS-27-2 | E4: Admin Staff | F4: Messenger | I4: Administrative Services | J4: Carolina C. Tenedero | K4: Carolina C. Tenedero | L4: 81123102 | M4: 52041499 | N4: Headcount, Rate per Month (w/ OT) | O4: Headcount x Rate per Month (w/ OT) | P4: Monthly | R4: Admin Services
A5: =_xlfn.XLOOKUP(I5,Lookup!A:A,Lookup!B:B) -> AS | B5: 27 | C5: =C4+1 -> 3 | D5: =A5&-B5&-C5 -> AS-27-3 | E5: Admin Staff | F5: Operator | I5: Administrative Services | J5: Carolina C. Tenedero | K5: Carolina C. Tenedero | L5: 81123102 | M5: 52041499 | N5: Headcount, Rate per Month (w/ OT) | O5: Headcount x Rate per Month (w/ OT) | P5: Monthly | R5: Admin Services
A6: =_xlfn.XLOOKUP(I6,Lookup!A:A,Lookup!B:B) -> AS | B6: 27 | C6: =C5+1 -> 4 | D6: =A6&-B6&-C6 -> AS-27-4 | E6: Communication | F6: Mobile Phone | G6: OCC | I6: Administrative Services | J6: Benedict Nicholas A. Sandejas | K6: Benedict Nicholas A. Sandejas | L6: 81123102 | M6: 52951101 | N6: Rank, Month Start, Employee Name, Department | P6: User to select which month
A7: =_xlfn.XLOOKUP(I7,Lookup!A:A,Lookup!B:B) -> AS | B7: 27 | C7: =C6+1 -> 5 | D7: =A7&-B7&-C7 -> AS-27-5 | E7: Communication | F7: Mobile Phone | G7: OCLP | I7: Administrative Services | J7: Benedict Nicholas A. Sandejas | K7: Benedict Nicholas A. Sandejas | L7: 80123102 | M7: 61721101 | N7: Rank, Month Start, Employee Name, Department | P7: User to select which month
A8: =_xlfn.XLOOKUP(I8,Lookup!A:A,Lookup!B:B) -> AS | B8: 27 | C8: =C7+1 -> 6 | D8: =A8&-B8&-C8 -> AS-27-6 | E8: Communication | F8: Phone - JHJ | I8: Administrative Services | J8: Benedict Nicholas A. Sandejas | K8: Benedict Nicholas A. Sandejas | L8: 80123102 | M8: 61721101
A9: =_xlfn.XLOOKUP(I9,Lookup!A:A,Lookup!B:B) -> AS | B9: 27 | C9: =C8+1 -> 7 | D9: =A9&-B9&-C9 -> AS-27-7 | E9: Communication | F9: Phone - MDIA | I9: Administrative Services | J9: Benedict Nicholas A. Sandejas | K9: Benedict Nicholas A. Sandejas | L9: 80123102 | M9: 61721101
A10: =_xlfn.XLOOKUP(I10,Lookup!A:A,Lookup!B:B) -> AS | B10: 27 | C10: =C9+1 -> 8 | D10: =A10&-B10&-C10 -> AS-27-8 | E10: Communication | F10: Trunk Line/Direct Line/Land Line | I10: Administrative Services | J10: Benedict Nicholas A. Sandejas | K10: Benedict Nicholas A. Sandejas | L10: 80123102 | M10: 61721101 | N10: Count | R10: Admin Services
A11: =_xlfn.XLOOKUP(I11,Lookup!A:A,Lookup!B:B) -> AS | B11: 27 | C11: =C10+1 -> 9 | D11: =A11&-B11&-C11 -> AS-27-9 | E11: Drivers' Meal Allowance | F11: Drivers' Meal Allowance | I11: Administrative Services | J11: Carolina C. Tenedero | K11: Carolina C. Tenedero | L11: 81123102 | M11: 52081103 | N11: Headcount, Meal Allowance Rate | O11: Headcount x Meal Allowance Rate x 20 days per month | P11: Monthly | R11: Admin Services
A12: =_xlfn.XLOOKUP(I12,Lookup!A:A,Lookup!B:B) -> AS | B12: 27 | C12: =C11+1 -> 10 | D12: =A12&-B12&-C12 -> AS-27-10 | E12: Dues and Fees | F12: Cenro | I12: Administrative Services | J12: Lino P. Arboleda | K12: Lino P. Arboleda | L12: 80123102 | M12: 61711101 | R12: Admin Services
A13: =_xlfn.XLOOKUP(I13,Lookup!A:A,Lookup!B:B) -> AS | B13: 27 | C13: =C12+1 -> 11 | D13: =A13&-B13&-C13 -> AS-27-11 | E13: Dues and Fees | F13: Others | I13: Administrative Services | J13: Lino P. Arboleda | K13: Lino P. Arboleda | L13: 80123102 | M13: 61711101 | N13: Specify | R13: Admin Services
A14: =_xlfn.XLOOKUP(I14,Lookup!A:A,Lookup!B:B) -> AS | B14: 27 | C14: =C13+1 -> 12 | D14: =A14&-B14&-C14 -> AS-27-12 | E14: Electricity & Water | F14: Electricity & Water | I14: Administrative Services | J14: Princess Vera P. Jumalon | K14: Princess Vera P. Jumalon | L14: 80123102 | M14: 61041101 | R14: TSG
A15: =_xlfn.XLOOKUP(I15,Lookup!A:A,Lookup!B:B) -> AS | B15: 27 | C15: =C14+1 -> 13 | D15: =A15&-B15&-C15 -> AS-27-13 | E15: Fuel & Lubricants | F15: Fuel & Lubricants - Fleet | I15: Administrative Services | J15: Carolina C. Tenedero | K15: Carolina C. Tenedero | L15: 80123102 | M15: 61111201 | R15: Admin Services
A16: =_xlfn.XLOOKUP(I16,Lookup!A:A,Lookup!B:B) -> AS | B16: 27 | C16: =C15+1 -> 14 | D16: =A16&-B16&-C16 -> AS-27-14 | E16: Fuel & Lubricants | F16: Fuel & Lubricants - Messenger | I16: Administrative Services | J16: Carolina C. Tenedero | K16: Carolina C. Tenedero | L16: 81123102 | M16: 52119101 | N16: Fuel Price per Liter, Average Daily Distance per Motor (km), Count of Motor | O16: ((Average Daily Distance km / 40km/L) x Fuel Price per Liter) x Count of Motor x 20 days per month | P16: Monthly | R16: Admin Services
A17: =_xlfn.XLOOKUP(I17,Lookup!A:A,Lookup!B:B) -> AS | B17: 27 | C17: =C16+1 -> 15 | D17: =A17&-B17&-C17 -> AS-27-15 | E17: Janitorial | F17: Janitorial | I17: Administrative Services | J17: Carolina C. Tenedero | K17: Carolina C. Tenedero | L17: 81123102 | M17: 52041405 | N17: Headcount, Rate per Month (w/ OT) | O17: Headcount x Rate per Month (w/ OT) | P17: Monthly | R17: Admin Services
A18: =_xlfn.XLOOKUP(I18,Lookup!A:A,Lookup!B:B) -> AS | B18: 27 | C18: =C17+1 -> 16 | D18: =A18&-B18&-C18 -> AS-27-16 | E18: Low Value Assets - HQ | F18: Kitchen Equipment | I18: Administrative Services | J18: Carolina C. Tenedero | K18: Carolina C. Tenedero | L18: 81123102 | M18: 52111102 | N18: Specify | Q18: e.g., plates, air fryer
A19: =_xlfn.XLOOKUP(I19,Lookup!A:A,Lookup!B:B) -> AS | B19: 27 | C19: =C18+1 -> 17 | D19: =A19&-B19&-C19 -> AS-27-17 | E19: Low Value Assets - HQ | F19: Office Equipment | I19: Administrative Services | J19: Carolina C. Tenedero | K19: Carolina C. Tenedero | L19: 81123102 | M19: 52111102 | N19: Specify | Q19: e.g., air purifier
A20: =_xlfn.XLOOKUP(I20,Lookup!A:A,Lookup!B:B) -> AS | B20: 27 | C20: =C19+1 -> 18 | D20: =A20&-B20&-C20 -> AS-27-18 | E20: LTO Registration | F20: LTO Registration | I20: Administrative Services | J20: Lino P. Arboleda | K20: Lino P. Arboleda | L20: 80123102 | M20: 61081101 | N20: No. of Vehicle, Registration Fee | O20: No. of Vehicle x Registration Fee | P20: July | R20: Admin Services
A21: =_xlfn.XLOOKUP(I21,Lookup!A:A,Lookup!B:B) -> AS | B21: 27 | C21: =C20+1 -> 19 | D21: =A21&-B21&-C21 -> AS-27-19 | E21: Office Supplies - HQ | F21: Others | I21: Administrative Services | J21: Carolina C. Tenedero | K21: Carolina C. Tenedero | L21: 81123102 | M21: 52111101 | N21: Specify
A22: =_xlfn.XLOOKUP(I22,Lookup!A:A,Lookup!B:B) -> AS | B22: 27 | C22: =C21+1 -> 20 | D22: =A22&-B22&-C22 -> AS-27-20 | E22: Office Supplies - HQ | F22: Toner/Ink | I22: Administrative Services | J22: Carolina C. Tenedero | K22: Carolina C. Tenedero | L22: 81123102 | M22: 52111101
A23: =_xlfn.XLOOKUP(I23,Lookup!A:A,Lookup!B:B) -> AS | B23: 27 | C23: =C22+1 -> 21 | D23: =A23&-B23&-C23 -> AS-27-21 | E23: Postal | F23: Postal | I23: Administrative Services | J23: Carolina C. Tenedero | K23: Carolina C. Tenedero | L23: 80123102 | M23: 61721103
A24: =_xlfn.XLOOKUP(I24,Lookup!A:A,Lookup!B:B) -> AS | B24: 27 | C24: =C23+1 -> 22 | D24: =A24&-B24&-C24 -> AS-27-22 | E24: Property Appraisal | F24: Property Appraisal | I24: Administrative Services | J24: Lino P. Arboleda | K24: Lino P. Arboleda | L24: 80123102 | M24: 61071099 | R24: Admin Services
A25: =_xlfn.XLOOKUP(I25,Lookup!A:A,Lookup!B:B) -> AS | B25: 27 | C25: =C24+1 -> 23 | D25: =A25&-B25&-C25 -> AS-27-23 | E25: Repairs & Maintenance - HQ | F25: Aircon Preventive Maintenance | I25: Administrative Services | J25: Carolina C. Tenedero | K25: Carolina C. Tenedero | L25: 81123102 | M25: 52061101
A26: =_xlfn.XLOOKUP(I26,Lookup!A:A,Lookup!B:B) -> AS | B26: 27 | C26: =C25+1 -> 24 | D26: =A26&-B26&-C26 -> AS-27-24 | E26: Repairs & Maintenance - HQ | F26: Building | I26: Administrative Services | J26: Carolina C. Tenedero | K26: Carolina C. Tenedero | L26: 81123102 | M26: 52061103 | N26: Specify
A27: =_xlfn.XLOOKUP(I27,Lookup!A:A,Lookup!B:B) -> AS | B27: 27 | C27: =C26+1 -> 25 | D27: =A27&-B27&-C27 -> AS-27-25 | E27: Repairs & Maintenance - HQ | F27: Cleaning Supplies | I27: Administrative Services | J27: Carolina C. Tenedero | K27: Carolina C. Tenedero | L27: 81123102 | M27: 52061111 | N27: Specify
A28: =_xlfn.XLOOKUP(I28,Lookup!A:A,Lookup!B:B) -> AS | B28: 27 | C28: =C27+1 -> 26 | D28: =A28&-B28&-C28 -> AS-27-26 | E28: Repairs & Maintenance - HQ | F28: Furniture, Fixture & Equipment | I28: Administrative Services | J28: Carolina C. Tenedero | K28: Carolina C. Tenedero | L28: 81123102 | M28: 52061101 | N28: Specify | Q28: e.g., carpet cleaning
A29: =_xlfn.XLOOKUP(I29,Lookup!A:A,Lookup!B:B) -> AS | B29: 27 | C29: =C28+1 -> 27 | D29: =A29&-B29&-C29 -> AS-27-27 | E29: Repairs & Maintenance - HQ | F29: Pest Control | I29: Administrative Services | J29: Carolina C. Tenedero | K29: Carolina C. Tenedero | L29: 80123102 | M29: 61061104
A30: =_xlfn.XLOOKUP(I30,Lookup!A:A,Lookup!B:B) -> AS | B30: 27 | C30: =C29+1 -> 28 | D30: =A30&-B30&-C30 -> AS-27-28 | E30: Repairs & Maintenance - HQ | F30: Vehicle | I30: Administrative Services | J30: Carolina C. Tenedero | K30: Carolina C. Tenedero | L30: 80123102 | M30: 61061104 | N30: No. of Vehicle, Allowed Limit of R&M per Month | O30: No. of Vehicle x Allowed Limit of R&M per Month | P30: Monthly
A31: =_xlfn.XLOOKUP(I31,Lookup!A:A,Lookup!B:B) -> AS | B31: 27 | C31: =C30+1 -> 29 | D31: =A31&-B31&-C31 -> AS-27-29 | E31: Security Services | F31: Security Services | I31: Administrative Services | J31: Carolina C. Tenedero | K31: Carolina C. Tenedero | L31: 81123102 | M31: 52041401 | N31: Headcount, Rate per Month (w/ OT) | O31: Headcount x Rate per Month (w/ OT) | P31: Monthly | R31: Admin Services
A32: =_xlfn.XLOOKUP(I32,Lookup!A:A,Lookup!B:B) -> AS | B32: 27 | C32: =C31+1 -> 30 | D32: =A32&-B32&-C32 -> AS-27-30 | E32: Transportation | F32: Parking Fees | I32: Administrative Services | J32: Carolina C. Tenedero | K32: Carolina C. Tenedero | L32: 81123102 | M32: 52081101 | R32: Admin Services
A33: =_xlfn.XLOOKUP(I33,Lookup!A:A,Lookup!B:B) -> AS | B33: 27 | C33: =C32+1 -> 31 | D33: =A33&-B33&-C33 -> AS-27-31 | E33: Transportation | F33: Toll Fees/RFID | I33: Administrative Services | J33: Carolina C. Tenedero | K33: Carolina C. Tenedero | L33: 81123102 | M33: 52081101 | R33: Admin Services
A34: =_xlfn.XLOOKUP(I34,Lookup!A:A,Lookup!B:B) -> AS | B34: 27 | C34: =C33+1 -> 32 | D34: =A34&-B34&-C34 -> AS-27-32 | E34: Transportation | F34: Vehicle Supplies | I34: Administrative Services | J34: Carolina C. Tenedero | K34: Carolina C. Tenedero | L34: 80123102 | M34: 61081101
A35: =_xlfn.XLOOKUP(I35,Lookup!A:A,Lookup!B:B) -> AS | B35: 27 | C35: =C34+1 -> 33 | D35: =A35&-B35&-C35 -> AS-27-33 | E35: Vehicle Insurance | F35: Vehicle Insurance | I35: Administrative Services | J35: Lino P. Arboleda | K35: Lino P. Arboleda | L35: 80123102 | M35: 61061104 | N35: No. of Vehicle, Allowed Limit of Insurance Anually | O35: No. of Vehicle x Allowed Limit of Insurance Anually | P35: July | R35: Admin Services
A36: =_xlfn.XLOOKUP(I36,Lookup!A:A,Lookup!B:B) -> BCA | B36: 27 | C36: =C35+1 -> 34 | D36: =A36&-B36&-C36 -> BCA-27-34 | E36: Dues and Fees | F36: Budget Reserve | I36: Budget, Controls & Analysis | J36: Princess Vera P. Jumalon | K36: Princess Vera P. Jumalon | L36: 80134103 | M36: 61711101
A37: =_xlfn.XLOOKUP(I37,Lookup!A:A,Lookup!B:B) -> BCA | B37: 27 | C37: =C36+1 -> 35 | D37: =A37&-B37&-C37 -> BCA-27-35 | E37: MTS | F37: MTS | I37: Budget, Controls & Analysis | J37: Princess Vera P. Jumalon | K37: Princess Vera P. Jumalon | L37: 80134103 | M37: 61901109
A38: =_xlfn.XLOOKUP(I38,Lookup!A:A,Lookup!B:B) -> BCA | B38: 27 | C38: =C37+1 -> 36 | D38: =A38&-B38&-C38 -> BCA-27-36 | E38: MTS | F38: MTS Recovery | I38: Budget, Controls & Analysis | J38: Princess Vera P. Jumalon | K38: Princess Vera P. Jumalon | L38: 81123102 | M38: 52041502
A39: =_xlfn.XLOOKUP(I39,Lookup!A:A,Lookup!B:B) -> BCA | B39: 27 | C39: =C38+1 -> 37 | D39: =A39&-B39&-C39 -> BCA-27-37 | E39: MTS | F39: MTS Recovery | I39: Budget, Controls & Analysis | J39: Princess Vera P. Jumalon | K39: Princess Vera P. Jumalon | L39: 80123102 | M39: 61961302
A40: =_xlfn.XLOOKUP(I40,Lookup!A:A,Lookup!B:B) -> BCA | B40: 27 | C40: =C39+1 -> 38 | D40: =A40&-B40&-C40 -> BCA-27-38 | E40: Performance Bonus | F40: Performance Bonus | G40: OCLP | I40: Budget, Controls & Analysis | J40: Princess Vera P. Jumalon | K40: Princess Vera P. Jumalon | L40: 80111101 | M40: 61021317
A41: =_xlfn.XLOOKUP(I41,Lookup!A:A,Lookup!B:B) -> BCA | B41: 27 | C41: =C40+1 -> 39 | D41: =A41&-B41&-C41 -> BCA-27-39 | E41: Performance Bonus | F41: Performance Bonus | G41: OCC | I41: Budget, Controls & Analysis | J41: Princess Vera P. Jumalon | K41: Princess Vera P. Jumalon | L41: 81111101 | M41: 52121316
A42: =_xlfn.XLOOKUP(I42,Lookup!A:A,Lookup!B:B) -> BCA | B42: 27 | C42: =C41+1 -> 40 | D42: =A42&-B42&-C42 -> BCA-27-40 | E42: Performance Bonus | F42: Performance Bonus | G42: OLC | I42: Budget, Controls & Analysis | J42: Princess Vera P. Jumalon | K42: Princess Vera P. Jumalon | L42: 90111101 | M42: 52121316
A43: =_xlfn.XLOOKUP(I43,Lookup!A:A,Lookup!B:B) -> BCA | B43: 27 | C43: 1 | D43: =A43&-B43&-C43 -> BCA-27-1 | E43: Research & Development | F43: CV Village | I43: Budget, Controls & Analysis | J43: Princess Vera P. Jumalon | K43: Princess Vera P. Jumalon | L43: 80349101 | M43: 61959994 | R43: Budget
A44: =_xlfn.XLOOKUP(I44,Lookup!A:A,Lookup!B:B) -> BCA | B44: 27 | C44: =C43+1 -> 2 | D44: =A44&-B44&-C44 -> BCA-27-2 | E44: Research & Development | F44: Calatagan | I44: Budget, Controls & Analysis | J44: Princess Vera P. Jumalon | K44: Princess Vera P. Jumalon | L44: 80349101 | M44: 61959994
A45: =_xlfn.XLOOKUP(I45,Lookup!A:A,Lookup!B:B) -> BCA | B45: 27 | C45: =C44+1 -> 3 | D45: =A45&-B45&-C45 -> BCA-27-3 | E45: Research & Development | F45: ES Expansion | I45: Budget, Controls & Analysis | J45: Princess Vera P. Jumalon | K45: Princess Vera P. Jumalon | L45: 81349101 | M45: 52959901 | R45: Budget
A46: =_xlfn.XLOOKUP(I46,Lookup!A:A,Lookup!B:B) -> BCA | B46: 27 | C46: =C45+1 -> 4 | D46: =A46&-B46&-C46 -> BCA-27-4 | E46: Research & Development | F46: GH Redev Plan | I46: Budget, Controls & Analysis | J46: Princess Vera P. Jumalon | K46: Princess Vera P. Jumalon | L46: 81349101 | M46: 52959901 | R46: Budget
A47: =_xlfn.XLOOKUP(I47,Lookup!A:A,Lookup!B:B) -> BCA | B47: 27 | C47: =C46+1 -> 5 | D47: =A47&-B47&-C47 -> BCA-27-5 | E47: Research & Development | F47: GH Resi Block | I47: Budget, Controls & Analysis | J47: Princess Vera P. Jumalon | K47: Princess Vera P. Jumalon | L47: 80349101 | M47: 61959994 | R47: Budget
A48: =_xlfn.XLOOKUP(I48,Lookup!A:A,Lookup!B:B) -> BCA | B48: 27 | C48: =C47+1 -> 6 | D48: =A48&-B48&-C48 -> BCA-27-6 | E48: Research & Development | F48: OE Redev Plan | I48: Budget, Controls & Analysis | J48: Princess Vera P. Jumalon | K48: Princess Vera P. Jumalon | L48: 81222101 | M48: 61959994 | R48: Budget
A49: =_xlfn.XLOOKUP(I49,Lookup!A:A,Lookup!B:B) -> BCA | B49: 27 | C49: =C48+1 -> 7 | D49: =A49&-B49&-C49 -> BCA-27-7 | E49: Research & Development | F49: OS2 | I49: Budget, Controls & Analysis | J49: Princess Vera P. Jumalon | K49: Princess Vera P. Jumalon | L49: 81349101 | M49: 52959901 | R49: Budget
A50: =_xlfn.XLOOKUP(I50,Lookup!A:A,Lookup!B:B) -> CF | B50: 27 | C50: 1 | D50: =A50&-B50&-C50 -> CF-27-1 | E50: Board of Directors (BOD) | F50: BOD Meeting Per Diem | I50: Corporate Finance | J50: Sharieanne A. Tabilin | K50: Andrea Romina C. Macasero, Maria Jennifer J. Almojuela | L50: 90134102 | M50: 52071103 | R50: Corporate Finance
A51: =_xlfn.XLOOKUP(I51,Lookup!A:A,Lookup!B:B) -> CF | B51: 27 | C51: =C50+1 -> 2 | D51: =A51&-B51&-C51 -> CF-27-2 | E51: Board of Directors (BOD) | F51: BOD Meeting Retainer | I51: Corporate Finance | J51: Sharieanne A. Tabilin | K51: Andrea Romina C. Macasero, Maria Jennifer J. Almojuela | L51: 90134102 | M51: 52091103 | R51: Corporate Finance
A52: =_xlfn.XLOOKUP(I52,Lookup!A:A,Lookup!B:B) -> CF | B52: 27 | C52: =C51+1 -> 3 | D52: =A52&-B52&-C52 -> CF-27-3 | E52: Contracted Services | F52: OFI Outsource - BDO CMC | G52: OLC | I52: Corporate Finance | J52: Sharieanne A. Tabilin | K52: Andrea Romina C. Macasero, Maria Jennifer J. Almojuela | L52: 90111101 | M52: 52041495 | R52: Corporate Finance
A53: =_xlfn.XLOOKUP(I53,Lookup!A:A,Lookup!B:B) -> CF | B53: 27 | C53: =C52+1 -> 4 | D53: =A53&-B53&-C53 -> CF-27-4 | E53: Dues and Fees | F53: SEC Filing Fee | G53: OCC | I53: Corporate Finance | J53: Sharieanne A. Tabilin | K53: Andrea Romina C. Macasero, Maria Jennifer J. Almojuela | L53: 81134102 | M53: 52952101
A54: =_xlfn.XLOOKUP(I54,Lookup!A:A,Lookup!B:B) -> CF | B54: 27 | C54: =C53+1 -> 5 | D54: =A54&-B54&-C54 -> CF-27-5 | E54: Dues and Fees | F54: SEC Filing Fee | G54: OLC | I54: Corporate Finance | J54: Sharieanne A. Tabilin | K54: Andrea Romina C. Macasero, Maria Jennifer J. Almojuela | L54: 90134102 | M54: 52952101
A55: =_xlfn.XLOOKUP(I55,Lookup!A:A,Lookup!B:B) -> CF | B55: 27 | C55: =C54+1 -> 6 | D55: =A55&-B55&-C55 -> CF-27-6 | E55: External Consultants | F55: FS Audit - PWC | G55: OCLP | I55: Corporate Finance | J55: Sharieanne A. Tabilin | K55: Andrea Romina C. Macasero, Maria Jennifer J. Almojuela | L55: 80134102 | M55: 61071001 | R55: Corporate Finance
A56: =_xlfn.XLOOKUP(I56,Lookup!A:A,Lookup!B:B) -> CF | B56: 27 | C56: =C55+1 -> 7 | D56: =A56&-B56&-C56 -> CF-27-7 | E56: External Consultants | F56: FS Audit - PWC | G56: OCC | I56: Corporate Finance | J56: Sharieanne A. Tabilin | K56: Andrea Romina C. Macasero, Maria Jennifer J. Almojuela | L56: 81134102 | M56: 61071001 | R56: Corporate Finance
A57: =_xlfn.XLOOKUP(I57,Lookup!A:A,Lookup!B:B) -> CF | B57: 27 | C57: =C56+1 -> 8 | D57: =A57&-B57&-C57 -> CF-27-8 | E57: External Consultants | F57: FS Audit - PWC | G57: OLC | I57: Corporate Finance | J57: Sharieanne A. Tabilin | K57: Andrea Romina C. Macasero, Maria Jennifer J. Almojuela | L57: 90134102 | M57: 61071001 | R57: Corporate Finance
A58: =_xlfn.XLOOKUP(I58,Lookup!A:A,Lookup!B:B) -> CF | B58: 27 | C58: =C57+1 -> 9 | D58: =A58&-B58&-C58 -> CF-27-9 | E58: External Consultants | F58: FS Audit OPE - PWC | G58: OCLP | I58: Corporate Finance | J58: Sharieanne A. Tabilin | K58: Andrea Romina C. Macasero, Maria Jennifer J. Almojuela | L58: 80134102 | M58: 61071006 | R58: Corporate Finance
A59: =_xlfn.XLOOKUP(I59,Lookup!A:A,Lookup!B:B) -> CF | B59: 27 | C59: =C58+1 -> 10 | D59: =A59&-B59&-C59 -> CF-27-10 | E59: External Consultants | F59: FS Audit OPE - PWC | G59: OCC | I59: Corporate Finance | J59: Sharieanne A. Tabilin | K59: Andrea Romina C. Macasero, Maria Jennifer J. Almojuela | L59: 81134102 | M59: 61071006 | R59: Corporate Finance
A60: =_xlfn.XLOOKUP(I60,Lookup!A:A,Lookup!B:B) -> CF | B60: 27 | C60: =C59+1 -> 11 | D60: =A60&-B60&-C60 -> CF-27-11 | E60: External Consultants | F60: FS Audit OPE - PWC | G60: OLC | I60: Corporate Finance | J60: Sharieanne A. Tabilin | K60: Andrea Romina C. Macasero, Maria Jennifer J. Almojuela | L60: 90134102 | M60: 61071006 | R60: Corporate Finance
A61: =_xlfn.XLOOKUP(I61,Lookup!A:A,Lookup!B:B) -> CF | B61: 27 | C61: =C60+1 -> 12 | D61: =A61&-B61&-C61 -> CF-27-12 | E61: External Consultants | F61: Transfer Pricing Documentation (TPD) - SGV | G61: OLC | I61: Corporate Finance | J61: Sharieanne A. Tabilin | K61: Andrea Romina C. Macasero, Maria Jennifer J. Almojuela | L61: 90134102 | M61: 52071104 | R61: Corporate Finance
A62: =_xlfn.XLOOKUP(I62,Lookup!A:A,Lookup!B:B) -> CF | B62: 27 | C62: =C61+1 -> 13 | D62: =A62&-B62&-C62 -> CF-27-13 | E62: External Consultants | F62: Transfer Pricing Documentation (TPD) - SGV | G62: OCLP | I62: Corporate Finance | J62: Sharieanne A. Tabilin | K62: Andrea Romina C. Macasero, Maria Jennifer J. Almojuela | L62: 80134102 | M62: 61071001
A63: =_xlfn.XLOOKUP(I63,Lookup!A:A,Lookup!B:B) -> CF | B63: 27 | C63: =C62+1 -> 14 | D63: =A63&-B63&-C63 -> CF-27-14 | E63: Insurance | F63: Bond | I63: Corporate Finance | J63: Sharieanne A. Tabilin | K63: Andrea Romina C. Macasero, Maria Jennifer J. Almojuela | L63: 90111101 | M63: 61101106 | R63: Corporate Finance
A64: =_xlfn.XLOOKUP(I64,Lookup!A:A,Lookup!B:B) -> CF | B64: 27 | C64: =C63+1 -> 15 | D64: =A64&-B64&-C64 -> CF-27-15 | E64: Insurance | F64: DOL | I64: Corporate Finance | J64: Sharieanne A. Tabilin | K64: Andrea Romina C. Macasero, Maria Jennifer J. Almojuela | L64: 90111101 | M64: 52101107 | R64: Corporate Finance
A65: =_xlfn.XLOOKUP(I65,Lookup!A:A,Lookup!B:B) -> CF | B65: 27 | C65: =C64+1 -> 16 | D65: =A65&-B65&-C65 -> CF-27-16 | E65: Insurance | F65: PARI | G65: OCLP | I65: Corporate Finance | J65: Sharieanne A. Tabilin | K65: Andrea Romina C. Macasero, Maria Jennifer J. Almojuela | L65: 80111101 | M65: 52101101 | R65: Corporate Finance
A66: =_xlfn.XLOOKUP(I66,Lookup!A:A,Lookup!B:B) -> CF | B66: 27 | C66: =C65+1 -> 17 | D66: =A66&-B66&-C66 -> CF-27-17 | E66: Insurance | F66: PARI | G66: OCC | I66: Corporate Finance | J66: Sharieanne A. Tabilin | K66: Andrea Romina C. Macasero, Maria Jennifer J. Almojuela | L66: 81111101 | M66: 52101101 | R66: Corporate Finance
A67: =_xlfn.XLOOKUP(I67,Lookup!A:A,Lookup!B:B) -> CF | B67: 27 | C67: =C66+1 -> 18 | D67: =A67&-B67&-C67 -> CF-27-18 | E67: Insurance | F67: PTS | G67: OCLP | I67: Corporate Finance | J67: Sharieanne A. Tabilin | K67: Andrea Romina C. Macasero, Maria Jennifer J. Almojuela | L67: 80111101 | M67: 52101105 | R67: Corporate Finance
A68: =_xlfn.XLOOKUP(I68,Lookup!A:A,Lookup!B:B) -> CF | B68: 27 | C68: =C67+1 -> 19 | D68: =A68&-B68&-C68 -> CF-27-19 | E68: Insurance | F68: PTS | G68: OCC | I68: Corporate Finance | J68: Sharieanne A. Tabilin | K68: Andrea Romina C. Macasero, Maria Jennifer J. Almojuela | L68: 81111101 | M68: 52101105 | R68: Corporate Finance
A69: =_xlfn.XLOOKUP(I69,Lookup!A:A,Lookup!B:B) -> CF | B69: 27 | C69: =C68+1 -> 20 | D69: =A69&-B69&-C69 -> CF-27-20 | E69: Interest & Penalty | F69: Interest | I69: Corporate Finance | J69: Sharieanne A. Tabilin | K69: Andrea Romina C. Macasero, Maria Jennifer J. Almojuela | L69: 81111101 | M69: 61959202 | R69: Corporate Finance
A70: =_xlfn.XLOOKUP(I70,Lookup!A:A,Lookup!B:B) -> CF | B70: 27 | C70: =C69+1 -> 21 | D70: =A70&-B70&-C70 -> CF-27-21 | E70: Interest & Penalty | F70: Penalty | I70: Corporate Finance | J70: Sharieanne A. Tabilin | K70: Andrea Romina C. Macasero, Maria Jennifer J. Almojuela | L70: 81111101 | M70: 61959202 | R70: Corporate Finance
A71: =_xlfn.XLOOKUP(I71,Lookup!A:A,Lookup!B:B) -> CF | B71: 27 | C71: =C70+1 -> 22 | D71: =A71&-B71&-C71 -> CF-27-22 | E71: Manpower | F71: Retirement | G71: OCLP | I71: Corporate Finance | J71: Sharieanne A. Tabilin | K71: Andrea Romina C. Macasero, Maria Jennifer J. Almojuela | L71: 80111101 | M71: 61021304 | R71: Corporate Finance
A72: =_xlfn.XLOOKUP(I72,Lookup!A:A,Lookup!B:B) -> CF | B72: 27 | C72: =C71+1 -> 23 | D72: =A72&-B72&-C72 -> CF-27-23 | E72: Manpower | F72: Retirement | G72: OCC | I72: Corporate Finance | J72: Sharieanne A. Tabilin | K72: Andrea Romina C. Macasero, Maria Jennifer J. Almojuela | L72: 81111101 | M72: 52121304 | R72: Corporate Finance
A73: =_xlfn.XLOOKUP(I73,Lookup!A:A,Lookup!B:B) -> CF | B73: 27 | C73: =C72+1 -> 24 | D73: =A73&-B73&-C73 -> CF-27-24 | E73: Manpower | F73: Retirement | G73: OLC | I73: Corporate Finance | J73: Sharieanne A. Tabilin | K73: Andrea Romina C. Macasero, Maria Jennifer J. Almojuela | L73: 90111101 | M73: 52121304 | R73: Corporate Finance
A74: =_xlfn.XLOOKUP(I74,Lookup!A:A,Lookup!B:B) -> CF | B74: 27 | C74: =C73+1 -> 25 | D74: =A74&-B74&-C74 -> CF-27-25 | E74: Professional Fees | F74: Systems Cost - SM | I74: Corporate Finance | J74: Sharieanne A. Tabilin | K74: Andrea Romina C. Macasero, Maria Jennifer J. Almojuela | L74: 90134102 | M74: 52041494
A75: =_xlfn.XLOOKUP(I75,Lookup!A:A,Lookup!B:B) -> CF | B75: 27 | C75: =C74+1 -> 26 | D75: =A75&-B75&-C75 -> CF-27-26 | E75: Professional Fees | F75: System Costs - ALI | I75: Corporate Finance | J75: Sharieanne A. Tabilin | K75: Andrea Romina C. Macasero, Maria Jennifer J. Almojuela | L75: 90134102 | M75: 52041494
A76: =_xlfn.XLOOKUP(I76,Lookup!A:A,Lookup!B:B) -> CF | B76: 27 | C76: =C75+1 -> 27 | D76: =A76&-B76&-C76 -> CF-27-27 | E76: Taxes & Licenses | F76: DST for Equity Infusion | G76: OCC | I76: Corporate Finance | J76: Sharieanne A. Tabilin | K76: Andrea Romina C. Macasero, Maria Jennifer J. Almojuela | L76: 81134102 | M76: 52031103 | R76: Corporate Finance
A77: =_xlfn.XLOOKUP(I77,Lookup!A:A,Lookup!B:B) -> CF | B77: 27 | C77: =C76+1 -> 28 | D77: =A77&-B77&-C77 -> CF-27-28 | E77: Valle Verde | F77: Consumables | I77: Corporate Finance | J77: Sharieanne A. Tabilin | K77: Andrea Romina C. Macasero, Maria Jennifer J. Almojuela | L77: 80134102 | M77: 61711101 | R77: Corporate Finance
A78: =_xlfn.XLOOKUP(I78,Lookup!A:A,Lookup!B:B) -> CF | B78: 27 | C78: =C77+1 -> 29 | D78: =A78&-B78&-C78 -> CF-27-29 | E78: Valle Verde | F78: Membership Dues | I78: Corporate Finance | J78: Sharieanne A. Tabilin | K78: Andrea Romina C. Macasero, Maria Jennifer J. Almojuela | L78: 80134102 | M78: 61711101 | R78: Corporate Finance
A79: =_xlfn.XLOOKUP(I79,Lookup!A:A,Lookup!B:B) -> CF | B79: 27 | C79: =C78+1 -> 30 | D79: =A79&-B79&-C79 -> CF-27-30 | E79: Valle Verde | F79: OPE | I79: Corporate Finance | J79: Sharieanne A. Tabilin | K79: Andrea Romina C. Macasero, Maria Jennifer J. Almojuela | L79: 80134102 | M79: 61711101 | R79: Corporate Finance
A80: =_xlfn.XLOOKUP(I80,Lookup!A:A,Lookup!B:B) -> CF | B80: 27 | C80: =C79+1 -> 31 | D80: =A80&-B80&-C80 -> CF-27-31 | E80: Valle Verde | F80: Special Assessment | I80: Corporate Finance | J80: Sharieanne A. Tabilin | K80: Andrea Romina C. Macasero, Maria Jennifer J. Almojuela | L80: 80134102 | M80: 61711101
A81: =_xlfn.XLOOKUP(I81,Lookup!A:A,Lookup!B:B) -> CM | B81: 27 | C81: 1 | D81: =A81&-B81&-C81 -> CM-27-1 | E81: Communications Branding | F81: Media Monitoring Services | I81: Corporate Marketing | J81: Justine Bianca B. Lagman | K81: Janeena Arielle Marie M. Lansangan | L81: 81314101 | M81: 52551201 | R81: Corporate Marketing
A82: =_xlfn.XLOOKUP(I82,Lookup!A:A,Lookup!B:B) -> CM | B82: 27 | C82: =C81+1 -> 2 | D82: =A82&-B82&-C82 -> CM-27-2 | E82: Communications Branding | F82: PR Retainer Fee | I82: Corporate Marketing | J82: Justine Bianca B. Lagman | K82: Janeena Arielle Marie M. Lansangan | L82: 81314101 | M82: 52551201 | R82: Corporate Marketing
A83: =_xlfn.XLOOKUP(I83,Lookup!A:A,Lookup!B:B) -> CM | B83: 27 | C83: =C82+1 -> 3 | D83: =A83&-B83&-C83 -> CM-27-3 | E83: Communications Branding | F83: Social Listening Services | I83: Corporate Marketing | J83: Justine Bianca B. Lagman | K83: Janeena Arielle Marie M. Lansangan | L83: 81314101 | M83: 52551201 | R83: Corporate Marketing
A84: =_xlfn.XLOOKUP(I84,Lookup!A:A,Lookup!B:B) -> CM | B84: 27 | C84: =C83+1 -> 4 | D84: =A84&-B84&-C84 -> CM-27-4 | E84: Marketing Events | F84: 95th Campaign | I84: Corporate Marketing | J84: Justine Bianca B. Lagman | K84: Janeena Arielle Marie M. Lansangan | L84: 81314101 | M84: 52551201 | R84: Corporate Marketing
A85: =_xlfn.XLOOKUP(I85,Lookup!A:A,Lookup!B:B) -> CM | B85: 27 | C85: =C84+1 -> 5 | D85: =A85&-B85&-C85 -> CM-27-5 | E85: Marketing Events | F85: Christmas Décor | I85: Corporate Marketing | J85: Justine Bianca B. Lagman | K85: Janeena Arielle Marie M. Lansangan | L85: 81314101 | M85: 52551201 | R85: Corporate Marketing
A86: =_xlfn.XLOOKUP(I86,Lookup!A:A,Lookup!B:B) -> CM | B86: 27 | C86: =C85+1 -> 6 | D86: =A86&-B86&-C86 -> CM-27-6 | E86: Marketing Events | F86: Townhall | I86: Corporate Marketing | J86: Justine Bianca B. Lagman | K86: Janeena Arielle Marie M. Lansangan | L86: 81314101 | M86: 52551201 | R86: Corporate Marketing
A87: =_xlfn.XLOOKUP(I87,Lookup!A:A,Lookup!B:B) -> CM | B87: 27 | C87: =C86+1 -> 7 | D87: =A87&-B87&-C87 -> CM-27-7 | E87: Marketing Subscriptions | F87: AI Pollo | I87: Corporate Marketing | J87: Justine Bianca B. Lagman | K87: Janeena Arielle Marie M. Lansangan | L87: 81314101 | M87: 52551201 | R87: Corporate Marketing
A88: =_xlfn.XLOOKUP(I88,Lookup!A:A,Lookup!B:B) -> CM | B88: 27 | C88: =C87+1 -> 8 | D88: =A88&-B88&-C88 -> CM-27-8 | E88: Marketing Subscriptions | F88: Capcut | I88: Corporate Marketing | J88: Justine Bianca B. Lagman | K88: Janeena Arielle Marie M. Lansangan | L88: 81314101 | M88: 52551201 | R88: Corporate Marketing
A89: =_xlfn.XLOOKUP(I89,Lookup!A:A,Lookup!B:B) -> CM | B89: 27 | C89: =C88+1 -> 9 | D89: =A89&-B89&-C89 -> CM-27-9 | E89: Marketing Subscriptions | F89: Meta | I89: Corporate Marketing | J89: Justine Bianca B. Lagman | K89: Janeena Arielle Marie M. Lansangan | L89: 81314101 | M89: 52551201 | R89: Corporate Marketing
A90: =_xlfn.XLOOKUP(I90,Lookup!A:A,Lookup!B:B) -> EA | B90: 27 | C90: 1 | D90: =A90&-B90&-C90 -> EA-27-1 | E90: Donations & Contributions | F90: Community Contributions | G90: OCLP | I90: External Affairs | J90: John Carmelo L. Ledesma | K90: Elias Isagani A. Elacio | L90: 80125101 | M90: 61959102
A91: =_xlfn.XLOOKUP(I91,Lookup!A:A,Lookup!B:B) -> EA | B91: 27 | C91: =C90+1 -> 2 | D91: =A91&-B91&-C91 -> EA-27-2 | E91: Donations & Contributions | F91: Community Contributions | G91: OCC | I91: External Affairs | J91: John Carmelo L. Ledesma | K91: Elias Isagani A. Elacio | L91: 81125101 | M91: 52959903
A92: =_xlfn.XLOOKUP(I92,Lookup!A:A,Lookup!B:B) -> EA | B92: 27 | C92: =C91+1 -> 3 | D92: =A92&-B92&-C92 -> EA-27-3 | E92: Donations & Contributions | F92: Community Contributions | G92: OLC | I92: External Affairs | J92: John Carmelo L. Ledesma | K92: Elias Isagani A. Elacio | L92: 90125101 | M92: 61959102
A93: =_xlfn.XLOOKUP(I93,Lookup!A:A,Lookup!B:B) -> EA | B93: 27 | C93: =C92+1 -> 4 | D93: =A93&-B93&-C93 -> EA-27-4 | E93: Donations & Contributions | F93: Valle Verde Country Club Annual Employees' Christmas Fund Contribution | I93: External Affairs | J93: John Carmelo L. Ledesma | K93: Elias Isagani A. Elacio | L93: 80125101 | M93: 61959102 | R93: External Affairs
A94: =_xlfn.XLOOKUP(I94,Lookup!A:A,Lookup!B:B) -> EA | B94: 27 | C94: =C93+1 -> 5 | D94: =A94&-B94&-C94 -> EA-27-5 | E94: Representation | F94: Representation Expense | G94: OCLP | I94: External Affairs | J94: John Carmelo L. Ledesma | K94: Elias Isagani A. Elacio | L94: 80125101 | M94: 61091101
A95: =_xlfn.XLOOKUP(I95,Lookup!A:A,Lookup!B:B) -> EA | B95: 27 | C95: =C94+1 -> 6 | D95: =A95&-B95&-C95 -> EA-27-6 | E95: Representation | F95: Representation Expense | G95: OCC | I95: External Affairs | J95: John Carmelo L. Ledesma | K95: Elias Isagani A. Elacio | L95: 81125101 | M95: 52091101
A96: =_xlfn.XLOOKUP(I96,Lookup!A:A,Lookup!B:B) -> EA | B96: 27 | C96: =C95+1 -> 7 | D96: =A96&-B96&-C96 -> EA-27-7 | E96: Representation | F96: Representation Expense | G96: OLC | I96: External Affairs | J96: John Carmelo L. Ledesma | K96: Elias Isagani A. Elacio | L96: 90125101 | M96: 61091101
A97: =_xlfn.XLOOKUP(I97,Lookup!A:A,Lookup!B:B) -> HR | B97: 27 | C97: 1 | D97: =A97&-B97&-C97 -> HR-27-1 | E97: Company Events | F97: Anniversary Breakfast | I97: Human Resources | J97: Daisy Abendanio, Albertine Ellen R. Jimenez | K97: Marybeth G. Monis | L97: 81122101 | M97: 52121401 | R97: Human Resources
A98: =_xlfn.XLOOKUP(I98,Lookup!A:A,Lookup!B:B) -> HR | B98: 27 | C98: =C97+1 -> 2 | D98: =A98&-B98&-C98 -> HR-27-2 | E98: Company Events | F98: Blue Friday | I98: Human Resources | J98: Daisy Abendanio, Albertine Ellen R. Jimenez | K98: Marybeth G. Monis | L98: 81122101 | M98: 52121401 | R98: Human Resources
A99: =_xlfn.XLOOKUP(I99,Lookup!A:A,Lookup!B:B) -> HR | B99: 27 | C99: =C98+1 -> 3 | D99: =A99&-B99&-C99 -> HR-27-3 | E99: Company Events | F99: Chinese New Year | I99: Human Resources | J99: Daisy Abendanio, Albertine Ellen R. Jimenez | K99: Marybeth G. Monis | L99: 81122101 | M99: 52121401 | R99: Human Resources
A100: =_xlfn.XLOOKUP(I100,Lookup!A:A,Lookup!B:B) -> HR | B100: 27 | C100: =C99+1 -> 4 | D100: =A100&-B100&-C100 -> HR-27-4 | E100: Company Events | F100: Christmas Party | I100: Human Resources | J100: Daisy Abendanio, Albertine Ellen R. Jimenez | K100: Marybeth G. Monis | L100: 81122101 | M100: 52121401 | R100: Human Resources
...

Sheet Lookup
A2: Administrative Services | B2: AS
A3: Corporate Finance | B3: CF
A4: External Affairs | B4: EA
A5: Human Resources | B5: HR
A6: Information System & Information Technology | B6: IT
A7: Legal | B7: LG
A8: Office of the CFO | B8: CF
A9: Tax | B9: TX
A10: Budget, Controls & Analysis | B10: BCA
A11: Corporate Marketing | B11: CM
A12: OMD Operations | B12: OM
A13: Procurement | B13: PR
A14: TECHNICAL SERVICES | B14: TS

Sheet Sheet2
A1: Department | B1: Admin
A2: GL number | B2: GL description | C2: Rule | D2: Full year 2025 | E2: YTD September 2026 | F2: October-December 2026 Forecast | G2: Full Year 2026 | H2: Average Monthly 2026 | I2: Full year 2027
A3: 52041499 | B3: Admin Staff - Driver/Messenger | C3: Headcount, Rate per day, no of days
A4: 52041499 | B4: Admin Staff - Driver/Messenger | C4: Headcount, Rate per day, no of days
A5: 52081103 | B5: Drivers' Meal Allowance | C5: Headcount, fixed rate
A6: 61711101 | B6: Dues and Fees - Others | C6: Dropdown selection: membership (specify), others (specify)
A7: 61041101 | B7: Electricity & Water | C7: Based on PY average, consider increase in meralco etc
A8: 52119101 | B8: Fuel & Lubricants - Messenger | C8: No of trips per day, no of days, no of messenger, based on PY average, consider increase in fuel
A9: 61111201 | B9: Fuel & Lubricants - Shell Fleet | C9: Based on PY average, consider increase in fuel
A10: 52041405 | B10: Janitorial | C10: Headcount, Rate per day, no of days
A11: 52111102 | B11: Low Value Assets
A12: 61081101 | B12: LTO Registration
A13: 52951101 | B13: Mobile Phone
A14: 52111101 | B14: Office Supplies - Toner
A15: 52081101 | B15: Parking Fees
A16: 61071099 | B16: Property Valuation
A17: 61061104 | B17: Repairs & Maintenance - Vehicle
A18: 52061103 | B18: Repairs & Maintenance - Building
A19: 52061101 | B19: Repairs & Maintenance - Furniture, Fixture & Equipment
A20: 52061111 | B20: Repairs & Maintenance - Supplies
A21: 52041401 | B21: Security | C21: Headcount, Rate per day, no of days
A22: 52081101 | B22: Parking Fees
A23: 52081101 | B23: Parking Fees
A24: 61721101 | B24: Trunk Line/Direct Line/Land Line
A25: 61061104 | B25: Repairs & Maintenance - Vehicle
